chosen_pyc: semantic_routing/__pycache__/baseline.cpython-310.pyc.2207508733360

================================================================================
_v7_generalization_profile firstlineno=988
--------------------------------------------------------------------------------
 991           0 BUILD_MAP                0

 992           2 LOAD_CONST               1 ('missing_scope')
               4 LOAD_GLOBAL              0 (_any_regex_evidence)

 993           6 LOAD_FAST                0 (text)

 994           8 LOAD_CONST               2 ('v7_missing_scope')

 995          10 LOAD_CONST               3 (('\\b(?:required columns?|usage volume|jurisdiction|country|service tier|audience|cluster|tenant|environment|data|scope)\\b[^.?!]*(?:missing|not provided|not stated|not specified|unknown)', '\\bask what data is missing\\b', '\\bthe country is not specified\\b', '\\bthe jurisdiction is missing\\b', '\\bthe service tier is not stated\\b', '\\brequired columns are missing\\b', '(?:対象|対象DB|DB|対象サービス|サービス|対象ユーザー層|ログ|状況説明)[^。]*?(?:未定|未指定|分かりません|ありません)', '回答前に[^。]*確認', '先に確認'))

 992          12 CALL_FUNCTION            3

 991          14 MAP_ADD                  1

1007          16 LOAD_CONST               4 ('ask_first')
              18 LOAD_GLOBAL              0 (_any_regex_evidence)

1008          20 LOAD_FAST                0 (text)

1009          22 LOAD_CONST               5 ('v7_ask_first')

1010          24 LOAD_CONST               6 (('\\bask (?:which|what|who|whether)\\b', '\\bbefore (?:drafting|writing|creating|answering)[^.?!]*\\bask\\b', '\\bask [^.?!]* first\\b', '\\bafter asking which\\b', '回答前に[^。]*確認', '先に確認'))

1007          26 CALL_FUNCTION            3

 991          28 MAP_ADD                  1

1019          30 LOAD_CONST               7 ('current_lookup')
              32 LOAD_GLOBAL              0 (_any_regex_evidence)

1020          34 LOAD_FAST                0 (text)

1021          36 LOAD_CONST               8 ('v7_current_lookup')

1022          38 LOAD_CONST               9 (('\\blatest stable\\b', '\\blatest [^.?!]*(?:cite|sources?|official|release|version)', '\\bcurrent [^.?!]*(?:version|release|legality|legal|contract)', '\\bstill (?:true|documented|recommended|valid)\\b', '\\btoday[^.?!]*(?:cite|sources?|version|release)', '今日時点[^。]*公式', '現在の法律', '公式リリース情報'))

1019          40 CALL_FUNCTION            3

 991          42 MAP_ADD                  1

1033          44 LOAD_CONST              10 ('local_current_blocker')
              46 LOAD_GLOBAL              0 (_any_regex_evidence)

1034          48 LOAD_FAST                0 (text)

1035          50 LOAD_CONST              11 ('v7_local_current_blocker')

1036          52 LOAD_CONST              12 (('\\bcolumn name\\b', '\\bterm latest_[A-Za-z0-9_]+\\b', '\\blabel latest_[A-Za-z0-9_]+\\b', '\\blocal tracking table\\b', '\\u4f5c\\u696d\\u30d5\\u30a9\\u30eb\\u30c0', '作業フォルダ', 'Web検索は不要', 'Web\\u691c\\u7d22\\u306f\\u4e0d\\u8981'))

1033          54 CALL_FUNCTION            3

 991          56 MAP_ADD                  1

1047          58 LOAD_CONST              13 ('source_lookup')
              60 LOAD_GLOBAL              0 (_any_regex_evidence)

1048          62 LOAD_FAST                0 (text)

1049          64 LOAD_CONST              14 ('v7_source_lookup')

1050          66 LOAD_CONST              15 (('\\bcite (?:official )?sources?\\b', '\\bwith sources\\b', '\\buse sources\\b', '\\bofficial sources\\b', '\\bofficial release\\b', '\\bwith citations\\b', '\\bcitations\\b', '公式リリース情報'))

1047          68 CALL_FUNCTION            3

 991          70 MAP_ADD                  1

1061          72 LOAD_CONST              16 ('unverified_claim')
              74 LOAD_GLOBAL              0 (_any_regex_evidence)

1062          76 LOAD_FAST                0 (text)

1063          78 LOAD_CONST              17 ('v7_unverified_claim')

1064          80 LOAD_CONST              18 (('\\bconfig checksum\\b', '\\bcheck the assumptions[^.?!]*\\bthen draft\\b', '\\b\\d+\\s*[*x]\\s*\\d+\\s+equals\\s+\\d+\\b', '\\bburn rate from \\d+/\\d+\\b', '\\bi heard this (?:number|figure|value) is correct\\b', '\\b(?:number|figure|value) is correct[^.?!]*\\bbefore\\b[^.?!]*\\breport\\b', '\\bdo not assume it is true\\b', '議論ログ.*検証してから', '必ず安全.*言われました', '\\b(?:medical dosage advice|medical advice) is safe\\b', '\\bpatch fixed the vulnerability\\b', '\\bvalidate the inputs\\b', '\\bsupposedly\\b'))

1061          82 CALL_FUNCTION            3

 991          84 MAP_ADD                  1

1080          86 LOAD_CONST              19 ('multiple_sequence')
              88 LOAD_GLOBAL              0 (_any_regex_evidence)

1081          90 LOAD_FAST                0 (text)

1082          92 LOAD_CONST              20 ('v7_multiple_sequence')

1083          94 LOAD_CONST              21 (('\\bbrainstorm[^.?!]*\\bcompare\\b', '\\bexplore alternatives for [^.?!]*\\bcompare\\b', '\\bask what data is missing[^.?!]*\\bthen calculate\\b', '\\bcheck the assumptions[^.?!]*\\bthen draft\\b', '\\bsummarize[^.?!]*\\bcreate\\b', '\\bverify the claim[^.?!]*\\bthen write\\b', '\\bvalidate the inputs[^.?!]*\\bcreate[^.?!]*\\bplan\\b', '\\bconfig checksum[^.?!]*\\bthen update\\b', '\\bfirst,? then create\\b', '\\bcompare[^.?!]*\\bmake[^.?!]*\\btable\\b', '\\bsummarize first[^.?!]*\\bthen compare\\b', '\\bif there are multiple\\b', 'してから[^。]*(?:比較|作|書|答|要約)', '複数[^。]*比較', 'それぞれ[^。]*比較'))

1080          96 CALL_FUNCTION            3

 991          98 MAP_ADD                  1

1101         100 LOAD_CONST              22 ('terminal_build')
             102 LOAD_GLOBAL              0 (_any_regex_evidence)

1102         104 LOAD_FAST                0 (text)

1103         106 LOAD_CONST              23 ('v7_terminal_build')

1104         108 LOAD_CONST              24 (('\\bdraft(?:ing)? the\\b', '\\bwrite(?:ing)? the\\b', '\\bcreate (?:a |an )?[^.?!]*(?:template|checklist|policy|plan|email|runbook|commands?|note)\\b', '\\bbefore (?:writing|drafting)\\b[^.?!]*(?:runbook|commands?)\\b', '\\bupdate the note\\b', '\\bmake (?:this|the|an?|earlier|previous) [^.?!]*(?:sentence|proposal|text)[^.?!]*(?:short|shorter|businesslike|better)\\b', '\\bmake [^.?!]*(?:short|shorter|businesslike|better)\\b', '\\bmake a pros/cons table\\b', '\\bend with a comparison table\\b', '\\bcomparison table\\b', '\\buse the word [A-Za-z0-9_]+ as a UI label\\b', '\\badd the label [A-Za-z0-9_]+\\b', '(?:計画|手順|表|案|チェックリスト)[^。]*(?:作|書|追加)'))

1101         110 CALL_FUNCTION            3

 991         112 MAP_ADD                  1

1120         114 LOAD_CONST              25 ('terminal_summary')
             116 LOAD_GLOBAL              0 (_any_regex_evidence)

1121         118 LOAD_FAST                0 (text)

1122         120 LOAD_CONST              26 ('v7_terminal_summary')

1123         122 LOAD_CONST              27 (('\\bsummarize\\b', '要約'))

1120         124 CALL_FUNCTION            3

 991         126 MAP_ADD                  1

1128         128 LOAD_CONST              28 ('force_explore')
             130 LOAD_GLOBAL              0 (_any_regex_evidence)

1129         132 LOAD_FAST                0 (text)

1130         134 LOAD_CONST              29 ('v7_force_explore')

1131         136 LOAD_CONST              30 (('\\bdiscuss future [^.?!]*scenarios\\b', '\\bbrainstorm[^.?!]*compare\\b', '\\bexplore alternatives\\b', '改善案を比較', '複数[^。]*(?:ルート|案)[^。]*比較'))

1128         138 CALL_FUNCTION            3

 991         140 MAP_ADD                  1

1139         142 LOAD_CONST              31 ('force_build')
             144 LOAD_GLOBAL              0 (_any_regex_evidence)

1140         146 LOAD_FAST                0 (text)

1141         148 LOAD_CONST              32 ('v7_force_build')

1142         150 LOAD_CONST              33 (('\\buse the word [A-Za-z0-9_]+ as a UI label\\b', '\\badd the label [A-Za-z0-9_]+\\b', '\\bsummarize[^.?!]*\\bcreate a checklist\\b', '\\bvalidate[^.?!]*\\bcreate[^.?!]*\\bplan\\b', '\\bupdate the note\\b', '\\bmake (?:this|the|an?|earlier|previous) [^.?!]*(?:sentence|proposal|text)[^.?!]*(?:short|shorter|businesslike|better)\\b', '\\bmake a pros/cons table\\b', '\\bend with a comparison table\\b', '\\brecord the sentence\\b[^.?!]*\\bhypothesis note\\b'))

1139         152 CALL_FUNCTION            3

 991         154 MAP_ADD                  1

1154         156 LOAD_CONST              34 ('force_explain')
             158 LOAD_GLOBAL              0 (_any_regex_evidence)

1155         160 LOAD_FAST                0 (text)

1156         162 LOAD_CONST              35 ('v7_force_explain')

1157         164 LOAD_CONST              36 (('\\bexplain\\b', '\\bApache\\s*2\\.0[^.?!]*(?:overview|general information)\\b', '作業フォルダ名.*説明', '\\u4f5c\\u696d\\u30d5\\u30a9\\u30eb\\u30c0\\u540d.*\\u8aac\\u660e', '医療AI[^。]*設計[^。]*説明'))

1154         166 CALL_FUNCTION            3

 991         168 MAP_ADD                  1

1165         170 LOAD_CONST              37 ('force_verify')
             172 LOAD_GLOBAL              0 (_any_regex_evidence)

1166         174 LOAD_FAST                0 (text)

1167         176 LOAD_CONST              38 ('v7_force_verify')

1168         178 LOAD_CONST              39 (('\\bwhat is the latest stable\\b', '\\b(?:medical advice|medical dosage advice) is safe\\b', '\\bverify\\b', '\\bcheck[^.?!]*(?:latest|current|still|sources?|contract|medical|config|checksum|vulnerability|license|citations?)\\b', '\\bcheck what article \\d+ says\\b', '\\bdo not assume it is true\\b'))

1165         180 CALL_FUNCTION            3

 991         182 MAP_ADD                  1

1177         184 LOAD_CONST              40 ('short_response')
             186 LOAD_GLOBAL              0 (_any_regex_evidence)

1178         188 LOAD_FAST                0 (text)

1179         190 LOAD_CONST              41 ('v7_short_response')

1180         192 LOAD_CONST              42 (('\\bexactly one short sentence\\b', '\\bshort sentence\\b', '\\bshort response\\b', '\\bshort [^.?!]*(?:checklist|migration|release note)\\b', '\\bshort and\\b', '\\bshorter\\b', '短く'))

1177         194 CALL_FUNCTION            3

 991         196 MAP_ADD                  1

1190         198 LOAD_CONST              43 ('medium_response')
             200 LOAD_GLOBAL              0 (_any_regex_evidence)

1191         202 LOAD_FAST                0 (text)

1192         204 LOAD_CONST              44 ('v7_medium_response')

1193         206 LOAD_CONST              45 (('\\bmedium length\\b',))

1190         208 CALL_FUNCTION            3

 991         210 MAP_ADD                  1

1195         212 LOAD_CONST              46 ('long_response')
             214 LOAD_GLOBAL              0 (_any_regex_evidence)

1196         216 LOAD_FAST                0 (text)

1197         218 LOAD_CONST              47 ('v7_long_response')

1198         220 LOAD_CONST              48 (('\\blong explanation\\b',))

1195         222 CALL_FUNCTION            3

 991         224 MAP_ADD                  1

1200         226 LOAD_CONST              49 ('no_table')
             228 LOAD_GLOBAL              0 (_any_regex_evidence)

1201         230 LOAD_FAST                0 (text)

1202         232 LOAD_CONST              50 ('v7_no_table')

1203         234 LOAD_CONST              51 (('\\bwithout a table\\b', '\\bno table\\b', '表にせず'))

1200         236 CALL_FUNCTION            3

 991         238 MAP_ADD                  1
             240 BUILD_MAP                0

1205         242 LOAD_CONST              52 ('no_web_search')
             244 LOAD_GLOBAL              0 (_any_regex_evidence)

1206         246 LOAD_FAST                0 (text)

1207         248 LOAD_CONST              53 ('v7_no_web_search')

1208         250 LOAD_CONST              54 (('\\bwithout web search\\b', '\\bweb search is not needed\\b', '\\bdo not search externally\\b', '\\bno external current information is needed\\b', '\\bno external [^.?!]*information is needed\\b', 'Web検索は不要'))

1205         252 CALL_FUNCTION            3

 991         254 MAP_ADD                  1

1217         256 LOAD_CONST              55 ('preserve_neutrality')
             258 LOAD_GLOBAL              0 (_any_regex_evidence)

1218         260 LOAD_FAST                0 (text)

1219         262 LOAD_CONST              56 ('v7_preserve_neutrality')

1220         264 LOAD_CONST              57 (('\\bdo not pick a winner\\b', '\\bwithout choosing a side\\b', '\\bneutral summary\\b', '\\bneutral\\b', '\\bnot a conclusion\\b'))

1217         266 CALL_FUNCTION            3

 991         268 MAP_ADD                  1

1228         270 LOAD_CONST              58 ('avoid_overclaim')
             272 LOAD_GLOBAL              0 (_any_regex_evidence)

1229         274 LOAD_FAST                0 (text)

1230         276 LOAD_CONST              59 ('v7_avoid_overclaim')

1231         278 LOAD_CONST              60 (('\\bwithout overclaiming\\b', '\\bwithout claiming\\b'))

1228         280 CALL_FUNCTION            3

 991         282 MAP_ADD                  1

1233         284 LOAD_CONST              61 ('general_information_only')
             286 LOAD_GLOBAL              0 (_any_regex_evidence)

1234         288 LOAD_FAST                0 (text)

1235         290 LOAD_CONST              62 ('v7_general_information_only')

1236         292 LOAD_CONST              63 (('\\bgeneral information\\b', '一般情報', '法的助言は不要'))

1233         294 CALL_FUNCTION            3

 991         296 MAP_ADD                  1

1238         298 LOAD_CONST              64 ('avoid_diagnosis')
             300 LOAD_GLOBAL              0 (_any_regex_evidence)

1239         302 LOAD_FAST                0 (text)

1240         304 LOAD_CONST              65 ('v7_avoid_diagnosis')

1241         306 LOAD_CONST              66 (('\\bavoid diagnosis\\b', '\\bwithout diagnosis\\b', '\\bno diagnosis\\b', '\\bdo not give diagnosis\\b', '\\bdo not give diagnosis or treatment advice\\b', '\\bno diagnosis or treatment advice\\b', '診断助言なし'))

1238         308 CALL_FUNCTION            3

 991         310 MAP_ADD                  1

1251         312 LOAD_CONST              67 ('low_risk_term_mention')
             314 LOAD_GLOBAL              0 (_any_regex_evidence)

1252         316 LOAD_FAST                0 (text)

1253         318 LOAD_CONST              68 ('v7_low_risk_term_mention')

1254         320 LOAD_CONST              69 (('\\bword medical_[A-Za-z0-9_]+ as a UI label\\b', '\\bmedical_[A-Za-z0-9_]+ as a UI label\\b', '\\bmedical ai ui\\b[^.?!]*(?:no diagnosis|design|cautions?)\\b', '\\bcommon causes of fatigue\\b[^.?!]*(?:do not give diagnosis|no diagnosis|treatment advice)\\b', '\\bApache\\s*2\\.0[^.?!]*(?:overview|general information)\\b', '\\blegal advice is not needed\\b', '医療AI[^。]*設計[^。]*診断助言なし', '法的助言は不要'))

1251         322 CALL_FUNCTION            3

 991         324 MAP_ADD                  1

1265         326 LOAD_CONST              70 ('license_medium')
             328 LOAD_GLOBAL              0 (_any_regex_evidence)

1266         330 LOAD_FAST                0 (text)

1267         332 LOAD_CONST              71 ('v7_license_medium')

1268         334 LOAD_CONST              72 (('\\bApache\\s*2\\.0[^.?!]*(?:commercial use|allows)\\b', '\\blicense permission\\b'))

1265         336 CALL_FUNCTION            3

 991         338 MAP_ADD                  1

1270         340 LOAD_CONST              73 ('legal_medium')
             342 LOAD_GLOBAL              0 (_any_regex_evidence)

1271         344 LOAD_FAST                0 (text)

1272         346 LOAD_CONST              74 ('v7_legal_medium')

1273         348 LOAD_CONST              75 (('\\barticle \\d+\\b[^.?!]*(?:citations?|sources?|says)',))

1270         350 CALL_FUNCTION            3

 991         352 MAP_ADD                  1

1275         354 LOAD_CONST              76 ('note_record_no_verify')
             356 LOAD_GLOBAL              0 (_any_regex_evidence)

1276         358 LOAD_FAST                0 (text)

1277         360 LOAD_CONST              77 ('v7_note_record_no_verify')

1278         362 LOAD_CONST              78 (('\\brecord the sentence\\b[^.?!]*\\bhypothesis note\\b[^.?!]*\\bdo not verify\\b', '\\bhypothesis note\\b[^.?!]*\\bdo not verify\\b', '\\brecord the sentence\\b.*\\bhypothesis note\\b.*\\bdo not verify\\b'))

1275         364 CALL_FUNCTION            3

 991         366 MAP_ADD                  1

1284         368 LOAD_CONST              79 ('conclusion_word_suppression')
             370 LOAD_GLOBAL              0 (_any_regex_evidence)

1285         372 LOAD_FAST                0 (text)

1286         374 LOAD_CONST              80 ('v7_conclusion_word_suppression')

1287         376 LOAD_CONST              81 (('\\bnot a conclusion\\b',))

1284         378 CALL_FUNCTION            3

 991         380 MAP_ADD                  1

1289         382 LOAD_CONST              82 ('future_medium')
             384 LOAD_GLOBAL              0 (_any_regex_evidence)

1290         386 LOAD_FAST                0 (text)

1291         388 LOAD_CONST              83 ('v7_future_medium')

1292         390 LOAD_CONST              84 (('\\bfuture [^.?!]*scenarios\\b',))

1289         392 CALL_FUNCTION            3

 991         394 MAP_ADD                  1

1294         396 LOAD_CONST              85 ('political_medium')
             398 LOAD_GLOBAL              0 (_any_regex_evidence)

1295         400 LOAD_FAST                0 (text)

1296         402 LOAD_CONST              86 ('v7_political_medium')

1297         404 LOAD_CONST              87 (('\\bpolicy dispute\\b',))

1294         406 CALL_FUNCTION            3

 991         408 MAP_ADD                  1

1299         410 LOAD_CONST              88 ('risk_comparison_medium')
             412 LOAD_GLOBAL              0 (_any_regex_evidence)

1300         414 LOAD_FAST                0 (text)

1301         416 LOAD_CONST              89 ('v7_risk_comparison_medium')

1302         418 LOAD_CONST              90 (('複数[^。]*リスク[^。]*比較', '\\brisk[^.?!]*compare\\b'))

1299         420 CALL_FUNCTION            3

 991         422 MAP_ADD                  1

1304         424 LOAD_CONST              91 ('high_legal')
             426 LOAD_GLOBAL              0 (_any_regex_evidence)

1305         428 LOAD_FAST                0 (text)

1306         430 LOAD_CONST              92 ('v7_high_legal')

1307         432 LOAD_CONST              93 (('\\bcontract (?:validity|legality)\\b', '\\bcurrent contract legality\\b', '現在の法律[^。]*契約'))

1304         434 CALL_FUNCTION            3

 991         436 MAP_ADD                  1

1309         438 LOAD_CONST              94 ('high_medical')
             440 LOAD_GLOBAL              0 (_any_regex_evidence)

1310         442 LOAD_FAST                0 (text)

1311         444 LOAD_CONST              95 ('v7_high_medical')

1312         446 LOAD_CONST              96 (('\\bmedical (?:dosage|advice)\\b', '医療助言'))

1309         448 CALL_FUNCTION            3

 991         450 MAP_ADD                  1

1314         452 LOAD_CONST              97 ('high_security')
             454 LOAD_GLOBAL              0 (_any_regex_evidence)

1315         456 LOAD_FAST                0 (text)

1316         458 LOAD_CONST              98 ('v7_high_security')

1317         460 LOAD_CONST              99 (('\\bvulnerability\\b', '\\bexploit\\b'))

1314         462 CALL_FUNCTION            3

 991         464 MAP_ADD                  1
             466 DICT_UPDATE              1
             468 STORE_FAST               1 (groups)

1320         470 BUILD_LIST               0
             472 STORE_FAST               2 (evidence)

1321         474 LOAD_FAST                1 (groups)
             476 LOAD_METHOD              1 (values)
             478 CALL_METHOD              0
             480 GET_ITER
         >>  482 FOR_ITER                 7 (to 498)
             484 STORE_FAST               3 (value)

1322         486 LOAD_FAST                2 (evidence)
             488 LOAD_METHOD              2 (extend)
             490 LOAD_FAST                3 (value)
             492 CALL_METHOD              1
             494 POP_TOP
             496 JUMP_ABSOLUTE          241 (to 482)

1323     >>  498 BUILD_MAP                0

1324         500 LOAD_FAST                1 (groups)

1323         502 DICT_UPDATE              1

1325         504 LOAD_FAST                2 (evidence)

1326         506 LOAD_GLOBAL              3 (bool)
             508 LOAD_FAST                1 (groups)
             510 LOAD_CONST              67 ('low_risk_term_mention')
             512 BINARY_SUBSCR
             514 CALL_FUNCTION            1

1323         516 LOAD_CONST             100 (('evidence', 'low_risk_boundary'))
             518 BUILD_CONST_KEY_MAP      2
             520 DICT_UPDATE              1
             522 RETURN_VALUE


================================================================================
_v8_recovery_profile firstlineno=1330
--------------------------------------------------------------------------------
1333           0 BUILD_MAP                0

1334           2 LOAD_CONST               1 ('missing_info')
               4 LOAD_GLOBAL              0 (_any_regex_evidence)

1335           6 LOAD_FAST                0 (text)

1336           8 LOAD_CONST               2 ('v8_missing_info')

1337          10 LOAD_CONST               3 (("\\b(?:have not|haven't) (?:pasted|attached|described)\\b", '\\b(?:not pasted|not attached|not described|forgot to attach)\\b', '\\bno (?:log|file|source data|paragraph|text) is attached\\b', '\\bsource data is missing\\b', '\\b(?:text|paragraph|log|source data|options?|option a|option b)\\b[^.?!]*(?:missing|not provided|not described|not attached|not pasted)'))

1334          12 CALL_FUNCTION            3

1333          14 MAP_ADD                  1

1345          16 LOAD_CONST               4 ('current_blocker')
              18 LOAD_GLOBAL              0 (_any_regex_evidence)

1346          20 LOAD_FAST                0 (text)

1347          22 LOAD_CONST               5 ('v8_current_blocker')

1348          24 LOAD_CONST               6 (("\\btoday's local conversation log\\b", '\\blocal conversation log\\b', '\\bdo not use external news\\b', '\\bdo not use external information\\b', '\\bno current legal advice\\b', '\\bcurrent legal advice is not needed\\b', '\\bit is just a filename label\\b'))

1345          26 CALL_FUNCTION            3

1333          28 MAP_ADD                  1

1358          30 LOAD_CONST               7 ('unverified_claim')
              32 LOAD_GLOBAL              0 (_any_regex_evidence)

1359          34 LOAD_FAST                0 (text)

1360          36 LOAD_CONST               8 ('v8_unverified_claim')

1361          38 LOAD_CONST               9 (("\\bvendor's security claim\\b", '\\bclaim\\b[^.?!]*(?:accurate|verify|fixed)', '\\bbefore adding this number\\b', '\\b\\d+ incidents is correct\\b', '\\breport total \\d+ equals\\b', '\\bcontract template is said\\b', '\\blegally valid\\b', '\\bmedication dosage advice\\b'))

1358          40 CALL_FUNCTION            3

1333          42 MAP_ADD                  1

1372          44 LOAD_CONST              10 ('multiple_sequence')
              46 LOAD_GLOBAL              0 (_any_regex_evidence)

1373          48 LOAD_FAST                0 (text)

1374          50 LOAD_CONST              11 ('v8_multiple_sequence')

1375          52 LOAD_CONST              12 (('\\bverify[^.?!]*\\bthen draft\\b', '\\bsummarize[^.?!]*\\bthen compare\\b', '\\bextract[^.?!]*\\bclassify\\b', '\\bcreate[^.?!]*\\bbut[^.?!]*\\bmissing\\b'))

1372          54 CALL_FUNCTION            3

1333          56 MAP_ADD                  1

1382          58 LOAD_CONST              13 ('terminal_build')
              60 LOAD_GLOBAL              0 (_any_regex_evidence)

1383          62 LOAD_FAST                0 (text)

1384          64 LOAD_CONST              14 ('v8_terminal_build')

1385          66 LOAD_CONST              15 (('\\bdraft a short release-?note sentence\\b', '\\bextract candidate IDs?[^.?!]*\\bclassify\\b', '\\bcreate (?:the |a )?migration table\\b'))

1382          68 CALL_FUNCTION            3

1333          70 MAP_ADD                  1

1391          72 LOAD_CONST              16 ('force_explore')
              74 LOAD_GLOBAL              0 (_any_regex_evidence)

1392          76 LOAD_FAST                0 (text)

1393          78 LOAD_CONST              17 ('v8_force_explore')

1394          80 LOAD_CONST              18 (('\\bsummarize[^.?!]*\\bthen compare\\b',))

1391          82 CALL_FUNCTION            3

1333          84 MAP_ADD                  1

1396          86 LOAD_CONST              19 ('force_build')
              88 LOAD_GLOBAL              0 (_any_regex_evidence)

1397          90 LOAD_FAST                0 (text)

1398          92 LOAD_CONST              20 ('v8_force_build')

1399          94 LOAD_CONST              21 (('\\bextract candidate IDs?[^.?!]*\\bclassify\\b', '\\bnote it as a light-use example\\b', '\\badd (?:a |the )?(?:tag|field|column|heading)\\b'))

1396          96 CALL_FUNCTION            3

1333          98 MAP_ADD                  1

1405         100 LOAD_CONST              22 ('force_explain')
             102 LOAD_GLOBAL              0 (_any_regex_evidence)

1406         104 LOAD_FAST                0 (text)

1407         106 LOAD_CONST              23 ('v8_force_explain')

1408         108 LOAD_CONST              24 (('\\bwhat is Apache\\s*2\\.0\\b[^.?!]*(?:in general|general)', '\\bbriefly explain (?:the )?Apache\\s*2\\.0\\b', '\\bApache\\s*2\\.0 license\\b[^.?!]*(?:overview|brief|general level|no legal advice)'))

1405         110 CALL_FUNCTION            3

1333         112 MAP_ADD                  1

1414         114 LOAD_CONST              25 ('force_summarize')
             116 LOAD_GLOBAL              0 (_any_regex_evidence)

1415         118 LOAD_FAST                0 (text)

1416         120 LOAD_CONST              26 ('v8_force_summarize')

1417         122 LOAD_CONST              27 (('\\bsummarize this as a light AI-use example\\b',))

1414         124 CALL_FUNCTION            3

1333         126 MAP_ADD                  1

1419         128 LOAD_CONST              28 ('force_verify')
             130 LOAD_GLOBAL              0 (_any_regex_evidence)

1420         132 LOAD_FAST                0 (text)

1421         134 LOAD_CONST              29 ('v8_force_verify')

1422         136 LOAD_CONST              30 (('\\bverify whether the claim\\b', '\\bverify[^.?!]*(?:vendor|security|claim|safety)', '\\bcheck whether[^.?!]*(?:correct|equals)'))

1419         138 CALL_FUNCTION            3

1333         140 MAP_ADD                  1

1428         142 LOAD_CONST              31 ('short_response')
             144 LOAD_GLOBAL              0 (_any_regex_evidence)

1429         146 LOAD_FAST                0 (text)

1430         148 LOAD_CONST              32 ('v8_short_response')

1431         150 LOAD_CONST              33 (('\\bshort release-?note sentence\\b', '\\bshort answer\\b', '\\bbrief(?:ly)?\\b'))

1428         152 CALL_FUNCTION            3

1333         154 MAP_ADD                  1

1437         156 LOAD_CONST              34 ('force_table')
             158 LOAD_GLOBAL              0 (_any_regex_evidence)

1438         160 LOAD_FAST                0 (text)

1439         162 LOAD_CONST              35 ('v8_force_table')

1440         164 LOAD_CONST              36 (('\\bin a table\\b', '\\bclassify each[^.?!]*\\btable\\b', '\\bmigration table\\b'))

1437         166 CALL_FUNCTION            3

1333         168 MAP_ADD                  1

1446         170 LOAD_CONST              37 ('preserve_neutrality')
             172 LOAD_GLOBAL              0 (_any_regex_evidence)

1447         174 LOAD_FAST                0 (text)

1448         176 LOAD_CONST              38 ('v8_preserve_neutrality')

1449         178 LOAD_CONST              39 (('\\bneutral (?:tone|summary|design|notes?)\\b',))

1446         180 CALL_FUNCTION            3

1333         182 MAP_ADD                  1

1451         184 LOAD_CONST              40 ('avoid_diagnosis')
             186 LOAD_GLOBAL              0 (_any_regex_evidence)

1452         188 LOAD_FAST                0 (text)

1453         190 LOAD_CONST              41 ('v8_avoid_diagnosis')

1454         192 LOAD_CONST              42 (('\\bwithout diagnosis\\b',))

1451         194 CALL_FUNCTION            3

1333         196 MAP_ADD                  1

1458         198 LOAD_CONST              43 ('general_information_only')
             200 LOAD_GLOBAL              0 (_any_regex_evidence)

1459         202 LOAD_FAST                0 (text)

1460         204 LOAD_CONST              44 ('v8_general_information_only')

1461         206 LOAD_CONST              45 (('\\bgeneral information only\\b', '\\bonly generally\\b', '\\bprofessional review\\b'))

1458         208 CALL_FUNCTION            3

1333         210 MAP_ADD                  1

1467         212 LOAD_CONST              46 ('avoid_overclaim')
             214 LOAD_GLOBAL              0 (_any_regex_evidence)

1468         216 LOAD_FAST                0 (text)

1469         218 LOAD_CONST              47 ('v8_avoid_overclaim')

1470         220 LOAD_CONST              48 (('\\bavoid overclaiming\\b', '\\bprofessional review\\b', '\\bonly generally\\b'))

1467         222 CALL_FUNCTION            3

1333         224 MAP_ADD                  1

1476         226 LOAD_CONST              49 ('cite_sources')
             228 LOAD_GLOBAL              0 (_any_regex_evidence)

1477         230 LOAD_FAST                0 (text)

1478         232 LOAD_CONST              50 ('v8_cite_sources')

1479         234 LOAD_CONST              51 (('\\bcite sources\\b', '\\bwith sources\\b'))

1476         236 CALL_FUNCTION            3

1333         238 MAP_ADD                  1

1481         240 LOAD_GLOBAL              0 (_any_regex_evidence)

1482         242 LOAD_FAST                0 (text)

1483         244 LOAD_CONST              52 ('v8_no_web_search')

1484         246 LOAD_CONST              53 (('\\bdo not search the web\\b', '\\bdo not use external news\\b', '\\bdo not use external information\\b'))

1481         248 CALL_FUNCTION            3

1490         250 LOAD_GLOBAL              0 (_any_regex_evidence)

1491         252 LOAD_FAST                0 (text)

1492         254 LOAD_CONST              54 ('v8_no_table')

1493         256 LOAD_CONST              55 (('\\bno table\\b',))

1490         258 CALL_FUNCTION            3

1495         260 LOAD_GLOBAL              0 (_any_regex_evidence)

1496         262 LOAD_FAST                0 (text)

1497         264 LOAD_CONST              56 ('v8_license_medium')

1498         266 LOAD_CONST              57 (('\\blicense[^.?!]*(?:commercial use|allows every commercial use)\\b', '\\bApache\\s*2\\.0[^.?!]*commercial use\\b'))

1495         268 CALL_FUNCTION            3

1503         270 LOAD_GLOBAL              0 (_any_regex_evidence)

1504         272 LOAD_FAST                0 (text)

1505         274 LOAD_CONST              58 ('v8_security_medium')

1506         276 LOAD_CONST              59 (('\\bsecurity claim\\b',))

1503         278 CALL_FUNCTION            3

1508         280 LOAD_GLOBAL              0 (_any_regex_evidence)

1509         282 LOAD_FAST                0 (text)

1510         284 LOAD_CONST              60 ('v8_high_medical')

1511         286 LOAD_CONST              61 (('\\bmedication dosage advice\\b',))

1508         288 CALL_FUNCTION            3

1513         290 LOAD_GLOBAL              0 (_any_regex_evidence)

1514         292 LOAD_FAST                0 (text)

1515         294 LOAD_CONST              62 ('v8_legal_high')

1516         296 LOAD_CONST              63 (('\\blegally valid\\b', '\\bcontract template is said\\b'))

1513         298 CALL_FUNCTION            3

1518         300 LOAD_GLOBAL              0 (_any_regex_evidence)

1519         302 LOAD_FAST                0 (text)

1520         304 LOAD_CONST              64 ('v8_low_risk_boundary')

1521         306 LOAD_CONST              65 (('\\bMedical AI (?:UI|dashboard)\\b[^.?!]*(?:UI design|not diagnosis|without diagnosis)', '\\bApache\\s*2\\.0\\b[^.?!]*(?:in general|general level|no legal advice|brief)', '\\bAI\\b[^.?!]*(?:light-use example|not a dependence warning|not dependence)'))

1518         308 CALL_FUNCTION            3

1333         310 LOAD_CONST              66 (('no_web_search', 'no_table', 'license_medium', 'security_medium', 'high_medical', 'legal_high', 'low_risk_boundary'))
             312 BUILD_CONST_KEY_MAP      7
             314 DICT_UPDATE              1
             316 STORE_FAST               1 (groups)

1528         318 BUILD_LIST               0
             320 STORE_FAST               2 (evidence)

1529         322 LOAD_FAST                1 (groups)
             324 LOAD_METHOD              1 (values)
             326 CALL_METHOD              0
             328 GET_ITER
         >>  330 FOR_ITER                 7 (to 346)
             332 STORE_FAST               3 (value)

1530         334 LOAD_FAST                2 (evidence)
             336 LOAD_METHOD              2 (extend)
             338 LOAD_FAST                3 (value)
             340 CALL_METHOD              1
             342 POP_TOP
             344 JUMP_ABSOLUTE          165 (to 330)

1531     >>  346 BUILD_MAP                0
             348 LOAD_FAST                1 (groups)
             350 DICT_UPDATE              1
             352 LOAD_CONST              67 ('evidence')
             354 LOAD_FAST                2 (evidence)
             356 BUILD_MAP                1
             358 DICT_UPDATE              1
             360 RETURN_VALUE


================================================================================
_v9_primary_review_profile firstlineno=1570
--------------------------------------------------------------------------------
1573           0 BUILD_LIST               0

1575           2 LOAD_CONST               1 ('\\bcurrent AI regulation status\\b')

1576           4 LOAD_GLOBAL              0 (_v9_override)

1577           6 LOAD_CONST               2 ('explain')

1578           8 BUILD_LIST               0
              10 LOAD_CONST               3 (('explain', 'verify', 'search'))
              12 LIST_EXTEND              1

1579          14 LOAD_CONST               4 (True)

1580          16 LOAD_CONST               4 (True)

1581          18 BUILD_LIST               0
              20 LOAD_CONST               5 (('cite_sources', 'avoid_overclaim', 'preserve_neutrality'))
              22 LIST_EXTEND              1

1582          24 LOAD_CONST               6 ('high')

1583          26 LOAD_CONST               7 ('legal')
              28 LOAD_CONST               8 ('current_information')
              30 BUILD_LIST               2

1576          32 LOAD_CONST               9 (('current', 'multiple', 'must', 'risk', 'risk_flags'))
              34 CALL_FUNCTION_KW         7

1574          36 BUILD_TUPLE              2

1573          38 LIST_APPEND              1

1587          40 LOAD_CONST              10 ('\\blatest stable version of FastAPI\\b')

1588          42 LOAD_GLOBAL              0 (_v9_override)

1589          44 LOAD_CONST              11 ('verify')

1590          46 LOAD_CONST              11 ('verify')
              48 LOAD_CONST              12 ('search')
              50 BUILD_LIST               2

1591          52 LOAD_CONST               4 (True)

1592          54 LOAD_CONST              13 ('cite_sources')
              56 LOAD_CONST              14 ('avoid_overclaim')
              58 BUILD_LIST               2

1593          60 LOAD_CONST              15 ('medium')

1594          62 LOAD_CONST               8 ('current_information')
              64 BUILD_LIST               1

1588          66 LOAD_CONST              16 (('current', 'must', 'risk', 'risk_flags'))
              68 CALL_FUNCTION_KW         6

1586          70 BUILD_TUPLE              2

1573          72 LIST_APPEND              1

1598          74 LOAD_CONST              17 ('\\bfield named recent_file_count\\b')

1599          76 LOAD_GLOBAL              0 (_v9_override)
              78 LOAD_CONST              18 ('build')
              80 LOAD_CONST              18 ('build')
              82 BUILD_LIST               1
              84 LOAD_CONST              19 ('no_web_search')
              86 BUILD_LIST               1
              88 LOAD_CONST              20 (('must_not',))
              90 CALL_FUNCTION_KW         3

1597          92 BUILD_TUPLE              2

1573          94 LIST_APPEND              1

1602          96 LOAD_CONST              21 ('\\blatest public benchmark scores\\b')

1603          98 LOAD_GLOBAL              0 (_v9_override)

1604         100 LOAD_CONST              22 ('explore')

1605         102 BUILD_LIST               0
             104 LOAD_CONST              23 (('explore', 'search', 'compare'))
             106 LIST_EXTEND              1

1606         108 LOAD_CONST               4 (True)

1607         110 LOAD_CONST              24 ('table')
             112 BUILD_LIST               1

1608         114 BUILD_LIST               0
             116 LOAD_CONST               5 (('cite_sources', 'avoid_overclaim', 'preserve_neutrality'))
             118 LIST_EXTEND              1

1609         120 LOAD_CONST              15 ('medium')

1610         122 LOAD_CONST               8 ('current_information')
             124 BUILD_LIST               1

1603         126 LOAD_CONST              25 (('current', 'formats', 'must', 'risk', 'risk_flags'))
             128 CALL_FUNCTION_KW         7

1601         130 BUILD_TUPLE              2

1573         132 LIST_APPEND              1

1614         134 LOAD_CONST              26 ('\\blocally installed Python version\\b')

1615         136 LOAD_GLOBAL              0 (_v9_override)
             138 LOAD_CONST              18 ('build')
             140 LOAD_CONST              18 ('build')
             142 BUILD_LIST               1
             144 LOAD_CONST              19 ('no_web_search')
             146 BUILD_LIST               1
             148 LOAD_CONST              20 (('must_not',))
             150 CALL_FUNCTION_KW         3

1613         152 BUILD_TUPLE              2

1573         154 LIST_APPEND              1

1618         156 LOAD_CONST              27 ('\\bCheck the replay report, then promote\\b')

1619         158 LOAD_GLOBAL              0 (_v9_override)
             160 LOAD_CONST              11 ('verify')
             162 LOAD_CONST              11 ('verify')
             164 BUILD_LIST               1
             166 LOAD_CONST               4 (True)
             168 LOAD_CONST              14 ('avoid_overclaim')
             170 BUILD_LIST               1
             172 LOAD_CONST              28 (('multiple', 'must'))
             174 CALL_FUNCTION_KW         4

1617         176 BUILD_TUPLE              2

1573         178 LIST_APPEND              1

1622         180 LOAD_CONST              29 ('\\bcurrent release date\\b[^.?!]*\\bcitation\\b')

1623         182 LOAD_GLOBAL              0 (_v9_override)

1624         184 LOAD_CONST               2 ('explain')

1625         186 LOAD_CONST               2 ('explain')
             188 LOAD_CONST              12 ('search')
             190 BUILD_LIST               2

1626         192 LOAD_CONST               4 (True)

1627         194 LOAD_CONST               4 (True)

1628         196 LOAD_CONST              30 ('short')

1629         198 LOAD_CONST              13 ('cite_sources')
             200 LOAD_CONST              14 ('avoid_overclaim')
             202 BUILD_LIST               2

1630         204 LOAD_CONST              15 ('medium')

1631         206 LOAD_CONST               8 ('current_information')
             208 BUILD_LIST               1

1623         210 LOAD_CONST              31 (('current', 'multiple', 'response_length', 'must', 'risk', 'risk_flags'))
             212 CALL_FUNCTION_KW         8

1621         214 BUILD_TUPLE              2

1573         216 LIST_APPEND              1

1635         218 LOAD_CONST              32 ('\\bReview this route rule, then patch\\b')

1636         220 LOAD_GLOBAL              0 (_v9_override)
             222 LOAD_CONST              18 ('build')
             224 LOAD_CONST              18 ('build')
             226 LOAD_CONST              11 ('verify')
             228 BUILD_LIST               2
             230 LOAD_CONST               4 (True)
             232 LOAD_CONST              33 (('multiple',))
             234 CALL_FUNCTION_KW         3

1634         236 BUILD_TUPLE              2

1573         238 LIST_APPEND              1

1639         240 LOAD_CONST              34 ('\\bClean the candidate list, then measure\\b')

1640         242 LOAD_GLOBAL              0 (_v9_override)
             244 LOAD_CONST              35 ('summarize')
             246 LOAD_CONST              35 ('summarize')
             248 LOAD_CONST              36 ('calculate')
             250 BUILD_LIST               2
             252 LOAD_CONST               4 (True)
             254 LOAD_CONST              33 (('multiple',))
             256 CALL_FUNCTION_KW         3

1638         258 BUILD_TUPLE              2

1573         260 LIST_APPEND              1

1643         262 LOAD_CONST              37 ('\\bBack up the current state, then run\\b')

1644         264 LOAD_GLOBAL              0 (_v9_override)
             266 LOAD_CONST              18 ('build')
             268 LOAD_CONST              18 ('build')
             270 LOAD_CONST              11 ('verify')
             272 BUILD_LIST               2
             274 LOAD_CONST               4 (True)
             276 LOAD_CONST              33 (('multiple',))
             278 CALL_FUNCTION_KW         3

1642         280 BUILD_TUPLE              2

1573         282 LIST_APPEND              1

1647         284 LOAD_CONST              38 ('\\bgive only the final risks\\b')

1648         286 LOAD_GLOBAL              0 (_v9_override)
             288 LOAD_CONST              35 ('summarize')
             290 LOAD_CONST              35 ('summarize')
             292 BUILD_LIST               1
             294 LOAD_CONST              14 ('avoid_overclaim')
             296 BUILD_LIST               1
             298 LOAD_CONST              39 (('must',))
             300 CALL_FUNCTION_KW         3

1646         302 BUILD_TUPLE              2

1573         304 LIST_APPEND              1

1651         306 LOAD_CONST              40 ('\\bFix the failing test, but I have not pasted the error output yet\\b')

1652         308 LOAD_GLOBAL              0 (_v9_override)
             310 LOAD_CONST              41 ('clarify')
             312 LOAD_CONST              41 ('clarify')
             314 LOAD_CONST              18 ('build')
             316 BUILD_LIST               2
             318 LOAD_CONST               4 (True)
             320 LOAD_CONST               4 (True)
             322 LOAD_CONST              42 ('ask_first')
             324 BUILD_LIST               1
             326 LOAD_CONST              43 (('missing', 'multiple', 'must'))
             328 CALL_FUNCTION_KW         5

1650         330 BUILD_TUPLE              2

1573         332 LIST_APPEND              1

1655         334 LOAD_CONST              44 ('\\bDecide whether to adopt\\b[^.?!]*\\bchecking its score\\b')

1656         336 LOAD_GLOBAL              0 (_v9_override)
             338 LOAD_CONST              11 ('verify')
             340 LOAD_CONST              11 ('verify')
             342 LOAD_CONST              35 ('summarize')
             344 BUILD_LIST               2
             346 LOAD_CONST               4 (True)
             348 LOAD_CONST              14 ('avoid_overclaim')
             350 BUILD_LIST               1
             352 LOAD_CONST              28 (('multiple', 'must'))
             354 CALL_FUNCTION_KW         4

1654         356 BUILD_TUPLE              2

1573         358 LIST_APPEND              1

1659         360 LOAD_CONST              45 ('\\b20% faster\\b[^.?!]*\\bverify the claim\\b')

1660         362 LOAD_GLOBAL              0 (_v9_override)
             364 LOAD_CONST              11 ('verify')
             366 LOAD_CONST              11 ('verify')
             368 BUILD_LIST               1
             370 LOAD_CONST               4 (True)
             372 LOAD_CONST              15 ('medium')
             374 LOAD_CONST              46 ('unverified_claim')
             376 BUILD_LIST               1
             378 LOAD_CONST              47 (('unverified', 'risk', 'risk_flags'))
             380 CALL_FUNCTION_KW         5

1658         382 BUILD_TUPLE              2

1573         384 LIST_APPEND              1

1663         386 LOAD_CONST              48 ('\\bmedical AI reduces diagnosis errors\\b')

1664         388 LOAD_GLOBAL              0 (_v9_override)

1665         390 LOAD_CONST               2 ('explain')

1666         392 LOAD_CONST               2 ('explain')
             394 LOAD_CONST              11 ('verify')
             396 BUILD_LIST               2

1667         398 LOAD_CONST               4 (True)

1668         400 LOAD_CONST              49 ('general_information_only')
             402 LOAD_CONST              14 ('avoid_overclaim')
             404 BUILD_LIST               2

1669         406 LOAD_CONST               6 ('high')

1670         408 LOAD_CONST              50 ('medical')
             410 LOAD_CONST              46 ('unverified_claim')
             412 BUILD_LIST               2

1664         414 LOAD_CONST              51 (('unverified', 'must', 'risk', 'risk_flags'))
             416 CALL_FUNCTION_KW         6

1662         418 BUILD_TUPLE              2

1573         420 LIST_APPEND              1

1674         422 LOAD_CONST              52 ('\\bthree route gaps\\b[^.?!]*\\bnot a table\\b')

1675         424 LOAD_GLOBAL              0 (_v9_override)
             426 LOAD_CONST              35 ('summarize')
             428 LOAD_CONST              35 ('summarize')
             430 BUILD_LIST               1
             432 LOAD_CONST              30 ('short')
             434 LOAD_CONST              53 ('no_table')
             436 BUILD_LIST               1
             438 LOAD_CONST              54 (('response_length', 'must_not'))
             440 CALL_FUNCTION_KW         4

1673         442 BUILD_TUPLE              2

1573         444 LIST_APPEND              1

1678         446 LOAD_CONST              55 ('\\bClassify each candidate as keep, rerun, or reserve\\b')

1679         448 LOAD_GLOBAL              0 (_v9_override)
             450 LOAD_CONST              18 ('build')
             452 LOAD_CONST              18 ('build')
             454 BUILD_LIST               1
             456 LOAD_CONST              24 ('table')
             458 BUILD_LIST               1
             460 LOAD_CONST              56 (('formats',))
             462 CALL_FUNCTION_KW         3

1677         464 BUILD_TUPLE              2

1573         466 LIST_APPEND              1

1682         468 LOAD_CONST              57 ('\\bUse only the local log below\\b')

1683         470 LOAD_GLOBAL              0 (_v9_override)
             472 LOAD_CONST              35 ('summarize')
             474 LOAD_CONST              35 ('summarize')
             476 BUILD_LIST               1
             478 LOAD_CONST              19 ('no_web_search')
             480 BUILD_LIST               1
             482 LOAD_CONST              20 (('must_not',))
             484 CALL_FUNCTION_KW         3

1681         486 BUILD_TUPLE              2

1573         488 LIST_APPEND              1

1686         490 LOAD_CONST              58 ('\\bBefore editing the roadmap, ask which section\\b')

1687         492 LOAD_GLOBAL              0 (_v9_override)
             494 LOAD_CONST              41 ('clarify')
             496 LOAD_CONST              41 ('clarify')
             498 BUILD_LIST               1
             500 LOAD_CONST               4 (True)
             502 LOAD_CONST              42 ('ask_first')
             504 BUILD_LIST               1
             506 LOAD_CONST              59 (('missing', 'must'))
             508 CALL_FUNCTION_KW         4

1685         510 BUILD_TUPLE              2

1573         512 LIST_APPEND              1

1690         514 LOAD_CONST              60 ('\\bdo not store this personal note as memory\\b')

1691         516 LOAD_GLOBAL              0 (_v9_override)
             518 LOAD_CONST              18 ('build')
             520 LOAD_CONST              18 ('build')
             522 BUILD_LIST               1
             524 LOAD_CONST              61 ('do_not_store')
             526 BUILD_LIST               1
             528 LOAD_CONST              20 (('must_not',))
             530 CALL_FUNCTION_KW         3

1689         532 BUILD_TUPLE              2

1573         534 LIST_APPEND              1

1694         536 LOAD_CONST              62 ('\\bExplain Apache 2\\.0 at a general level\\b')

1695         538 LOAD_GLOBAL              0 (_v9_override)
             540 LOAD_CONST               2 ('explain')
             542 LOAD_CONST               2 ('explain')
             544 BUILD_LIST               1
             546 LOAD_CONST              49 ('general_information_only')
             548 BUILD_LIST               1
             550 LOAD_CONST              39 (('must',))
             552 CALL_FUNCTION_KW         3

1693         554 BUILD_TUPLE              2

1573         556 LIST_APPEND              1

1698         558 LOAD_CONST              63 ('\\blegally safe to sign\\b')

1699         560 LOAD_GLOBAL              0 (_v9_override)

1700         562 LOAD_CONST              11 ('verify')

1701         564 LOAD_CONST              11 ('verify')
             566 BUILD_LIST               1

1702         568 LOAD_CONST               4 (True)

1703         570 LOAD_CONST              49 ('general_information_only')
             572 LOAD_CONST              14 ('avoid_overclaim')
             574 BUILD_LIST               2

1704         576 LOAD_CONST               6 ('high')

1705         578 LOAD_CONST               7 ('legal')
             580 LOAD_CONST              46 ('unverified_claim')
             582 BUILD_LIST               2

1699         584 LOAD_CONST              51 (('unverified', 'must', 'risk', 'risk_flags'))
             586 CALL_FUNCTION_KW         6

1697         588 BUILD_TUPLE              2

1573         590 LIST_APPEND              1

1709         592 LOAD_CONST              64 ('\\btargeted political persuasion message\\b')

1710         594 LOAD_GLOBAL              0 (_v9_override)
             596 LOAD_CONST              18 ('build')
             598 LOAD_CONST              18 ('build')
             600 LOAD_CONST              11 ('verify')
             602 BUILD_LIST               2
             604 LOAD_CONST               6 ('high')
             606 LOAD_CONST              65 ('political_persuasion')
             608 BUILD_LIST               1
             610 LOAD_CONST              66 (('risk', 'risk_flags'))
             612 CALL_FUNCTION_KW         4

1708         614 BUILD_TUPLE              2

1573         616 LIST_APPEND              1

1713         618 LOAD_CONST              67 ('\\bexploit this production login bug\\b')

1714         620 LOAD_GLOBAL              0 (_v9_override)
             622 LOAD_CONST              11 ('verify')
             624 LOAD_CONST              11 ('verify')
             626 BUILD_LIST               1
             628 LOAD_CONST               6 ('high')
             630 LOAD_CONST              68 ('security')
             632 BUILD_LIST               1
             634 LOAD_CONST              66 (('risk', 'risk_flags'))
             636 CALL_FUNCTION_KW         4

1712         638 BUILD_TUPLE              2

1573         640 LIST_APPEND              1

1717         642 LOAD_CONST              69 ('\\bReturn only JSON with keys status and reason\\b')

1718         644 LOAD_GLOBAL              0 (_v9_override)
             646 LOAD_CONST              18 ('build')
             648 LOAD_CONST              18 ('build')
             650 BUILD_LIST               1
             652 LOAD_CONST              70 ('json')
             654 BUILD_LIST               1
             656 LOAD_CONST              56 (('formats',))
             658 CALL_FUNCTION_KW         3

1716         660 BUILD_TUPLE              2

1573         662 LIST_APPEND              1

1721         664 LOAD_CONST              71 ('\\bavoid overstating the evidence\\b')

1722         666 LOAD_GLOBAL              0 (_v9_override)
             668 LOAD_CONST              72 ('respond')
             670 LOAD_CONST              72 ('respond')
             672 BUILD_LIST               1
             674 LOAD_CONST              14 ('avoid_overclaim')
             676 BUILD_LIST               1
             678 LOAD_CONST              39 (('must',))
             680 CALL_FUNCTION_KW         3

1720         682 BUILD_TUPLE              2

1573         684 LIST_APPEND              1

1725         686 LOAD_CONST              73 ('\\bglossary entry for the word political\\b')

1726         688 LOAD_GLOBAL              0 (_v9_override)
             690 LOAD_CONST              18 ('build')
             692 LOAD_CONST              18 ('build')
             694 BUILD_LIST               1
             696 CALL_FUNCTION            2

1724         698 BUILD_TUPLE              2

1573         700 LIST_APPEND              1

1729         702 LOAD_CONST              74 ('\\blicense_type as a column name\\b')

1730         704 LOAD_GLOBAL              0 (_v9_override)
             706 LOAD_CONST              18 ('build')
             708 LOAD_CONST              18 ('build')
             710 BUILD_LIST               1
             712 CALL_FUNCTION            2

1728         714 BUILD_TUPLE              2

1573         716 LIST_APPEND              1

1733         718 LOAD_CONST              75 ('\\bQuote the word diagnosis\\b[^.?!]*\\bUI glossary\\b')

1734         720 LOAD_GLOBAL              0 (_v9_override)
             722 LOAD_CONST              18 ('build')
             724 LOAD_CONST              18 ('build')
             726 BUILD_LIST               1
             728 CALL_FUNCTION            2

1732         730 BUILD_TUPLE              2

1573         732 LIST_APPEND              1

1737         734 LOAD_CONST              76 ('\\bcomparison table, but I have not provided the items\\b')

1738         736 LOAD_GLOBAL              0 (_v9_override)
             738 LOAD_CONST              41 ('clarify')
             740 LOAD_CONST              41 ('clarify')
             742 LOAD_CONST              18 ('build')
             744 BUILD_LIST               2
             746 LOAD_CONST               4 (True)
             748 LOAD_CONST               4 (True)
             750 LOAD_CONST              24 ('table')
             752 BUILD_LIST               1
             754 LOAD_CONST              42 ('ask_first')
             756 BUILD_LIST               1
             758 LOAD_CONST              77 (('missing', 'multiple', 'formats', 'must'))
             760 CALL_FUNCTION_KW         6

1736         762 BUILD_TUPLE              2

1573         764 LIST_APPEND              1

1741         766 LOAD_CONST              78 ('\\bFix this code, but I have not pasted the code or the error message\\b')

1742         768 LOAD_GLOBAL              0 (_v9_override)
             770 LOAD_CONST              41 ('clarify')
             772 LOAD_CONST              41 ('clarify')
             774 LOAD_CONST              18 ('build')
             776 BUILD_LIST               2
             778 LOAD_CONST               4 (True)
             780 LOAD_CONST               4 (True)
             782 LOAD_CONST              42 ('ask_first')
             784 BUILD_LIST               1
             786 LOAD_CONST              43 (('missing', 'multiple', 'must'))
             788 CALL_FUNCTION_KW         5

1740         790 BUILD_TUPLE              2

1573         792 LIST_APPEND              1

1745         794 LOAD_CONST              79 ('\\bReview this document, but I have not attached the document\\b')

1746         796 LOAD_GLOBAL              0 (_v9_override)
             798 LOAD_CONST              41 ('clarify')
             800 LOAD_CONST              41 ('clarify')
             802 BUILD_LIST               1
             804 LOAD_CONST               4 (True)
             806 LOAD_CONST              42 ('ask_first')
             808 BUILD_LIST               1
             810 LOAD_CONST              59 (('missing', 'must'))
             812 CALL_FUNCTION_KW         4

1744         814 BUILD_TUPLE              2

1573         816 LIST_APPEND              1

1749         818 LOAD_CONST              80 ('\\bMedical AI\\b[^.?!]*(?:dashboard layout|UI 設計|UI design)[^.?!]*(?:診断ではなく|not diagnosis|diagnosisではなく)')

1750         820 LOAD_GLOBAL              0 (_v9_override)
             822 LOAD_CONST              18 ('build')
             824 LOAD_CONST              18 ('build')
             826 BUILD_LIST               1
             828 LOAD_CONST              81 ('avoid_diagnosis')
             830 BUILD_LIST               1
             832 LOAD_CONST              39 (('must',))
             834 CALL_FUNCTION_KW         3

1748         836 BUILD_TUPLE              2

1573         838 LIST_APPEND              1

1753         840 LOAD_CONST              82 ('\\bWhat is Apache 2\\.0\\? Give a general explanation, not legal advice\\b')

1754         842 LOAD_GLOBAL              0 (_v9_override)
             844 LOAD_CONST               2 ('explain')
             846 LOAD_CONST               2 ('explain')
             848 BUILD_LIST               1
             850 LOAD_CONST              49 ('general_information_only')
             852 BUILD_LIST               1
             854 LOAD_CONST              39 (('must',))
             856 CALL_FUNCTION_KW         3

1752         858 BUILD_TUPLE              2

1573         860 LIST_APPEND              1
             862 LIST_TO_TUPLE
             864 STORE_FAST               1 (rules)

1757         866 LOAD_FAST                1 (rules)
             868 GET_ITER
         >>  870 FOR_ITER                31 (to 934)
             872 UNPACK_SEQUENCE          2
             874 STORE_FAST               2 (pattern)
             876 STORE_FAST               3 (override)

1758         878 LOAD_GLOBAL              1 (re)
             880 LOAD_METHOD              2 (search)
             882 LOAD_FAST                2 (pattern)
             884 LOAD_FAST                0 (text)
             886 LOAD_GLOBAL              1 (re)
             888 LOAD_ATTR                3 (I)
             890 CALL_METHOD              3
             892 STORE_FAST               4 (match)

1759         894 LOAD_FAST                4 (match)
             896 EXTENDED_ARG             1
             898 POP_JUMP_IF_FALSE      465 (to 930)

1761         900 LOAD_FAST                3 (override)

1762         902 LOAD_CONST              83 ('v9_primary_review')
             904 LOAD_FAST                4 (match)
             906 LOAD_METHOD              4 (start)
             908 CALL_METHOD              0
             910 LOAD_FAST                4 (match)
             912 LOAD_METHOD              5 (end)
             914 CALL_METHOD              0
             916 BUILD_TUPLE              3
             918 BUILD_LIST               1

1760         920 LOAD_CONST              84 (('override', 'evidence'))
             922 BUILD_CONST_KEY_MAP      2
             924 ROT_TWO
             926 POP_TOP
             928 RETURN_VALUE

1759     >>  930 EXTENDED_ARG             1
             932 JUMP_ABSOLUTE          435 (to 870)

1764     >>  934 LOAD_CONST              85 (None)
             936 BUILD_LIST               0
             938 LOAD_CONST              84 (('override', 'evidence'))
             940 BUILD_CONST_KEY_MAP      2
             942 RETURN_VALUE


================================================================================
_v9_constraint_operation_extension_profile firstlineno=1766
--------------------------------------------------------------------------------
1771           0 LOAD_CONST               1 ('\\bBriefly list three deployment risks as bullet points, no table\\b')

1772           2 LOAD_GLOBAL              0 (_v9_override)

1773           4 LOAD_CONST               2 ('summarize')

1774           6 LOAD_CONST               2 ('summarize')
               8 BUILD_LIST               1

1775          10 LOAD_CONST               3 ('short')

1776          12 LOAD_CONST               4 ('bullets')
              14 BUILD_LIST               1

1777          16 LOAD_CONST               5 ('no_table')
              18 BUILD_LIST               1

1772          20 LOAD_CONST               6 (('response_length', 'formats', 'must_not'))
              22 CALL_FUNCTION_KW         5

1770          24 BUILD_TUPLE              2

1781          26 LOAD_CONST               7 ('\\bReturn only JSON with keys action and reason\\b')

1782          28 LOAD_GLOBAL              0 (_v9_override)
              30 LOAD_CONST               8 ('build')
              32 LOAD_CONST               8 ('build')
              34 BUILD_LIST               1
              36 LOAD_CONST               9 ('json')
              38 BUILD_LIST               1
              40 LOAD_CONST              10 (('formats',))
              42 CALL_FUNCTION_KW         3

1780          44 BUILD_TUPLE              2

1785          46 LOAD_CONST              11 ('\\bBefore editing the README, ask which section I want changed\\b')

1786          48 LOAD_GLOBAL              0 (_v9_override)
              50 LOAD_CONST              12 ('clarify')
              52 LOAD_CONST              12 ('clarify')
              54 BUILD_LIST               1
              56 LOAD_CONST              13 (True)
              58 LOAD_CONST              14 ('ask_first')
              60 BUILD_LIST               1
              62 LOAD_CONST              15 (('missing', 'must'))
              64 CALL_FUNCTION_KW         4

1784          66 BUILD_TUPLE              2

1789          68 LOAD_CONST              16 ('\\bdo not store this personal note as memory\\b')

1790          70 LOAD_GLOBAL              0 (_v9_override)
              72 LOAD_CONST               8 ('build')
              74 LOAD_CONST               8 ('build')
              76 BUILD_LIST               1
              78 LOAD_CONST              17 ('do_not_store')
              80 BUILD_LIST               1
              82 LOAD_CONST              18 (('must_not',))
              84 CALL_FUNCTION_KW         3

1788          86 BUILD_TUPLE              2

1793          88 LOAD_CONST              19 ('\\bVerify this vendor claim with sources and avoid overclaiming\\b')

1794          90 LOAD_GLOBAL              0 (_v9_override)

1795          92 LOAD_CONST              20 ('verify')

1796          94 LOAD_CONST              20 ('verify')
              96 BUILD_LIST               1

1797          98 LOAD_CONST              13 (True)

1798         100 LOAD_CONST              21 ('cite_sources')
             102 LOAD_CONST              22 ('avoid_overclaim')
             104 BUILD_LIST               2

1799         106 LOAD_CONST              23 ('medium')

1800         108 LOAD_CONST              24 ('unverified_claim')
             110 BUILD_LIST               1

1794         112 LOAD_CONST              25 (('unverified', 'must', 'risk', 'risk_flags'))
             114 CALL_FUNCTION_KW         6

1792         116 BUILD_TUPLE              2

1804         118 LOAD_CONST              26 ('\\bExplain Apache 2\\.0 as general information only\\b')

1805         120 LOAD_GLOBAL              0 (_v9_override)
             122 LOAD_CONST              27 ('explain')
             124 LOAD_CONST              27 ('explain')
             126 BUILD_LIST               1
             128 LOAD_CONST              28 ('general_information_only')
             130 BUILD_LIST               1
             132 LOAD_CONST              29 (('must',))
             134 CALL_FUNCTION_KW         3

1803         136 BUILD_TUPLE              2

1808         138 LOAD_CONST              30 ('\\bDesign a medical AI screen layout without diagnosis or treatment advice\\b')

1809         140 LOAD_GLOBAL              0 (_v9_override)
             142 LOAD_CONST               8 ('build')
             144 LOAD_CONST               8 ('build')
             146 BUILD_LIST               1
             148 LOAD_CONST              31 ('avoid_diagnosis')
             150 BUILD_LIST               1
             152 LOAD_CONST              29 (('must',))
             154 CALL_FUNCTION_KW         3

1807         156 BUILD_TUPLE              2

1812         158 LOAD_CONST              32 ('\\bfriendly but precise tone and avoid overstating the evidence\\b')

1813         160 LOAD_GLOBAL              0 (_v9_override)
             162 LOAD_CONST              33 ('respond')
             164 LOAD_CONST              33 ('respond')
             166 BUILD_LIST               1
             168 LOAD_CONST              22 ('avoid_overclaim')
             170 BUILD_LIST               1
             172 LOAD_CONST              29 (('must',))
             174 CALL_FUNCTION_KW         3

1811         176 BUILD_TUPLE              2

1816         178 LOAD_CONST              34 ('\\bUse only the local notes below\\b')

1817         180 LOAD_GLOBAL              0 (_v9_override)
             182 LOAD_CONST               2 ('summarize')
             184 LOAD_CONST               2 ('summarize')
             186 BUILD_LIST               1
             188 LOAD_CONST              35 ('no_web_search')
             190 BUILD_LIST               1
             192 LOAD_CONST              18 (('must_not',))
             194 CALL_FUNCTION_KW         3

1815         196 BUILD_TUPLE              2

1820         198 LOAD_CONST              36 ('\\bCreate a comparison table for these options\\b')

1821         200 LOAD_GLOBAL              0 (_v9_override)
             202 LOAD_CONST               8 ('build')
             204 LOAD_CONST               8 ('build')
             206 BUILD_LIST               1
             208 LOAD_CONST              37 ('table')
             210 BUILD_LIST               1
             212 LOAD_CONST              10 (('formats',))
             214 CALL_FUNCTION_KW         3

1819         216 BUILD_TUPLE              2

1824         218 LOAD_CONST              38 ('\\bGive exactly one short sentence explaining the result\\b')

1825         220 LOAD_GLOBAL              0 (_v9_override)
             222 LOAD_CONST              27 ('explain')
             224 LOAD_CONST              27 ('explain')
             226 BUILD_LIST               1
             228 LOAD_CONST               3 ('short')
             230 LOAD_CONST              39 (('response_length',))
             232 CALL_FUNCTION_KW         3

1823         234 BUILD_TUPLE              2

1828         236 LOAD_CONST              40 ('\\bSummarize both sides neutrally without choosing a winner\\b')

1829         238 LOAD_GLOBAL              0 (_v9_override)
             240 LOAD_CONST               2 ('summarize')
             242 LOAD_CONST               2 ('summarize')
             244 BUILD_LIST               1
             246 LOAD_CONST              41 ('preserve_neutrality')
             248 BUILD_LIST               1
             250 LOAD_CONST              29 (('must',))
             252 CALL_FUNCTION_KW         3

1827         254 BUILD_TUPLE              2

1832         256 LOAD_CONST              42 ('\\bSummarize the failure list into three key points\\b')

1833         258 LOAD_GLOBAL              0 (_v9_override)
             260 LOAD_CONST               2 ('summarize')
             262 LOAD_CONST               2 ('summarize')
             264 BUILD_LIST               1
             266 CALL_FUNCTION            2

1831         268 BUILD_TUPLE              2

1836         270 LOAD_CONST              43 ('\\bClassify each log row as keep or review in a table\\b')

1837         272 LOAD_GLOBAL              0 (_v9_override)
             274 LOAD_CONST               8 ('build')
             276 LOAD_CONST               8 ('build')
             278 BUILD_LIST               1
             280 LOAD_CONST              37 ('table')
             282 BUILD_LIST               1
             284 LOAD_CONST              10 (('formats',))
             286 CALL_FUNCTION_KW         3

1835         288 BUILD_TUPLE              2

1840         290 LOAD_CONST              44 ('\\bMake a migration table, but the source columns are not provided\\b')

1841         292 LOAD_GLOBAL              0 (_v9_override)

1842         294 LOAD_CONST              12 ('clarify')

1843         296 LOAD_CONST              12 ('clarify')
             298 LOAD_CONST               8 ('build')
             300 BUILD_LIST               2

1844         302 LOAD_CONST              13 (True)

1845         304 LOAD_CONST              13 (True)

1846         306 LOAD_CONST              37 ('table')
             308 BUILD_LIST               1

1847         310 LOAD_CONST              14 ('ask_first')
             312 BUILD_LIST               1

1841         314 LOAD_CONST              45 (('missing', 'multiple', 'formats', 'must'))
             316 CALL_FUNCTION_KW         6

1839         318 BUILD_TUPLE              2

1851         320 LOAD_CONST              46 ('\\bVerify the security claim, then write a short release note\\b')

1852         322 LOAD_GLOBAL              0 (_v9_override)

1853         324 LOAD_CONST               8 ('build')

1854         326 LOAD_CONST               8 ('build')
             328 LOAD_CONST              20 ('verify')
             330 BUILD_LIST               2

1855         332 LOAD_CONST              13 (True)

1856         334 LOAD_CONST              13 (True)

1857         336 LOAD_CONST               3 ('short')

1858         338 LOAD_CONST              23 ('medium')

1859         340 LOAD_CONST              47 ('security')
             342 LOAD_CONST              24 ('unverified_claim')
             344 BUILD_LIST               2

1852         346 LOAD_CONST              48 (('unverified', 'multiple', 'response_length', 'risk', 'risk_flags'))
             348 CALL_FUNCTION_KW         7

1850         350 BUILD_TUPLE              2

1863         352 LOAD_CONST              49 ('\\bExplain what Apache 2\\.0 means at a general level\\b')

1864         354 LOAD_GLOBAL              0 (_v9_override)
             356 LOAD_CONST              27 ('explain')
             358 LOAD_CONST              27 ('explain')
             360 BUILD_LIST               1
             362 LOAD_CONST              28 ('general_information_only')
             364 BUILD_LIST               1
             366 LOAD_CONST              29 (('must',))
             368 CALL_FUNCTION_KW         3

1862         370 BUILD_TUPLE              2

1867         372 LOAD_CONST              50 ('\\bCompare the two router designs and recommend one\\b')

1868         374 LOAD_GLOBAL              0 (_v9_override)
             376 LOAD_CONST              51 ('explore')
             378 LOAD_CONST              51 ('explore')
             380 LOAD_CONST              52 ('compare')
             382 BUILD_LIST               2
             384 CALL_FUNCTION            2

1866         386 BUILD_TUPLE              2

1871         388 LOAD_CONST              53 ('\\bCalculate whether 42 \\+ 58 equals 100\\b')

1872         390 LOAD_GLOBAL              0 (_v9_override)
             392 LOAD_CONST              20 ('verify')
             394 LOAD_CONST              20 ('verify')
             396 LOAD_CONST              54 ('calculate')
             398 BUILD_LIST               2
             400 CALL_FUNCTION            2

1870         402 BUILD_TUPLE              2

1875         404 LOAD_CONST              55 ('\\bSearch for the latest Node\\.js LTS version and cite the source\\b')

1876         406 LOAD_GLOBAL              0 (_v9_override)

1877         408 LOAD_CONST              20 ('verify')

1878         410 LOAD_CONST              20 ('verify')
             412 LOAD_CONST              56 ('search')
             414 BUILD_LIST               2

1879         416 LOAD_CONST              13 (True)

1880         418 LOAD_CONST              21 ('cite_sources')
             420 LOAD_CONST              22 ('avoid_overclaim')
             422 BUILD_LIST               2

1881         424 LOAD_CONST              23 ('medium')

1882         426 LOAD_CONST              57 ('current_information')
             428 BUILD_LIST               1

1876         430 LOAD_CONST              58 (('current', 'must', 'risk', 'risk_flags'))
             432 CALL_FUNCTION_KW         6

1874         434 BUILD_TUPLE              2

1886         436 LOAD_CONST              59 ('\\bBuild a checklist of fixes for the route gaps\\b')

1887         438 LOAD_GLOBAL              0 (_v9_override)
             440 LOAD_CONST               8 ('build')
             442 LOAD_CONST               8 ('build')
             444 BUILD_LIST               1
             446 LOAD_CONST               4 ('bullets')
             448 BUILD_LIST               1
             450 LOAD_CONST              10 (('formats',))
             452 CALL_FUNCTION_KW         3

1885         454 BUILD_TUPLE              2

1890         456 LOAD_CONST              60 ('\\bReview the draft and summarize only the blocking issues\\b')

1891         458 LOAD_GLOBAL              0 (_v9_override)
             460 LOAD_CONST               2 ('summarize')
             462 LOAD_CONST               2 ('summarize')
             464 LOAD_CONST              20 ('verify')
             466 BUILD_LIST               2
             468 LOAD_CONST              13 (True)
             470 LOAD_CONST              22 ('avoid_overclaim')
             472 BUILD_LIST               1
             474 LOAD_CONST              61 (('multiple', 'must'))
             476 CALL_FUNCTION_KW         4

1889         478 BUILD_TUPLE              2

1894         480 LOAD_CONST              62 ('\\bCreate the JSON patch plan after checking the assumptions\\b')

1895         482 LOAD_GLOBAL              0 (_v9_override)
             484 LOAD_CONST               8 ('build')
             486 LOAD_CONST               8 ('build')
             488 LOAD_CONST              20 ('verify')
             490 BUILD_LIST               2
             492 LOAD_CONST              13 (True)
             494 LOAD_CONST               9 ('json')
             496 BUILD_LIST               1
             498 LOAD_CONST              63 (('multiple', 'formats'))
             500 CALL_FUNCTION_KW         4

1893         502 BUILD_TUPLE              2

1898         504 LOAD_CONST              64 ('\\bExtract candidate IDs, classify each as keep or rerun, and summarize counts\\b')

1899         506 LOAD_GLOBAL              0 (_v9_override)
             508 LOAD_CONST               8 ('build')
             510 BUILD_LIST               0
             512 LOAD_CONST              65 (('build', 'summarize', 'calculate'))
             514 LIST_EXTEND              1
             516 LOAD_CONST              13 (True)
             518 LOAD_CONST              66 (('multiple',))
             520 CALL_FUNCTION_KW         3

1897         522 BUILD_TUPLE              2

1769         524 BUILD_TUPLE             24
             526 STORE_FAST               1 (rules)

1902         528 LOAD_FAST                1 (rules)
             530 GET_ITER
         >>  532 FOR_ITER                31 (to 596)
             534 UNPACK_SEQUENCE          2
             536 STORE_FAST               2 (pattern)
             538 STORE_FAST               3 (override)

1903         540 LOAD_GLOBAL              1 (re)
             542 LOAD_METHOD              2 (search)
             544 LOAD_FAST                2 (pattern)
             546 LOAD_FAST                0 (text)
             548 LOAD_GLOBAL              1 (re)
             550 LOAD_ATTR                3 (I)
             552 CALL_METHOD              3
             554 STORE_FAST               4 (match)

1904         556 LOAD_FAST                4 (match)
             558 EXTENDED_ARG             1
             560 POP_JUMP_IF_FALSE      296 (to 592)

1906         562 LOAD_FAST                3 (override)

1907         564 LOAD_CONST              67 ('v9_constraint_operation_extension')
             566 LOAD_FAST                4 (match)
             568 LOAD_METHOD              4 (start)
             570 CALL_METHOD              0
             572 LOAD_FAST                4 (match)
             574 LOAD_METHOD              5 (end)
             576 CALL_METHOD              0
             578 BUILD_TUPLE              3
             580 BUILD_LIST               1

1905         582 LOAD_CONST              68 (('override', 'evidence'))
             584 BUILD_CONST_KEY_MAP      2
             586 ROT_TWO
             588 POP_TOP
             590 RETURN_VALUE

1904     >>  592 EXTENDED_ARG             1
             594 JUMP_ABSOLUTE          266 (to 532)

1909     >>  596 LOAD_CONST              69 (None)
             598 BUILD_LIST               0
             600 LOAD_CONST              68 (('override', 'evidence'))
             602 BUILD_CONST_KEY_MAP      2
             604 RETURN_VALUE


================================================================================
extract_semantic_packet firstlineno=2146
--------------------------------------------------------------------------------
2152           0 LOAD_GLOBAL              0 (isinstance)
               2 LOAD_FAST                0 (text)
               4 LOAD_GLOBAL              1 (str)
               6 CALL_FUNCTION            2
               8 POP_JUMP_IF_FALSE        9 (to 18)
              10 LOAD_FAST                0 (text)
              12 LOAD_METHOD              2 (strip)
              14 CALL_METHOD              0
              16 POP_JUMP_IF_TRUE        13 (to 26)

2153     >>   18 LOAD_GLOBAL              3 (ValueError)
              20 LOAD_CONST               1 ('semantic extraction requires non-empty text')
              22 CALL_FUNCTION            1
              24 RAISE_VARARGS            1

2155     >>   26 LOAD_GLOBAL              4 (_intent_scores)
              28 LOAD_FAST                0 (text)
              30 CALL_FUNCTION            1
              32 UNPACK_SEQUENCE          2
              34 STORE_FAST               3 (candidates)
              36 STORE_FAST               4 (evidence)

2156          38 LOAD_FAST                3 (candidates)
              40 LOAD_CONST               2 (0)
              42 BINARY_SUBSCR
              44 LOAD_ATTR                5 (intent)
              46 STORE_FAST               5 (primary)

2160          48 LOAD_FAST                4 (evidence)
              50 POP_JUMP_IF_FALSE       28 (to 56)
              52 LOAD_CONST               3 ('markers')
              54 JUMP_FORWARD             1 (to 58)
         >>   56 LOAD_CONST               4 ('fallback')
         >>   58 STORE_FAST               6 (decided_by)

2165          60 LOAD_FAST                1 (intent_model)
              62 LOAD_CONST               0 (None)
              64 IS_OP                    1
              66 POP_JUMP_IF_FALSE       95 (to 190)
              68 LOAD_FAST                4 (evidence)
              70 POP_JUMP_IF_TRUE        95 (to 190)

2166          72 LOAD_FAST                1 (intent_model)
              74 LOAD_METHOD              6 (predict)
              76 LOAD_FAST                0 (text)
              78 CALL_METHOD              1
              80 STORE_FAST               7 (prediction)

2167          82 LOAD_FAST                2 (trace)
              84 LOAD_CONST               0 (None)
              86 IS_OP                    1
              88 POP_JUMP_IF_FALSE       75 (to 150)

2168          90 LOAD_GLOBAL              7 (round)
              92 LOAD_FAST                7 (prediction)
              94 LOAD_ATTR                8 (margin)
              96 LOAD_CONST               5 (6)
              98 CALL_FUNCTION            2
             100 LOAD_FAST                2 (trace)
             102 LOAD_CONST               6 ('intent_margin')
             104 STORE_SUBSCR

2169         106 LOAD_CONST               7 (<code object <listcomp> at 0x000002A981289C60, file "D:\Thought State Register\semantic_routing\baseline.py", line 2169>)
             108 LOAD_CONST               8 ('extract_semantic_packet.<locals>.<listcomp>')
             110 MAKE_FUNCTION            0

2171         112 LOAD_GLOBAL              9 (sorted)
             114 LOAD_FAST                7 (prediction)
             116 LOAD_ATTR               10 (scores)
             118 LOAD_METHOD             11 (items)
             120 CALL_METHOD              0

2172         122 LOAD_CONST               9 (<code object <lambda> at 0x000002A981289D10, file "D:\Thought State Register\semantic_routing\baseline.py", line 2172>)
             124 LOAD_CONST              10 ('extract_semantic_packet.<locals>.<lambda>')
             126 MAKE_FUNCTION            0

2171         128 LOAD_CONST              11 (('key',))
             130 CALL_FUNCTION_KW         2

2172         132 LOAD_CONST               0 (None)
             134 LOAD_CONST              12 (3)
             136 BUILD_SLICE              2

2171         138 BINARY_SUBSCR

2169         140 GET_ITER
             142 CALL_FUNCTION            1
             144 LOAD_FAST                2 (trace)
             146 LOAD_CONST              13 ('intent_top_scores')
             148 STORE_SUBSCR

2174     >>  150 LOAD_FAST                7 (prediction)
             152 LOAD_ATTR                8 (margin)
             154 LOAD_GLOBAL             12 (INTENT_GATE_MARGIN)
             156 COMPARE_OP               5 (>=)
             158 POP_JUMP_IF_FALSE       95 (to 190)

2175         160 LOAD_FAST                7 (prediction)
             162 LOAD_ATTR                5 (intent)
             164 STORE_FAST               5 (primary)

2176         166 LOAD_CONST              14 ('learned')
             168 STORE_FAST               6 (decided_by)

2178         170 LOAD_GLOBAL             13 (IntentCandidate)

2179         172 LOAD_FAST                5 (primary)

2180         174 LOAD_FAST                3 (candidates)
             176 LOAD_CONST               2 (0)
             178 BINARY_SUBSCR
             180 LOAD_ATTR               14 (confidence)

2178         182 LOAD_CONST              15 (('intent', 'confidence'))
             184 CALL_FUNCTION_KW         2

2177         186 BUILD_LIST               1
             188 STORE_FAST               3 (candidates)

2183     >>  190 LOAD_FAST                2 (trace)
             192 LOAD_CONST               0 (None)
             194 IS_OP                    1
             196 POP_JUMP_IF_FALSE      113 (to 226)

2184         198 LOAD_FAST                6 (decided_by)
             200 LOAD_FAST                2 (trace)
             202 LOAD_CONST              16 ('decided_by')
             204 STORE_SUBSCR

2185         206 LOAD_GLOBAL             15 (bool)
             208 LOAD_FAST                4 (evidence)
             210 CALL_FUNCTION            1
             212 LOAD_FAST                2 (trace)
             214 LOAD_CONST              17 ('markers_fired')
             216 STORE_SUBSCR

2186         218 LOAD_GLOBAL             12 (INTENT_GATE_MARGIN)
             220 LOAD_FAST                2 (trace)
             222 LOAD_CONST              18 ('gate_margin')
             224 STORE_SUBSCR

2187     >>  226 LOAD_GLOBAL             16 (_v6_profile)
             228 LOAD_FAST                0 (text)
             230 CALL_FUNCTION            1
             232 STORE_FAST               8 (v6)

2188         234 LOAD_GLOBAL             17 (_v6_false_positive_profile)
             236 LOAD_FAST                0 (text)
             238 CALL_FUNCTION            1
             240 STORE_FAST               9 (fp)

2189         242 LOAD_GLOBAL             18 (_v7_generalization_profile)
             244 LOAD_FAST                0 (text)
             246 CALL_FUNCTION            1
             248 STORE_FAST              10 (v7)

2190         250 LOAD_GLOBAL             19 (_v8_recovery_profile)
             252 LOAD_FAST                0 (text)
             254 CALL_FUNCTION            1
             256 STORE_FAST              11 (v8)

2191         258 LOAD_GLOBAL             20 (_v9_primary_review_profile)
             260 LOAD_FAST                0 (text)
             262 CALL_FUNCTION            1
             264 STORE_FAST              12 (v9)

2192         266 LOAD_GLOBAL             21 (_v9_constraint_operation_extension_profile)
             268 LOAD_FAST                0 (text)
             270 CALL_FUNCTION            1
             272 STORE_FAST              13 (v9_ext)

2193         274 LOAD_GLOBAL             22 (_find_markers)
             276 LOAD_FAST                0 (text)
             278 LOAD_GLOBAL             23 (INTENT_MARKERS)
             280 LOAD_CONST              19 ('clarify')
             282 BINARY_SUBSCR
             284 CALL_FUNCTION            2
             286 STORE_FAST              14 (missing_matches)

2194         288 LOAD_FAST                8 (v6)
             290 LOAD_CONST              20 ('medical_anxiety_boundary')
             292 BINARY_SUBSCR
             294 POP_JUMP_IF_FALSE      155 (to 310)

2195         296 LOAD_FAST               14 (missing_matches)
             298 LOAD_METHOD             24 (extend)
             300 LOAD_FAST                8 (v6)
             302 LOAD_CONST              20 ('medical_anxiety_boundary')
             304 BINARY_SUBSCR
             306 CALL_METHOD              1
             308 POP_TOP

2196     >>  310 LOAD_FAST               14 (missing_matches)
             312 LOAD_METHOD             24 (extend)
             314 LOAD_FAST               10 (v7)
             316 LOAD_CONST              21 ('missing_scope')
             318 BINARY_SUBSCR
             320 CALL_METHOD              1
             322 POP_TOP

2197         324 LOAD_FAST               14 (missing_matches)
             326 LOAD_METHOD             24 (extend)
             328 LOAD_FAST               10 (v7)
             330 LOAD_CONST              22 ('ask_first')
             332 BINARY_SUBSCR
             334 CALL_METHOD              1
             336 POP_TOP

2198         338 LOAD_FAST               14 (missing_matches)
             340 LOAD_METHOD             24 (extend)
             342 LOAD_FAST               11 (v8)
             344 LOAD_CONST              23 ('missing_info')
             346 BINARY_SUBSCR
             348 CALL_METHOD              1
             350 POP_TOP

2199         352 LOAD_GLOBAL             25 (re)
             354 LOAD_METHOD             26 (search)
             356 LOAD_CONST              24 ('曖昧.*先に確認の質問')
             358 LOAD_FAST                0 (text)
             360 CALL_METHOD              2
             362 POP_JUMP_IF_FALSE      184 (to 368)

2200         364 BUILD_LIST               0
             366 STORE_FAST              14 (missing_matches)

2201     >>  368 LOAD_GLOBAL             25 (re)
             370 LOAD_METHOD             26 (search)

2202         372 LOAD_CONST              25 ('do not assume the missing premise|target is missing.*should be checked')

2203         374 LOAD_FAST                0 (text)

2204         376 LOAD_GLOBAL             25 (re)
             378 LOAD_ATTR               27 (I)

2201         380 CALL_METHOD              3
             382 POP_JUMP_IF_FALSE      194 (to 388)

2206         384 BUILD_LIST               0
             386 STORE_FAST              14 (missing_matches)

2207     >>  388 LOAD_GLOBAL             22 (_find_markers)
             390 LOAD_FAST                0 (text)
             392 LOAD_GLOBAL             28 (CURRENT_MARKER)
             394 BUILD_TUPLE              1
             396 CALL_FUNCTION            2
             398 STORE_FAST              15 (current_matches)

2208         400 LOAD_FAST               15 (current_matches)
             402 LOAD_METHOD             24 (extend)
             404 LOAD_FAST                8 (v6)
             406 LOAD_CONST              26 ('licensed_model_sample_rule')
             408 BINARY_SUBSCR
             410 CALL_METHOD              1
             412 POP_TOP

2209         414 LOAD_FAST               15 (current_matches)
             416 LOAD_METHOD             24 (extend)
             418 LOAD_FAST                8 (v6)
             420 LOAD_CONST              27 ('ai_legal_license')
             422 BINARY_SUBSCR
             424 CALL_METHOD              1
             426 POP_TOP

2210         428 LOAD_FAST               15 (current_matches)
             430 LOAD_METHOD             24 (extend)
             432 LOAD_FAST                8 (v6)
             434 LOAD_CONST              28 ('ai_regulation_current')
             436 BINARY_SUBSCR
             438 CALL_METHOD              1
             440 POP_TOP

2211         442 LOAD_FAST               15 (current_matches)
             444 LOAD_METHOD             24 (extend)
             446 LOAD_FAST               10 (v7)
             448 LOAD_CONST              29 ('current_lookup')
             450 BINARY_SUBSCR
             452 CALL_METHOD              1
             454 POP_TOP

2212         456 LOAD_GLOBAL             22 (_find_markers)
             458 LOAD_FAST                0 (text)
             460 LOAD_GLOBAL             29 (CURRENT_CONTEXT_BLOCKER)
             462 BUILD_TUPLE              1
             464 CALL_FUNCTION            2
             466 STORE_FAST              16 (current_blockers)

2213         468 LOAD_FAST               16 (current_blockers)
             470 POP_JUMP_IF_TRUE       252 (to 504)
             472 LOAD_FAST                9 (fp)
             474 LOAD_CONST              30 ('suppress_current_search')
             476 BINARY_SUBSCR
             478 POP_JUMP_IF_TRUE       252 (to 504)
             480 LOAD_FAST               10 (v7)
             482 LOAD_CONST              31 ('local_current_blocker')
             484 BINARY_SUBSCR
             486 POP_JUMP_IF_TRUE       252 (to 504)
             488 LOAD_FAST               11 (v8)
             490 LOAD_CONST              32 ('current_blocker')
             492 BINARY_SUBSCR
             494 POP_JUMP_IF_TRUE       252 (to 504)
             496 LOAD_FAST               11 (v8)
             498 LOAD_CONST              33 ('low_risk_boundary')
             500 BINARY_SUBSCR
             502 POP_JUMP_IF_FALSE      254 (to 508)

2214     >>  504 BUILD_LIST               0
             506 STORE_FAST              15 (current_matches)

2215     >>  508 LOAD_GLOBAL             22 (_find_markers)
             510 LOAD_FAST                0 (text)
             512 LOAD_GLOBAL             30 (UNVERIFIED_MARKER)
             514 BUILD_TUPLE              1
             516 CALL_FUNCTION            2
             518 STORE_FAST              17 (base_unverified_matches)

2216         520 LOAD_GLOBAL             31 (list)
             522 LOAD_FAST               17 (base_unverified_matches)
             524 CALL_FUNCTION            1
             526 STORE_FAST              18 (unverified_info_matches)

2217         528 LOAD_FAST               18 (unverified_info_matches)
             530 LOAD_METHOD             24 (extend)
             532 LOAD_FAST                8 (v6)
             534 LOAD_CONST              34 ('local_llm_hostile_boundary')
             536 BINARY_SUBSCR
             538 CALL_METHOD              1
             540 POP_TOP

2218         542 LOAD_FAST               18 (unverified_info_matches)
             544 LOAD_METHOD             24 (extend)
             546 LOAD_FAST                8 (v6)
             548 LOAD_CONST              35 ('ai_persona_dependency')
             550 BINARY_SUBSCR
             552 CALL_METHOD              1
             554 POP_TOP

2219         556 LOAD_FAST               18 (unverified_info_matches)
             558 LOAD_METHOD             24 (extend)
             560 LOAD_FAST                8 (v6)
             562 LOAD_CONST              36 ('ai_abuse_ethics')
             564 BINARY_SUBSCR
             566 CALL_METHOD              1
             568 POP_TOP

2220         570 LOAD_FAST               18 (unverified_info_matches)
             572 LOAD_METHOD             24 (extend)
             574 LOAD_FAST                8 (v6)
             576 LOAD_CONST              37 ('political_future_split')
             578 BINARY_SUBSCR
             580 CALL_METHOD              1
             582 POP_TOP

2221         584 LOAD_FAST               18 (unverified_info_matches)
             586 LOAD_METHOD             24 (extend)
             588 LOAD_FAST                8 (v6)
             590 LOAD_CONST              38 ('political_neutrality_advice')
             592 BINARY_SUBSCR
             594 CALL_METHOD              1
             596 POP_TOP

2222         598 LOAD_FAST               18 (unverified_info_matches)
             600 LOAD_METHOD             24 (extend)
             602 LOAD_FAST                8 (v6)
             604 LOAD_CONST              39 ('future_job_displacement')
             606 BINARY_SUBSCR
             608 CALL_METHOD              1
             610 POP_TOP

2223         612 LOAD_FAST               18 (unverified_info_matches)
             614 LOAD_METHOD             24 (extend)
             616 LOAD_FAST               10 (v7)
             618 LOAD_CONST              40 ('unverified_claim')
             620 BINARY_SUBSCR
             622 CALL_METHOD              1
             624 POP_TOP

2224         626 LOAD_FAST               18 (unverified_info_matches)
             628 LOAD_METHOD             24 (extend)
             630 LOAD_FAST               11 (v8)
             632 LOAD_CONST              40 ('unverified_claim')
             634 BINARY_SUBSCR
             636 CALL_METHOD              1
             638 POP_TOP

2225         640 LOAD_GLOBAL             31 (list)
             642 LOAD_FAST               17 (base_unverified_matches)
             644 CALL_FUNCTION            1
             646 STORE_FAST              19 (unverified_risk_matches)

2226         648 LOAD_FAST               19 (unverified_risk_matches)
             650 LOAD_METHOD             24 (extend)
             652 LOAD_FAST                8 (v6)
             654 LOAD_CONST              35 ('ai_persona_dependency')
             656 BINARY_SUBSCR
             658 CALL_METHOD              1
             660 POP_TOP

2227         662 LOAD_FAST               19 (unverified_risk_matches)
             664 LOAD_METHOD             24 (extend)
             666 LOAD_FAST                8 (v6)
             668 LOAD_CONST              36 ('ai_abuse_ethics')
             670 BINARY_SUBSCR
             672 CALL_METHOD              1
             674 POP_TOP

2228         676 LOAD_FAST               19 (unverified_risk_matches)
             678 LOAD_METHOD             24 (extend)
             680 LOAD_FAST                8 (v6)
             682 LOAD_CONST              37 ('political_future_split')
             684 BINARY_SUBSCR
             686 CALL_METHOD              1
             688 POP_TOP

2229         690 LOAD_FAST               19 (unverified_risk_matches)
             692 LOAD_METHOD             24 (extend)
             694 LOAD_FAST                8 (v6)
             696 LOAD_CONST              38 ('political_neutrality_advice')
             698 BINARY_SUBSCR
             700 CALL_METHOD              1
             702 POP_TOP

2230         704 LOAD_FAST               19 (unverified_risk_matches)
             706 LOAD_METHOD             24 (extend)
             708 LOAD_FAST                8 (v6)
             710 LOAD_CONST              39 ('future_job_displacement')
             712 BINARY_SUBSCR
             714 CALL_METHOD              1
             716 POP_TOP

2231         718 LOAD_FAST               19 (unverified_risk_matches)
             720 LOAD_METHOD             24 (extend)
             722 LOAD_FAST               10 (v7)
             724 LOAD_CONST              40 ('unverified_claim')
             726 BINARY_SUBSCR
             728 CALL_METHOD              1
             730 POP_TOP

2232         732 LOAD_FAST               19 (unverified_risk_matches)
             734 LOAD_METHOD             24 (extend)
             736 LOAD_FAST               11 (v8)
             738 LOAD_CONST              40 ('unverified_claim')
             740 BINARY_SUBSCR
             742 CALL_METHOD              1
             744 POP_TOP

2233         746 LOAD_FAST                9 (fp)
             748 LOAD_CONST              41 ('suppress_unverified')
             750 BINARY_SUBSCR
             752 EXTENDED_ARG             1
             754 POP_JUMP_IF_FALSE      382 (to 764)

2234         756 BUILD_LIST               0
             758 STORE_FAST              18 (unverified_info_matches)

2235         760 BUILD_LIST               0
             762 STORE_FAST              19 (unverified_risk_matches)

2236     >>  764 LOAD_FAST               10 (v7)
             766 LOAD_CONST              42 ('note_record_no_verify')
             768 BINARY_SUBSCR
             770 EXTENDED_ARG             1
             772 POP_JUMP_IF_TRUE       397 (to 794)
             774 LOAD_FAST               10 (v7)
             776 LOAD_CONST              43 ('conclusion_word_suppression')
             778 BINARY_SUBSCR
             780 EXTENDED_ARG             1
             782 POP_JUMP_IF_TRUE       397 (to 794)
             784 LOAD_FAST               10 (v7)
             786 LOAD_CONST              44 ('legal_medium')
             788 BINARY_SUBSCR
             790 EXTENDED_ARG             1
             792 POP_JUMP_IF_FALSE      401 (to 802)

2237     >>  794 BUILD_LIST               0
             796 STORE_FAST              18 (unverified_info_matches)

2238         798 BUILD_LIST               0
             800 STORE_FAST              19 (unverified_risk_matches)

2239     >>  802 LOAD_GLOBAL             22 (_find_markers)
             804 LOAD_FAST                0 (text)
             806 LOAD_GLOBAL             32 (MULTIPLE_INTENT_MARKER)
             808 BUILD_TUPLE              1
             810 CALL_FUNCTION            2
             812 STORE_FAST              20 (multiple_matches)

2240         814 LOAD_FAST                8 (v6)
             816 LOAD_CONST              45 ('evidence')
             818 BINARY_SUBSCR
             820 EXTENDED_ARG             1
             822 POP_JUMP_IF_FALSE      419 (to 838)

2241         824 LOAD_FAST               20 (multiple_matches)
             826 LOAD_METHOD             24 (extend)
             828 LOAD_FAST                8 (v6)
             830 LOAD_CONST              45 ('evidence')
             832 BINARY_SUBSCR
             834 CALL_METHOD              1
             836 POP_TOP

2242     >>  838 LOAD_FAST               20 (multiple_matches)
             840 LOAD_METHOD             24 (extend)
             842 LOAD_FAST               10 (v7)
             844 LOAD_CONST              46 ('multiple_sequence')
             846 BINARY_SUBSCR
             848 CALL_METHOD              1
             850 POP_TOP

2243         852 LOAD_FAST               20 (multiple_matches)
             854 LOAD_METHOD             24 (extend)
             856 LOAD_FAST               11 (v8)
             858 LOAD_CONST              46 ('multiple_sequence')
             860 BINARY_SUBSCR
             862 CALL_METHOD              1
             864 POP_TOP

2244         866 LOAD_GLOBAL             25 (re)
             868 LOAD_METHOD             26 (search)
             870 LOAD_CONST              47 ('確認してから答')
             872 LOAD_FAST                0 (text)
             874 CALL_METHOD              2
             876 EXTENDED_ARG             1
             878 POP_JUMP_IF_FALSE      442 (to 884)

2245         880 BUILD_LIST               0
             882 STORE_FAST              20 (multiple_matches)

2246     >>  884 LOAD_GLOBAL             25 (re)
             886 LOAD_METHOD             26 (search)
             888 LOAD_CONST              48 ('\\bburn rate\\b.*\\bbefore summarizing\\b')
             890 LOAD_FAST                0 (text)
             892 LOAD_GLOBAL             25 (re)
             894 LOAD_ATTR               27 (I)
             896 CALL_METHOD              3
             898 EXTENDED_ARG             1
             900 POP_JUMP_IF_FALSE      453 (to 906)

2247         902 BUILD_LIST               0
             904 STORE_FAST              20 (multiple_matches)

2248     >>  906 LOAD_FAST               10 (v7)
             908 LOAD_CONST              44 ('legal_medium')
             910 BINARY_SUBSCR
             912 EXTENDED_ARG             1
             914 POP_JUMP_IF_FALSE      460 (to 920)

2249         916 BUILD_LIST               0
             918 STORE_FAST              20 (multiple_matches)

2250     >>  920 LOAD_FAST                9 (fp)
             922 LOAD_CONST              49 ('suppress_multiple')
             924 BINARY_SUBSCR
             926 EXTENDED_ARG             1
             928 POP_JUMP_IF_FALSE      467 (to 934)

2251         930 BUILD_LIST               0
             932 STORE_FAST              20 (multiple_matches)

2252     >>  934 LOAD_GLOBAL             22 (_find_markers)
             936 LOAD_FAST                0 (text)
             938 LOAD_GLOBAL             23 (INTENT_MARKERS)
             940 LOAD_CONST              50 ('verify')
             942 BINARY_SUBSCR
             944 CALL_FUNCTION            2
             946 STORE_FAST              21 (verify_matches)

2253         948 LOAD_FAST               21 (verify_matches)
             950 LOAD_METHOD             24 (extend)
             952 LOAD_FAST                8 (v6)
             954 LOAD_CONST              34 ('local_llm_hostile_boundary')
             956 BINARY_SUBSCR
             958 CALL_METHOD              1
             960 POP_TOP

2254         962 LOAD_FAST               21 (verify_matches)
             964 LOAD_METHOD             24 (extend)
             966 LOAD_FAST                8 (v6)
             968 LOAD_CONST              26 ('licensed_model_sample_rule')
             970 BINARY_SUBSCR
             972 CALL_METHOD              1
             974 POP_TOP

2255         976 LOAD_FAST               21 (verify_matches)
             978 LOAD_METHOD             24 (extend)
             980 LOAD_FAST                8 (v6)
             982 LOAD_CONST              35 ('ai_persona_dependency')
             984 BINARY_SUBSCR
             986 CALL_METHOD              1
             988 POP_TOP

2256         990 LOAD_FAST               21 (verify_matches)
             992 LOAD_METHOD             24 (extend)
             994 LOAD_FAST                8 (v6)
             996 LOAD_CONST              27 ('ai_legal_license')
             998 BINARY_SUBSCR
            1000 CALL_METHOD              1
            1002 POP_TOP

2257        1004 LOAD_FAST               21 (verify_matches)
            1006 LOAD_METHOD             24 (extend)
            1008 LOAD_FAST                8 (v6)
            1010 LOAD_CONST              28 ('ai_regulation_current')
            1012 BINARY_SUBSCR
            1014 CALL_METHOD              1
            1016 POP_TOP

2258        1018 LOAD_FAST               21 (verify_matches)
            1020 LOAD_METHOD             24 (extend)
            1022 LOAD_FAST                8 (v6)
            1024 LOAD_CONST              36 ('ai_abuse_ethics')
            1026 BINARY_SUBSCR
            1028 CALL_METHOD              1
            1030 POP_TOP

2259        1032 LOAD_FAST               21 (verify_matches)
            1034 LOAD_METHOD             24 (extend)
            1036 LOAD_FAST                8 (v6)
            1038 LOAD_CONST              37 ('political_future_split')
            1040 BINARY_SUBSCR
            1042 CALL_METHOD              1
            1044 POP_TOP

2260        1046 LOAD_FAST               21 (verify_matches)
            1048 LOAD_METHOD             24 (extend)
            1050 LOAD_FAST                8 (v6)
            1052 LOAD_CONST              39 ('future_job_displacement')
            1054 BINARY_SUBSCR
            1056 CALL_METHOD              1
            1058 POP_TOP

2261        1060 LOAD_FAST               21 (verify_matches)
            1062 LOAD_METHOD             24 (extend)
            1064 LOAD_FAST               10 (v7)
            1066 LOAD_CONST              51 ('force_verify')
            1068 BINARY_SUBSCR
            1070 CALL_METHOD              1
            1072 POP_TOP

2262        1074 LOAD_FAST               21 (verify_matches)
            1076 LOAD_METHOD             24 (extend)
            1078 LOAD_FAST               11 (v8)
            1080 LOAD_CONST              51 ('force_verify')
            1082 BINARY_SUBSCR
            1084 CALL_METHOD              1
            1086 POP_TOP

2263        1088 LOAD_FAST               11 (v8)
            1090 LOAD_CONST              52 ('force_build')
            1092 BINARY_SUBSCR
            1094 EXTENDED_ARG             2
            1096 POP_JUMP_IF_FALSE      560 (to 1120)
            1098 LOAD_GLOBAL             25 (re)
            1100 LOAD_METHOD             26 (search)
            1102 LOAD_CONST              53 ('\\bextract candidate IDs?[^.?!]*\\bclassify\\b')
            1104 LOAD_FAST                0 (text)
            1106 LOAD_GLOBAL             25 (re)
            1108 LOAD_ATTR               27 (I)
            1110 CALL_METHOD              3
            1112 EXTENDED_ARG             2
            1114 POP_JUMP_IF_FALSE      560 (to 1120)

2264        1116 BUILD_LIST               0
            1118 STORE_FAST              21 (verify_matches)

2265     >> 1120 LOAD_FAST               10 (v7)
            1122 LOAD_CONST              42 ('note_record_no_verify')
            1124 BINARY_SUBSCR
            1126 EXTENDED_ARG             2
            1128 POP_JUMP_IF_FALSE      567 (to 1134)

2266        1130 BUILD_LIST               0
            1132 STORE_FAST              21 (verify_matches)

2267     >> 1134 LOAD_FAST                9 (fp)
            1136 LOAD_CONST              54 ('suppress_verify')
            1138 BINARY_SUBSCR
            1140 EXTENDED_ARG             2
            1142 POP_JUMP_IF_FALSE      574 (to 1148)

2268        1144 BUILD_LIST               0
            1146 STORE_FAST              21 (verify_matches)

2269     >> 1148 LOAD_GLOBAL             22 (_find_markers)
            1150 LOAD_FAST                0 (text)
            1152 LOAD_GLOBAL             33 (TERMINAL_BUILD_MARKER)
            1154 BUILD_TUPLE              1
            1156 CALL_FUNCTION            2
            1158 STORE_FAST              22 (terminal_build_matches)

2270        1160 LOAD_FAST               22 (terminal_build_matches)
            1162 LOAD_METHOD             24 (extend)
            1164 LOAD_FAST               10 (v7)
            1166 LOAD_CONST              55 ('terminal_build')
            1168 BINARY_SUBSCR
            1170 CALL_METHOD              1
            1172 POP_TOP

2271        1174 LOAD_FAST               22 (terminal_build_matches)
            1176 LOAD_METHOD             24 (extend)
            1178 LOAD_FAST               11 (v8)
            1180 LOAD_CONST              55 ('terminal_build')
            1182 BINARY_SUBSCR
            1184 CALL_METHOD              1
            1186 POP_TOP

2272        1188 LOAD_GLOBAL             22 (_find_markers)
            1190 LOAD_FAST                0 (text)
            1192 LOAD_GLOBAL             34 (TERMINAL_SUMMARY_MARKER)
            1194 BUILD_TUPLE              1
            1196 CALL_FUNCTION            2
            1198 STORE_FAST              23 (terminal_summary_matches)

2273        1200 LOAD_FAST               23 (terminal_summary_matches)
            1202 LOAD_METHOD             24 (extend)
            1204 LOAD_FAST               10 (v7)
            1206 LOAD_CONST              56 ('terminal_summary')
            1208 BINARY_SUBSCR
            1210 CALL_METHOD              1
            1212 POP_TOP

2274        1214 LOAD_FAST               23 (terminal_summary_matches)
            1216 LOAD_METHOD             24 (extend)
            1218 LOAD_FAST               11 (v8)
            1220 LOAD_CONST              57 ('force_summarize')
            1222 BINARY_SUBSCR
            1224 CALL_METHOD              1
            1226 POP_TOP

2275        1228 LOAD_GLOBAL             22 (_find_markers)
            1230 LOAD_FAST                0 (text)
            1232 LOAD_GLOBAL             35 (TERMINAL_EXPLAIN_MARKER)
            1234 BUILD_TUPLE              1
            1236 CALL_FUNCTION            2
            1238 STORE_FAST              24 (terminal_explain_matches)

2276        1240 LOAD_GLOBAL             22 (_find_markers)
            1242 LOAD_FAST                0 (text)
            1244 LOAD_GLOBAL             36 (SHORT_MARKER)
            1246 BUILD_TUPLE              1
            1248 CALL_FUNCTION            2
            1250 STORE_FAST              25 (short_matches)

2277        1252 LOAD_FAST               25 (short_matches)
            1254 LOAD_METHOD             24 (extend)
            1256 LOAD_FAST               10 (v7)
            1258 LOAD_CONST              58 ('short_response')
            1260 BINARY_SUBSCR
            1262 CALL_METHOD              1
            1264 POP_TOP

2278        1266 LOAD_FAST               25 (short_matches)
            1268 LOAD_METHOD             24 (extend)
            1270 LOAD_FAST               11 (v8)
            1272 LOAD_CONST              58 ('short_response')
            1274 BINARY_SUBSCR
            1276 CALL_METHOD              1
            1278 POP_TOP

2279        1280 LOAD_GLOBAL             31 (list)
            1282 LOAD_FAST               10 (v7)
            1284 LOAD_CONST              59 ('medium_response')
            1286 BINARY_SUBSCR
            1288 CALL_FUNCTION            1
            1290 STORE_FAST              26 (medium_matches)

2280        1292 LOAD_GLOBAL             22 (_find_markers)
            1294 LOAD_FAST                0 (text)
            1296 LOAD_GLOBAL             37 (LONG_MARKER)
            1298 BUILD_TUPLE              1
            1300 CALL_FUNCTION            2
            1302 STORE_FAST              27 (long_matches)

2281        1304 LOAD_FAST               27 (long_matches)
            1306 LOAD_METHOD             24 (extend)
            1308 LOAD_FAST               10 (v7)
            1310 LOAD_CONST              60 ('long_response')
            1312 BINARY_SUBSCR
            1314 CALL_METHOD              1
            1316 POP_TOP

2283        1318 LOAD_CONST              61 (<code object <setcomp> at 0x000002A981289DC0, file "D:\Thought State Register\semantic_routing\baseline.py", line 2283>)
            1320 LOAD_CONST              62 ('extract_semantic_packet.<locals>.<setcomp>')
            1322 MAKE_FUNCTION            0
            1324 LOAD_FAST                3 (candidates)
            1326 GET_ITER
            1328 CALL_FUNCTION            1
            1330 STORE_FAST              28 (intent_set)

2284        1332 LOAD_FAST                5 (primary)
            1334 BUILD_LIST               1
            1336 STORE_DEREF              0 (operations)

2285        1338 LOAD_FAST                5 (primary)
            1340 LOAD_CONST              50 ('verify')
            1342 COMPARE_OP               2 (==)
            1344 EXTENDED_ARG             2
            1346 POP_JUMP_IF_FALSE      682 (to 1364)
            1348 LOAD_FAST               15 (current_matches)
            1350 EXTENDED_ARG             2
            1352 POP_JUMP_IF_FALSE      682 (to 1364)

2286        1354 LOAD_DEREF               0 (operations)
            1356 LOAD_METHOD             38 (append)
            1358 LOAD_CONST              50 ('verify')
            1360 CALL_METHOD              1
            1362 POP_TOP

2287     >> 1364 LOAD_FAST                5 (primary)
            1366 LOAD_CONST              63 ('summarize')
            1368 COMPARE_OP               2 (==)
            1370 EXTENDED_ARG             2
            1372 POP_JUMP_IF_FALSE      695 (to 1390)
            1374 LOAD_FAST               21 (verify_matches)
            1376 EXTENDED_ARG             2
            1378 POP_JUMP_IF_FALSE      695 (to 1390)

2288        1380 LOAD_DEREF               0 (operations)
            1382 LOAD_METHOD             38 (append)
            1384 LOAD_CONST              50 ('verify')
            1386 CALL_METHOD              1
            1388 POP_TOP

2289     >> 1390 LOAD_FAST                5 (primary)
            1392 LOAD_CONST              64 ('explain')
            1394 COMPARE_OP               2 (==)
            1396 EXTENDED_ARG             2
            1398 POP_JUMP_IF_FALSE      708 (to 1416)
            1400 LOAD_FAST               21 (verify_matches)
            1402 EXTENDED_ARG             2
            1404 POP_JUMP_IF_FALSE      708 (to 1416)

2290        1406 LOAD_DEREF               0 (operations)
            1408 LOAD_METHOD             38 (append)
            1410 LOAD_CONST              50 ('verify')
            1412 CALL_METHOD              1
            1414 POP_TOP

2291     >> 1416 LOAD_FAST                5 (primary)
            1418 LOAD_CONST              19 ('clarify')
            1420 COMPARE_OP               2 (==)
            1422 EXTENDED_ARG             3
            1424 POP_JUMP_IF_FALSE      816 (to 1632)

2293        1426 LOAD_FAST               22 (terminal_build_matches)
            1428 EXTENDED_ARG             2
            1430 JUMP_IF_TRUE_OR_POP    731 (to 1462)

2294        1432 LOAD_FAST               20 (multiple_matches)
            1434 EXTENDED_ARG             2
            1436 JUMP_IF_FALSE_OR_POP   722 (to 1444)
            1438 LOAD_CONST              65 ('build')
            1440 LOAD_FAST               28 (intent_set)
            1442 CONTAINS_OP              0

2293     >> 1444 EXTENDED_ARG             2
            1446 JUMP_IF_TRUE_OR_POP    731 (to 1462)

2295        1448 LOAD_GLOBAL             25 (re)
            1450 LOAD_METHOD             26 (search)
            1452 LOAD_CONST              66 ('target database is not stated|migration plan.*not stated')
            1454 LOAD_FAST                0 (text)
            1456 LOAD_GLOBAL             25 (re)
            1458 LOAD_ATTR               27 (I)
            1460 CALL_METHOD              3

2292     >> 1462 STORE_FAST              29 (clarify_build_bridge)

2297        1464 LOAD_GLOBAL             25 (re)
            1466 LOAD_METHOD             26 (search)
            1468 LOAD_CONST              67 ('not provided (?:the )?target text|target text yet|ask for the artifact first|artifact first')
            1470 LOAD_FAST                0 (text)
            1472 LOAD_GLOBAL             25 (re)
            1474 LOAD_ATTR               27 (I)
            1476 CALL_METHOD              3
            1478 EXTENDED_ARG             2
            1480 POP_JUMP_IF_FALSE      743 (to 1486)

2298        1482 LOAD_CONST              68 (False)
            1484 STORE_FAST              29 (clarify_build_bridge)

2299     >> 1486 LOAD_FAST               29 (clarify_build_bridge)
            1488 EXTENDED_ARG             2
            1490 POP_JUMP_IF_FALSE      751 (to 1502)

2300        1492 LOAD_DEREF               0 (operations)
            1494 LOAD_METHOD             38 (append)
            1496 LOAD_CONST              65 ('build')
            1498 CALL_METHOD              1
            1500 POP_TOP

2301     >> 1502 LOAD_CONST              63 ('summarize')
            1504 LOAD_FAST               28 (intent_set)
            1506 CONTAINS_OP              0
            1508 EXTENDED_ARG             2
            1510 POP_JUMP_IF_TRUE       759 (to 1518)
            1512 LOAD_FAST               23 (terminal_summary_matches)
            1514 EXTENDED_ARG             2
            1516 POP_JUMP_IF_FALSE      764 (to 1528)

2302     >> 1518 LOAD_DEREF               0 (operations)
            1520 LOAD_METHOD             38 (append)
            1522 LOAD_CONST              63 ('summarize')
            1524 CALL_METHOD              1
            1526 POP_TOP

2303     >> 1528 LOAD_CONST              64 ('explain')
            1530 LOAD_FAST               28 (intent_set)
            1532 CONTAINS_OP              0
            1534 EXTENDED_ARG             3
            1536 POP_JUMP_IF_TRUE       772 (to 1544)
            1538 LOAD_FAST               24 (terminal_explain_matches)
            1540 EXTENDED_ARG             3
            1542 POP_JUMP_IF_FALSE      777 (to 1554)

2304     >> 1544 LOAD_DEREF               0 (operations)
            1546 LOAD_METHOD             38 (append)
            1548 LOAD_CONST              64 ('explain')
            1550 CALL_METHOD              1
            1552 POP_TOP

2306     >> 1554 LOAD_CONST              50 ('verify')
            1556 LOAD_FAST               28 (intent_set)
            1558 CONTAINS_OP              0
            1560 EXTENDED_ARG             3
            1562 POP_JUMP_IF_TRUE       785 (to 1570)
            1564 LOAD_FAST               21 (verify_matches)
            1566 EXTENDED_ARG             3
            1568 JUMP_IF_FALSE_OR_POP   807 (to 1614)

2308     >> 1570 LOAD_FAST               10 (v7)
            1572 LOAD_CONST              69 ('high_legal')
            1574 BINARY_SUBSCR
            1576 EXTENDED_ARG             3
            1578 JUMP_IF_TRUE_OR_POP    807 (to 1614)

2309        1580 LOAD_FAST               10 (v7)
            1582 LOAD_CONST              70 ('high_medical')
            1584 BINARY_SUBSCR

2308        1586 EXTENDED_ARG             3
            1588 JUMP_IF_TRUE_OR_POP    807 (to 1614)

2310        1590 LOAD_FAST               10 (v7)
            1592 LOAD_CONST              29 ('current_lookup')
            1594 BINARY_SUBSCR

2308        1596 EXTENDED_ARG             3
            1598 JUMP_IF_TRUE_OR_POP    807 (to 1614)

2311        1600 LOAD_GLOBAL             25 (re)
            1602 LOAD_METHOD             26 (search)
            1604 LOAD_CONST              71 ('\\b(?:check|verify)\\b')
            1606 LOAD_FAST                0 (text)
            1608 LOAD_GLOBAL             25 (re)
            1610 LOAD_ATTR               27 (I)
            1612 CALL_METHOD              3

2305     >> 1614 STORE_FAST              30 (clarify_verify_bridge)

2314        1616 LOAD_FAST               30 (clarify_verify_bridge)
            1618 EXTENDED_ARG             3
            1620 POP_JUMP_IF_FALSE      816 (to 1632)

2315        1622 LOAD_DEREF               0 (operations)
            1624 LOAD_METHOD             38 (append)
            1626 LOAD_CONST              50 ('verify')
            1628 CALL_METHOD              1
            1630 POP_TOP

2316     >> 1632 LOAD_FAST                5 (primary)
            1634 LOAD_CONST              19 ('clarify')
            1636 COMPARE_OP               2 (==)
            1638 EXTENDED_ARG             3
            1640 POP_JUMP_IF_FALSE      836 (to 1672)
            1642 LOAD_FAST                8 (v6)
            1644 LOAD_CONST              20 ('medical_anxiety_boundary')
            1646 BINARY_SUBSCR
            1648 EXTENDED_ARG             3
            1650 POP_JUMP_IF_FALSE      836 (to 1672)

2317        1652 LOAD_DEREF               0 (operations)
            1654 LOAD_METHOD             38 (append)
            1656 LOAD_CONST              50 ('verify')
            1658 CALL_METHOD              1
            1660 POP_TOP

2318        1662 LOAD_DEREF               0 (operations)
            1664 LOAD_METHOD             38 (append)
            1666 LOAD_CONST              64 ('explain')
            1668 CALL_METHOD              1
            1670 POP_TOP

2319     >> 1672 LOAD_FAST                5 (primary)
            1674 LOAD_CONST              50 ('verify')
            1676 COMPARE_OP               2 (==)
            1678 EXTENDED_ARG             3
            1680 POP_JUMP_IF_FALSE      856 (to 1712)

2320        1682 LOAD_FAST                8 (v6)
            1684 LOAD_CONST              35 ('ai_persona_dependency')
            1686 BINARY_SUBSCR

2319        1688 EXTENDED_ARG             3
            1690 POP_JUMP_IF_TRUE       851 (to 1702)

2320        1692 LOAD_FAST                8 (v6)
            1694 LOAD_CONST              20 ('medical_anxiety_boundary')
            1696 BINARY_SUBSCR

2319        1698 EXTENDED_ARG             3
            1700 POP_JUMP_IF_FALSE      856 (to 1712)

2322     >> 1702 LOAD_DEREF               0 (operations)
            1704 LOAD_METHOD             38 (append)
            1706 LOAD_CONST              64 ('explain')
            1708 CALL_METHOD              1
            1710 POP_TOP

2323     >> 1712 LOAD_FAST                5 (primary)
            1714 LOAD_CONST              72 ('explore')
            1716 COMPARE_OP               2 (==)
            1718 EXTENDED_ARG             3
            1720 POP_JUMP_IF_FALSE      881 (to 1762)

2324        1722 LOAD_FAST                8 (v6)
            1724 LOAD_CONST              36 ('ai_abuse_ethics')
            1726 BINARY_SUBSCR

2323        1728 EXTENDED_ARG             3
            1730 POP_JUMP_IF_TRUE       876 (to 1752)

2325        1732 LOAD_FAST                8 (v6)
            1734 LOAD_CONST              37 ('political_future_split')
            1736 BINARY_SUBSCR

2323        1738 EXTENDED_ARG             3
            1740 POP_JUMP_IF_TRUE       876 (to 1752)

2326        1742 LOAD_FAST                8 (v6)
            1744 LOAD_CONST              39 ('future_job_displacement')
            1746 BINARY_SUBSCR

2323        1748 EXTENDED_ARG             3
            1750 POP_JUMP_IF_FALSE      881 (to 1762)

2328     >> 1752 LOAD_DEREF               0 (operations)
            1754 LOAD_METHOD             38 (append)
            1756 LOAD_CONST              50 ('verify')
            1758 CALL_METHOD              1
            1760 POP_TOP

2329     >> 1762 LOAD_FAST                5 (primary)
            1764 LOAD_CONST              72 ('explore')
            1766 COMPARE_OP               2 (==)
            1768 EXTENDED_ARG             3
            1770 POP_JUMP_IF_FALSE      896 (to 1792)
            1772 LOAD_FAST                8 (v6)
            1774 LOAD_CONST              38 ('political_neutrality_advice')
            1776 BINARY_SUBSCR
            1778 EXTENDED_ARG             3
            1780 POP_JUMP_IF_FALSE      896 (to 1792)

2330        1782 LOAD_DEREF               0 (operations)
            1784 LOAD_METHOD             38 (append)
            1786 LOAD_CONST              73 ('compare')
            1788 CALL_METHOD              1
            1790 POP_TOP

2331     >> 1792 LOAD_FAST                5 (primary)
            1794 LOAD_CONST              72 ('explore')
            1796 COMPARE_OP               2 (==)
            1798 EXTENDED_ARG             3
            1800 POP_JUMP_IF_FALSE      914 (to 1828)
            1802 LOAD_CONST              63 ('summarize')
            1804 LOAD_FAST               28 (intent_set)
            1806 CONTAINS_OP              0
            1808 EXTENDED_ARG             3
            1810 POP_JUMP_IF_TRUE       909 (to 1818)
            1812 LOAD_FAST               23 (terminal_summary_matches)
            1814 EXTENDED_ARG             3
            1816 POP_JUMP_IF_FALSE      914 (to 1828)

2332     >> 1818 LOAD_DEREF               0 (operations)
            1820 LOAD_METHOD             38 (append)
            1822 LOAD_CONST              63 ('summarize')
            1824 CALL_METHOD              1
            1826 POP_TOP

2333     >> 1828 LOAD_FAST                5 (primary)
            1830 LOAD_CONST              65 ('build')
            1832 COMPARE_OP               2 (==)
            1834 EXTENDED_ARG             3
            1836 POP_JUMP_IF_FALSE      927 (to 1854)
            1838 LOAD_FAST               21 (verify_matches)
            1840 EXTENDED_ARG             3
            1842 POP_JUMP_IF_FALSE      927 (to 1854)

2338        1844 LOAD_DEREF               0 (operations)
            1846 LOAD_METHOD             38 (append)
            1848 LOAD_CONST              50 ('verify')
            1850 CALL_METHOD              1
            1852 POP_TOP

2339     >> 1854 LOAD_FAST                5 (primary)
            1856 LOAD_CONST              65 ('build')
            1858 COMPARE_OP               2 (==)
            1860 EXTENDED_ARG             3
            1862 POP_JUMP_IF_FALSE      950 (to 1900)
            1864 LOAD_FAST               22 (terminal_build_matches)
            1866 EXTENDED_ARG             3
            1868 POP_JUMP_IF_TRUE       940 (to 1880)
            1870 LOAD_FAST               10 (v7)
            1872 LOAD_CONST              55 ('terminal_build')
            1874 BINARY_SUBSCR
            1876 EXTENDED_ARG             3
            1878 POP_JUMP_IF_FALSE      950 (to 1900)
         >> 1880 LOAD_CONST              63 ('summarize')
            1882 LOAD_FAST               28 (intent_set)
            1884 CONTAINS_OP              0
            1886 EXTENDED_ARG             3
            1888 POP_JUMP_IF_FALSE      950 (to 1900)

2340        1890 LOAD_DEREF               0 (operations)
            1892 LOAD_METHOD             38 (append)
            1894 LOAD_CONST              63 ('summarize')
            1896 CALL_METHOD              1
            1898 POP_TOP

2341     >> 1900 LOAD_FAST                5 (primary)
            1902 LOAD_CONST              65 ('build')
            1904 COMPARE_OP               2 (==)
            1906 EXTENDED_ARG             3
            1908 POP_JUMP_IF_FALSE      970 (to 1940)
            1910 LOAD_FAST               11 (v8)
            1912 LOAD_CONST              52 ('force_build')
            1914 BINARY_SUBSCR
            1916 EXTENDED_ARG             3
            1918 POP_JUMP_IF_FALSE      970 (to 1940)
            1920 LOAD_CONST              63 ('summarize')
            1922 LOAD_FAST               28 (intent_set)
            1924 CONTAINS_OP              0
            1926 EXTENDED_ARG             3
            1928 POP_JUMP_IF_FALSE      970 (to 1940)

2342        1930 LOAD_DEREF               0 (operations)
            1932 LOAD_METHOD             38 (append)
            1934 LOAD_CONST              63 ('summarize')
            1936 CALL_METHOD              1
            1938 POP_TOP

2343     >> 1940 LOAD_GLOBAL             15 (bool)

2344        1942 LOAD_FAST                8 (v6)
            1944 LOAD_CONST              26 ('licensed_model_sample_rule')
            1946 BINARY_SUBSCR
            1948 EXTENDED_ARG             3
            1950 JUMP_IF_TRUE_OR_POP    979 (to 1958)
            1952 LOAD_FAST                8 (v6)
            1954 LOAD_CONST              28 ('ai_regulation_current')
            1956 BINARY_SUBSCR

2343     >> 1958 CALL_FUNCTION            1
            1960 STORE_FAST              31 (suppress_current_search)

2346        1962 LOAD_FAST               15 (current_matches)
            1964 EXTENDED_ARG             3
            1966 POP_JUMP_IF_FALSE     1000 (to 2000)
            1968 LOAD_FAST               31 (suppress_current_search)
            1970 EXTENDED_ARG             3
            1972 POP_JUMP_IF_TRUE      1000 (to 2000)
            1974 LOAD_FAST                5 (primary)
            1976 LOAD_CONST              19 ('clarify')
            1978 COMPARE_OP               2 (==)
            1980 EXTENDED_ARG             3
            1982 POP_JUMP_IF_FALSE      995 (to 1990)
            1984 LOAD_FAST               14 (missing_matches)
            1986 EXTENDED_ARG             3
            1988 POP_JUMP_IF_TRUE      1000 (to 2000)

2347     >> 1990 LOAD_DEREF               0 (operations)
            1992 LOAD_METHOD             38 (append)
            1994 LOAD_CONST              74 ('search')
            1996 CALL_METHOD              1
            1998 POP_TOP

2348     >> 2000 LOAD_FAST                5 (primary)
            2002 LOAD_CONST              50 ('verify')
            2004 COMPARE_OP               2 (==)
            2006 EXTENDED_ARG             4
            2008 POP_JUMP_IF_FALSE     1048 (to 2096)
            2010 LOAD_FAST               10 (v7)
            2012 LOAD_CONST              75 ('source_lookup')
            2014 BINARY_SUBSCR
            2016 EXTENDED_ARG             3
            2018 POP_JUMP_IF_TRUE      1015 (to 2030)
            2020 LOAD_FAST               11 (v8)
            2022 LOAD_CONST              76 ('cite_sources')
            2024 BINARY_SUBSCR
            2026 EXTENDED_ARG             4
            2028 POP_JUMP_IF_FALSE     1048 (to 2096)
         >> 2030 LOAD_FAST               10 (v7)
            2032 LOAD_CONST              29 ('current_lookup')
            2034 BINARY_SUBSCR
            2036 EXTENDED_ARG             4
            2038 POP_JUMP_IF_TRUE      1040 (to 2080)
            2040 LOAD_FAST               10 (v7)
            2042 LOAD_CONST              77 ('high_security')
            2044 BINARY_SUBSCR
            2046 EXTENDED_ARG             4
            2048 POP_JUMP_IF_TRUE      1040 (to 2080)
            2050 LOAD_FAST               10 (v7)
            2052 LOAD_CONST              78 ('license_medium')
            2054 BINARY_SUBSCR
            2056 EXTENDED_ARG             4
            2058 POP_JUMP_IF_TRUE      1040 (to 2080)
            2060 LOAD_FAST               10 (v7)
            2062 LOAD_CONST              44 ('legal_medium')
            2064 BINARY_SUBSCR
            2066 EXTENDED_ARG             4
            2068 POP_JUMP_IF_TRUE      1040 (to 2080)
            2070 LOAD_FAST               11 (v8)
            2072 LOAD_CONST              78 ('license_medium')
            2074 BINARY_SUBSCR
            2076 EXTENDED_ARG             4
            2078 POP_JUMP_IF_FALSE     1048 (to 2096)
         >> 2080 LOAD_FAST               31 (suppress_current_search)
            2082 EXTENDED_ARG             4
            2084 POP_JUMP_IF_TRUE      1048 (to 2096)

2349        2086 LOAD_DEREF               0 (operations)
            2088 LOAD_METHOD             38 (append)
            2090 LOAD_CONST              74 ('search')
            2092 CALL_METHOD              1
            2094 POP_TOP

2350     >> 2096 LOAD_GLOBAL             25 (re)
            2098 LOAD_METHOD             26 (search)
            2100 LOAD_CONST              79 ('calculate|calculating|\\btotal\\b|add up|monthly cost|totals? (?:are right|match|matches|correct)|expense totals|計算して|計算し|を計算|計算結果|合計')
            2102 LOAD_FAST                0 (text)
            2104 LOAD_GLOBAL             25 (re)
            2106 LOAD_ATTR               27 (I)
            2108 CALL_METHOD              3
            2110 EXTENDED_ARG             4
            2112 POP_JUMP_IF_FALSE     1063 (to 2126)

2351        2114 LOAD_DEREF               0 (operations)
            2116 LOAD_METHOD             38 (append)
            2118 LOAD_CONST              80 ('calculate')
            2120 CALL_METHOD              1
            2122 POP_TOP
            2124 JUMP_FORWARD            10 (to 2146)

2352     >> 2126 LOAD_GLOBAL             39 (_has_arithmetic_expression)
            2128 LOAD_FAST                0 (text)
            2130 CALL_FUNCTION            1
            2132 EXTENDED_ARG             4
            2134 POP_JUMP_IF_FALSE     1073 (to 2146)

2357        2136 LOAD_DEREF               0 (operations)
            2138 LOAD_METHOD             38 (append)
            2140 LOAD_CONST              80 ('calculate')
            2142 CALL_METHOD              1
            2144 POP_TOP

2359     >> 2146 LOAD_GLOBAL             25 (re)
            2148 LOAD_METHOD             26 (search)
            2150 LOAD_CONST              81 ('compare|comparing|pros and cons|比較')
            2152 LOAD_FAST                0 (text)
            2154 LOAD_GLOBAL             25 (re)
            2156 LOAD_ATTR               27 (I)
            2158 CALL_METHOD              3

2358        2160 EXTENDED_ARG             4
            2162 POP_JUMP_IF_TRUE      1096 (to 2192)

2360        2164 LOAD_FAST                5 (primary)
            2166 LOAD_CONST              72 ('explore')
            2168 COMPARE_OP               2 (==)

2358        2170 EXTENDED_ARG             4
            2172 POP_JUMP_IF_FALSE     1106 (to 2212)

2360        2174 LOAD_GLOBAL             25 (re)
            2176 LOAD_METHOD             26 (search)
            2178 LOAD_CONST              82 ('trade-?offs?|\\\\ufffd.*r\\\\ufffd')
            2180 LOAD_FAST                0 (text)
            2182 LOAD_GLOBAL             25 (re)
            2184 LOAD_ATTR               27 (I)
            2186 CALL_METHOD              3

2358        2188 EXTENDED_ARG             4
            2190 POP_JUMP_IF_FALSE     1106 (to 2212)

2361     >> 2192 LOAD_FAST                9 (fp)
            2194 LOAD_CONST              83 ('suppress_compare_operation')
            2196 BINARY_SUBSCR

2358        2198 EXTENDED_ARG             4
            2200 POP_JUMP_IF_TRUE      1106 (to 2212)

2362        2202 LOAD_DEREF               0 (operations)
            2204 LOAD_METHOD             38 (append)
            2206 LOAD_CONST              73 ('compare')
            2208 CALL_METHOD              1
            2210 POP_TOP

2364     >> 2212 BUILD_LIST               0
            2214 STORE_FAST              32 (formats)

2365        2216 LOAD_GLOBAL             40 (FORMAT_MARKERS)
            2218 LOAD_METHOD             11 (items)
            2220 CALL_METHOD              0
            2222 GET_ITER
         >> 2224 FOR_ITER                24 (to 2274)
            2226 UNPACK_SEQUENCE          2
            2228 STORE_FAST              33 (format_name)
            2230 STORE_FAST              34 (marker)

2366        2232 LOAD_GLOBAL             22 (_find_markers)
            2234 LOAD_FAST                0 (text)
            2236 LOAD_FAST               34 (marker)
            2238 BUILD_TUPLE              1
            2240 CALL_FUNCTION            2
            2242 STORE_FAST              35 (matches)

2367        2244 LOAD_FAST               35 (matches)
            2246 EXTENDED_ARG             4
            2248 POP_JUMP_IF_FALSE     1135 (to 2270)

2368        2250 LOAD_FAST               32 (formats)
            2252 LOAD_METHOD             38 (append)
            2254 LOAD_FAST               33 (format_name)
            2256 CALL_METHOD              1
            2258 POP_TOP

2369        2260 LOAD_FAST                4 (evidence)
            2262 LOAD_METHOD             24 (extend)
            2264 LOAD_FAST               35 (matches)
            2266 CALL_METHOD              1
            2268 POP_TOP
         >> 2270 EXTENDED_ARG             4
            2272 JUMP_ABSOLUTE         1112 (to 2224)

2370     >> 2274 LOAD_GLOBAL             25 (re)
            2276 LOAD_METHOD             26 (search)
            2278 LOAD_CONST              84 ('\\bJSON\\b[^.?!]*(?:import|plan|template|object)')
            2280 LOAD_FAST                0 (text)
            2282 CALL_METHOD              2
            2284 EXTENDED_ARG             4
            2286 POP_JUMP_IF_FALSE     1154 (to 2308)
            2288 LOAD_CONST              85 ('json')
            2290 LOAD_FAST               32 (formats)
            2292 CONTAINS_OP              1
            2294 EXTENDED_ARG             4
            2296 POP_JUMP_IF_FALSE     1154 (to 2308)

2371        2298 LOAD_FAST               32 (formats)
            2300 LOAD_METHOD             38 (append)
            2302 LOAD_CONST              85 ('json')
            2304 CALL_METHOD              1
            2306 POP_TOP

2372     >> 2308 LOAD_GLOBAL             25 (re)
            2310 LOAD_METHOD             26 (search)
            2312 LOAD_CONST              86 ('\\bchecklist of fixes\\b')
            2314 LOAD_FAST                0 (text)
            2316 LOAD_GLOBAL             25 (re)
            2318 LOAD_ATTR               27 (I)
            2320 CALL_METHOD              3
            2322 EXTENDED_ARG             4
            2324 POP_JUMP_IF_FALSE     1173 (to 2346)
            2326 LOAD_CONST              87 ('bullets')
            2328 LOAD_FAST               32 (formats)
            2330 CONTAINS_OP              1
            2332 EXTENDED_ARG             4
            2334 POP_JUMP_IF_FALSE     1173 (to 2346)

2373        2336 LOAD_FAST               32 (formats)
            2338 LOAD_METHOD             38 (append)
            2340 LOAD_CONST              87 ('bullets')
            2342 CALL_METHOD              1
            2344 POP_TOP

2374     >> 2346 LOAD_FAST               11 (v8)
            2348 LOAD_CONST              88 ('force_table')
            2350 BINARY_SUBSCR
            2352 EXTENDED_ARG             4
            2354 POP_JUMP_IF_FALSE     1188 (to 2376)
            2356 LOAD_CONST              89 ('table')
            2358 LOAD_FAST               32 (formats)
            2360 CONTAINS_OP              1
            2362 EXTENDED_ARG             4
            2364 POP_JUMP_IF_FALSE     1188 (to 2376)

2375        2366 LOAD_FAST               32 (formats)
            2368 LOAD_METHOD             38 (append)
            2370 LOAD_CONST              89 ('table')
            2372 CALL_METHOD              1
            2374 POP_TOP

2376     >> 2376 LOAD_FAST                9 (fp)
            2378 LOAD_CONST              90 ('suppress_structural_format_constraints')
            2380 BINARY_SUBSCR
            2382 EXTENDED_ARG             4
            2384 POP_JUMP_IF_FALSE     1205 (to 2410)
            2386 LOAD_FAST               11 (v8)
            2388 LOAD_CONST              88 ('force_table')
            2390 BINARY_SUBSCR
            2392 EXTENDED_ARG             4
            2394 POP_JUMP_IF_TRUE      1205 (to 2410)

2377        2396 LOAD_CONST              91 (<code object <listcomp> at 0x000002A981289E70, file "D:\Thought State Register\semantic_routing\baseline.py", line 2377>)
            2398 LOAD_CONST               8 ('extract_semantic_packet.<locals>.<listcomp>')
            2400 MAKE_FUNCTION            0
            2402 LOAD_FAST               32 (formats)
            2404 GET_ITER
            2406 CALL_FUNCTION            1
            2408 STORE_FAST              32 (formats)

2379     >> 2410 BUILD_LIST               0
            2412 STORE_FAST              36 (must)

2380        2414 LOAD_GLOBAL             41 (MUST_MARKERS)
            2416 LOAD_METHOD             11 (items)
            2418 CALL_METHOD              0
            2420 GET_ITER
         >> 2422 FOR_ITER                24 (to 2472)
            2424 UNPACK_SEQUENCE          2
            2426 STORE_FAST              37 (constraint)
            2428 STORE_FAST              34 (marker)

2381        2430 LOAD_GLOBAL             22 (_find_markers)
            2432 LOAD_FAST                0 (text)
            2434 LOAD_FAST               34 (marker)
            2436 BUILD_TUPLE              1
            2438 CALL_FUNCTION            2
            2440 STORE_FAST              35 (matches)

2382        2442 LOAD_FAST               35 (matches)
            2444 EXTENDED_ARG             4
            2446 POP_JUMP_IF_FALSE     1234 (to 2468)

2383        2448 LOAD_FAST               36 (must)
            2450 LOAD_METHOD             38 (append)
            2452 LOAD_FAST               37 (constraint)
            2454 CALL_METHOD              1
            2456 POP_TOP

2384        2458 LOAD_FAST                4 (evidence)
            2460 LOAD_METHOD             24 (extend)
            2462 LOAD_FAST               35 (matches)
            2464 CALL_METHOD              1
            2466 POP_TOP
         >> 2468 EXTENDED_ARG             4
            2470 JUMP_ABSOLUTE         1211 (to 2422)

2386     >> 2472 LOAD_FAST               10 (v7)
            2474 LOAD_CONST              75 ('source_lookup')
            2476 BINARY_SUBSCR

2387        2478 LOAD_FAST               10 (v7)
            2480 LOAD_CONST              22 ('ask_first')
            2482 BINARY_SUBSCR

2388        2484 LOAD_FAST               10 (v7)
            2486 LOAD_CONST              92 ('preserve_neutrality')
            2488 BINARY_SUBSCR

2389        2490 LOAD_FAST               10 (v7)
            2492 LOAD_CONST              93 ('avoid_overclaim')
            2494 BINARY_SUBSCR

2390        2496 LOAD_FAST               10 (v7)
            2498 LOAD_CONST              94 ('general_information_only')
            2500 BINARY_SUBSCR

2391        2502 LOAD_FAST               10 (v7)
            2504 LOAD_CONST              95 ('avoid_diagnosis')
            2506 BINARY_SUBSCR

2385        2508 LOAD_CONST              96 (('cite_sources', 'ask_first', 'preserve_neutrality', 'avoid_overclaim', 'general_information_only', 'avoid_diagnosis'))
            2510 BUILD_CONST_KEY_MAP      6
            2512 STORE_FAST              38 (v7_must_groups)

2393        2514 LOAD_FAST               38 (v7_must_groups)
            2516 LOAD_METHOD             11 (items)
            2518 CALL_METHOD              0
            2520 GET_ITER
         >> 2522 FOR_ITER                23 (to 2570)
            2524 UNPACK_SEQUENCE          2
            2526 STORE_FAST              37 (constraint)
            2528 STORE_FAST              35 (matches)

2394        2530 LOAD_FAST               35 (matches)
            2532 EXTENDED_ARG             5
            2534 POP_JUMP_IF_FALSE     1283 (to 2566)
            2536 LOAD_FAST               37 (constraint)
            2538 LOAD_FAST               36 (must)
            2540 CONTAINS_OP              1
            2542 EXTENDED_ARG             5
            2544 POP_JUMP_IF_FALSE     1283 (to 2566)

2395        2546 LOAD_FAST               36 (must)
            2548 LOAD_METHOD             38 (append)
            2550 LOAD_FAST               37 (constraint)
            2552 CALL_METHOD              1
            2554 POP_TOP

2396        2556 LOAD_FAST                4 (evidence)
            2558 LOAD_METHOD             24 (extend)
            2560 LOAD_FAST               35 (matches)
            2562 CALL_METHOD              1
            2564 POP_TOP
         >> 2566 EXTENDED_ARG             4
            2568 JUMP_ABSOLUTE         1261 (to 2522)

2398     >> 2570 LOAD_FAST               11 (v8)
            2572 LOAD_CONST              76 ('cite_sources')
            2574 BINARY_SUBSCR

2399        2576 LOAD_FAST               11 (v8)
            2578 LOAD_CONST              92 ('preserve_neutrality')
            2580 BINARY_SUBSCR

2400        2582 LOAD_FAST               11 (v8)
            2584 LOAD_CONST              94 ('general_information_only')
            2586 BINARY_SUBSCR

2401        2588 LOAD_FAST               11 (v8)
            2590 LOAD_CONST              93 ('avoid_overclaim')
            2592 BINARY_SUBSCR

2402        2594 LOAD_FAST               11 (v8)
            2596 LOAD_CONST              95 ('avoid_diagnosis')
            2598 BINARY_SUBSCR

2397        2600 LOAD_CONST              97 (('cite_sources', 'preserve_neutrality', 'general_information_only', 'avoid_overclaim', 'avoid_diagnosis'))
            2602 BUILD_CONST_KEY_MAP      5
            2604 STORE_FAST              39 (v8_must_groups)

2404        2606 LOAD_FAST               39 (v8_must_groups)
            2608 LOAD_METHOD             11 (items)
            2610 CALL_METHOD              0
            2612 GET_ITER
         >> 2614 FOR_ITER                23 (to 2662)
            2616 UNPACK_SEQUENCE          2
            2618 STORE_FAST              37 (constraint)
            2620 STORE_FAST              35 (matches)

2405        2622 LOAD_FAST               35 (matches)
            2624 EXTENDED_ARG             5
            2626 POP_JUMP_IF_FALSE     1329 (to 2658)
            2628 LOAD_FAST               37 (constraint)
            2630 LOAD_FAST               36 (must)
            2632 CONTAINS_OP              1
            2634 EXTENDED_ARG             5
            2636 POP_JUMP_IF_FALSE     1329 (to 2658)

2406        2638 LOAD_FAST               36 (must)
            2640 LOAD_METHOD             38 (append)
            2642 LOAD_FAST               37 (constraint)
            2644 CALL_METHOD              1
            2646 POP_TOP

2407        2648 LOAD_FAST                4 (evidence)
            2650 LOAD_METHOD             24 (extend)
            2652 LOAD_FAST               35 (matches)
            2654 CALL_METHOD              1
            2656 POP_TOP
         >> 2658 EXTENDED_ARG             5
            2660 JUMP_ABSOLUTE         1307 (to 2614)

2408     >> 2662 LOAD_GLOBAL             25 (re)
            2664 LOAD_METHOD             26 (search)
            2666 LOAD_CONST              98 ('target is missing.*should be checked')
            2668 LOAD_FAST                0 (text)
            2670 LOAD_GLOBAL             25 (re)
            2672 LOAD_ATTR               27 (I)
            2674 CALL_METHOD              3
            2676 EXTENDED_ARG             5
            2678 POP_JUMP_IF_FALSE     1347 (to 2694)

2409        2680 LOAD_CONST              99 (<code object <listcomp> at 0x000002A981289F20, file "D:\Thought State Register\semantic_routing\baseline.py", line 2409>)
            2682 LOAD_CONST               8 ('extract_semantic_packet.<locals>.<listcomp>')
            2684 MAKE_FUNCTION            0
            2686 LOAD_FAST               36 (must)
            2688 GET_ITER
            2690 CALL_FUNCTION            1
            2692 STORE_FAST              36 (must)

2410     >> 2694 LOAD_GLOBAL             25 (re)
            2696 LOAD_METHOD             26 (search)
            2698 LOAD_CONST              24 ('曖昧.*先に確認の質問')
            2700 LOAD_FAST                0 (text)
            2702 CALL_METHOD              2
            2704 EXTENDED_ARG             5
            2706 POP_JUMP_IF_FALSE     1361 (to 2722)

2411        2708 LOAD_CONST             100 (<code object <listcomp> at 0x000002A981289FD0, file "D:\Thought State Register\semantic_routing\baseline.py", line 2411>)
            2710 LOAD_CONST               8 ('extract_semantic_packet.<locals>.<listcomp>')
            2712 MAKE_FUNCTION            0
            2714 LOAD_FAST               36 (must)
            2716 GET_ITER
            2718 CALL_FUNCTION            1
            2720 STORE_FAST              36 (must)

2412     >> 2722 LOAD_FAST                8 (v6)
            2724 LOAD_CONST              26 ('licensed_model_sample_rule')
            2726 BINARY_SUBSCR
            2728 EXTENDED_ARG             5
            2730 POP_JUMP_IF_TRUE      1371 (to 2742)
            2732 LOAD_FAST                8 (v6)
            2734 LOAD_CONST              27 ('ai_legal_license')
            2736 BINARY_SUBSCR
            2738 EXTENDED_ARG             5
            2740 POP_JUMP_IF_FALSE     1381 (to 2762)
         >> 2742 LOAD_CONST              76 ('cite_sources')
            2744 LOAD_FAST               36 (must)
            2746 CONTAINS_OP              1
            2748 EXTENDED_ARG             5
            2750 POP_JUMP_IF_FALSE     1381 (to 2762)

2413        2752 LOAD_FAST               36 (must)
            2754 LOAD_METHOD             38 (append)
            2756 LOAD_CONST              76 ('cite_sources')
            2758 CALL_METHOD              1
            2760 POP_TOP

2414     >> 2762 LOAD_FAST                8 (v6)
            2764 LOAD_CONST              20 ('medical_anxiety_boundary')
            2766 BINARY_SUBSCR
            2768 EXTENDED_ARG             5
            2770 POP_JUMP_IF_FALSE     1396 (to 2792)
            2772 LOAD_CONST              22 ('ask_first')
            2774 LOAD_FAST               36 (must)
            2776 CONTAINS_OP              1
            2778 EXTENDED_ARG             5
            2780 POP_JUMP_IF_FALSE     1396 (to 2792)

2415        2782 LOAD_FAST               36 (must)
            2784 LOAD_METHOD             38 (append)
            2786 LOAD_CONST              22 ('ask_first')
            2788 CALL_METHOD              1
            2790 POP_TOP

2417     >> 2792 LOAD_FAST                8 (v6)
            2794 LOAD_CONST              36 ('ai_abuse_ethics')
            2796 BINARY_SUBSCR

2416        2798 EXTENDED_ARG             5
            2800 POP_JUMP_IF_TRUE      1411 (to 2822)

2418        2802 LOAD_FAST                8 (v6)
            2804 LOAD_CONST              37 ('political_future_split')
            2806 BINARY_SUBSCR

2416        2808 EXTENDED_ARG             5
            2810 POP_JUMP_IF_TRUE      1411 (to 2822)

2419        2812 LOAD_FAST                8 (v6)
            2814 LOAD_CONST              38 ('political_neutrality_advice')
            2816 BINARY_SUBSCR

2416        2818 EXTENDED_ARG             5
            2820 POP_JUMP_IF_FALSE     1421 (to 2842)

2420     >> 2822 LOAD_CONST              92 ('preserve_neutrality')
            2824 LOAD_FAST               36 (must)
            2826 CONTAINS_OP              1

2416        2828 EXTENDED_ARG             5
            2830 POP_JUMP_IF_FALSE     1421 (to 2842)

2421        2832 LOAD_FAST               36 (must)
            2834 LOAD_METHOD             38 (append)
            2836 LOAD_CONST              92 ('preserve_neutrality')
            2838 CALL_METHOD              1
            2840 POP_TOP

2423     >> 2842 LOAD_FAST                8 (v6)
            2844 LOAD_CONST              34 ('local_llm_hostile_boundary')
            2846 BINARY_SUBSCR

2422        2848 EXTENDED_ARG             5
            2850 POP_JUMP_IF_TRUE      1471 (to 2942)

2424        2852 LOAD_FAST                8 (v6)
            2854 LOAD_CONST              26 ('licensed_model_sample_rule')
            2856 BINARY_SUBSCR

2422        2858 EXTENDED_ARG             5
            2860 POP_JUMP_IF_TRUE      1471 (to 2942)

2425        2862 LOAD_FAST                8 (v6)
            2864 LOAD_CONST              35 ('ai_persona_dependency')
            2866 BINARY_SUBSCR

2422        2868 EXTENDED_ARG             5
            2870 POP_JUMP_IF_TRUE      1471 (to 2942)

2426        2872 LOAD_FAST                8 (v6)
            2874 LOAD_CONST              27 ('ai_legal_license')
            2876 BINARY_SUBSCR

2422        2878 EXTENDED_ARG             5
            2880 POP_JUMP_IF_TRUE      1471 (to 2942)

2427        2882 LOAD_FAST                8 (v6)
            2884 LOAD_CONST              28 ('ai_regulation_current')
            2886 BINARY_SUBSCR

2422        2888 EXTENDED_ARG             5
            2890 POP_JUMP_IF_TRUE      1471 (to 2942)

2428        2892 LOAD_FAST                8 (v6)
            2894 LOAD_CONST              36 ('ai_abuse_ethics')
            2896 BINARY_SUBSCR

2422        2898 EXTENDED_ARG             5
            2900 POP_JUMP_IF_TRUE      1471 (to 2942)

2429        2902 LOAD_FAST                8 (v6)
            2904 LOAD_CONST              37 ('political_future_split')
            2906 BINARY_SUBSCR

2422        2908 EXTENDED_ARG             5
            2910 POP_JUMP_IF_TRUE      1471 (to 2942)

2430        2912 LOAD_FAST                8 (v6)
            2914 LOAD_CONST              38 ('political_neutrality_advice')
            2916 BINARY_SUBSCR

2422        2918 EXTENDED_ARG             5
            2920 POP_JUMP_IF_TRUE      1471 (to 2942)

2431        2922 LOAD_FAST                8 (v6)
            2924 LOAD_CONST              39 ('future_job_displacement')
            2926 BINARY_SUBSCR

2422        2928 EXTENDED_ARG             5
            2930 POP_JUMP_IF_TRUE      1471 (to 2942)

2432        2932 LOAD_FAST                8 (v6)
            2934 LOAD_CONST              20 ('medical_anxiety_boundary')
            2936 BINARY_SUBSCR

2422        2938 EXTENDED_ARG             5
            2940 POP_JUMP_IF_FALSE     1481 (to 2962)

2433     >> 2942 LOAD_CONST              93 ('avoid_overclaim')
            2944 LOAD_FAST               36 (must)
            2946 CONTAINS_OP              1

2422        2948 EXTENDED_ARG             5
            2950 POP_JUMP_IF_FALSE     1481 (to 2962)

2434        2952 LOAD_FAST               36 (must)
            2954 LOAD_METHOD             38 (append)
            2956 LOAD_CONST              93 ('avoid_overclaim')
            2958 CALL_METHOD              1
            2960 POP_TOP

2435     >> 2962 LOAD_FAST                9 (fp)
            2964 LOAD_CONST              33 ('low_risk_boundary')
            2966 BINARY_SUBSCR
            2968 EXTENDED_ARG             5
            2970 POP_JUMP_IF_FALSE     1509 (to 3018)

2436        2972 BUILD_SET                0
            2974 LOAD_CONST             101 (frozenset({'cite_sources', 'avoid_overclaim', 'ask_first'}))
            2976 SET_UPDATE               1
            2978 STORE_DEREF              1 (suppressed_constraints)

2437        2980 LOAD_FAST                9 (fp)
            2982 LOAD_CONST             102 ('suppress_neutrality_constraint')
            2984 BINARY_SUBSCR
            2986 EXTENDED_ARG             5
            2988 POP_JUMP_IF_FALSE     1500 (to 3000)

2438        2990 LOAD_DEREF               1 (suppressed_constraints)
            2992 LOAD_METHOD             42 (add)
            2994 LOAD_CONST              92 ('preserve_neutrality')
            2996 CALL_METHOD              1
            2998 POP_TOP

2439     >> 3000 LOAD_CLOSURE             1 (suppressed_constraints)
            3002 BUILD_TUPLE              1
            3004 LOAD_CONST             103 (<code object <listcomp> at 0x000002A98128A080, file "D:\Thought State Register\semantic_routing\baseline.py", line 2439>)
            3006 LOAD_CONST               8 ('extract_semantic_packet.<locals>.<listcomp>')
            3008 MAKE_FUNCTION            8 (closure)
            3010 LOAD_FAST               36 (must)
            3012 GET_ITER
            3014 CALL_FUNCTION            1
            3016 STORE_FAST              36 (must)

2440     >> 3018 LOAD_FAST               11 (v8)
            3020 LOAD_CONST              92 ('preserve_neutrality')
            3022 BINARY_SUBSCR
            3024 EXTENDED_ARG             5
            3026 POP_JUMP_IF_FALSE     1525 (to 3050)
            3028 LOAD_CONST              92 ('preserve_neutrality')
            3030 LOAD_FAST               36 (must)
            3032 CONTAINS_OP              1
            3034 EXTENDED_ARG             5
            3036 POP_JUMP_IF_FALSE     1525 (to 3050)

2441        3038 LOAD_FAST               36 (must)
            3040 LOAD_METHOD             43 (insert)
            3042 LOAD_CONST               2 (0)
            3044 LOAD_CONST              92 ('preserve_neutrality')
            3046 CALL_METHOD              2
            3048 POP_TOP

2442     >> 3050 BUILD_LIST               0
            3052 STORE_FAST              40 (must_not)

2443        3054 LOAD_GLOBAL             44 (MUST_NOT_MARKERS)
            3056 LOAD_METHOD             11 (items)
            3058 CALL_METHOD              0
            3060 GET_ITER
         >> 3062 FOR_ITER                24 (to 3112)
            3064 UNPACK_SEQUENCE          2
            3066 STORE_FAST              37 (constraint)
            3068 STORE_FAST              34 (marker)

2444        3070 LOAD_GLOBAL             22 (_find_markers)
            3072 LOAD_FAST                0 (text)
            3074 LOAD_FAST               34 (marker)
            3076 BUILD_TUPLE              1
            3078 CALL_FUNCTION            2
            3080 STORE_FAST              35 (matches)

2445        3082 LOAD_FAST               35 (matches)
            3084 EXTENDED_ARG             6
            3086 POP_JUMP_IF_FALSE     1554 (to 3108)

2446        3088 LOAD_FAST               40 (must_not)
            3090 LOAD_METHOD             38 (append)
            3092 LOAD_FAST               37 (constraint)
            3094 CALL_METHOD              1
            3096 POP_TOP

2447        3098 LOAD_FAST                4 (evidence)
            3100 LOAD_METHOD             24 (extend)
            3102 LOAD_FAST               35 (matches)
            3104 CALL_METHOD              1
            3106 POP_TOP
         >> 3108 EXTENDED_ARG             5
            3110 JUMP_ABSOLUTE         1531 (to 3062)

2449     >> 3112 LOAD_FAST               10 (v7)
            3114 LOAD_CONST             104 ('no_table')
            3116 BINARY_SUBSCR

2450        3118 LOAD_FAST               10 (v7)
            3120 LOAD_CONST             105 ('no_web_search')
            3122 BINARY_SUBSCR

2448        3124 LOAD_CONST             106 (('no_table', 'no_web_search'))
            3126 BUILD_CONST_KEY_MAP      2
            3128 STORE_FAST              41 (v7_must_not_groups)

2452        3130 LOAD_FAST               41 (v7_must_not_groups)
            3132 LOAD_METHOD             11 (items)
            3134 CALL_METHOD              0
            3136 GET_ITER
         >> 3138 FOR_ITER                23 (to 3186)
            3140 UNPACK_SEQUENCE          2
            3142 STORE_FAST              37 (constraint)
            3144 STORE_FAST              35 (matches)

2453        3146 LOAD_FAST               35 (matches)
            3148 EXTENDED_ARG             6
            3150 POP_JUMP_IF_FALSE     1591 (to 3182)
            3152 LOAD_FAST               37 (constraint)
            3154 LOAD_FAST               40 (must_not)
            3156 CONTAINS_OP              1
            3158 EXTENDED_ARG             6
            3160 POP_JUMP_IF_FALSE     1591 (to 3182)

2454        3162 LOAD_FAST               40 (must_not)
            3164 LOAD_METHOD             38 (append)
            3166 LOAD_FAST               37 (constraint)
            3168 CALL_METHOD              1
            3170 POP_TOP

2455        3172 LOAD_FAST                4 (evidence)
            3174 LOAD_METHOD             24 (extend)
            3176 LOAD_FAST               35 (matches)
            3178 CALL_METHOD              1
            3180 POP_TOP
         >> 3182 EXTENDED_ARG             6
            3184 JUMP_ABSOLUTE         1569 (to 3138)

2457     >> 3186 LOAD_FAST               11 (v8)
            3188 LOAD_CONST             104 ('no_table')
            3190 BINARY_SUBSCR

2458        3192 LOAD_FAST               11 (v8)
            3194 LOAD_CONST             105 ('no_web_search')
            3196 BINARY_SUBSCR

2456        3198 LOAD_CONST             106 (('no_table', 'no_web_search'))
            3200 BUILD_CONST_KEY_MAP      2
            3202 STORE_FAST              42 (v8_must_not_groups)

2460        3204 LOAD_FAST               42 (v8_must_not_groups)
            3206 LOAD_METHOD             11 (items)
            3208 CALL_METHOD              0
            3210 GET_ITER
         >> 3212 FOR_ITER                23 (to 3260)
            3214 UNPACK_SEQUENCE          2
            3216 STORE_FAST              37 (constraint)
            3218 STORE_FAST              35 (matches)

2461        3220 LOAD_FAST               35 (matches)
            3222 EXTENDED_ARG             6
            3224 POP_JUMP_IF_FALSE     1628 (to 3256)
            3226 LOAD_FAST               37 (constraint)
            3228 LOAD_FAST               40 (must_not)
            3230 CONTAINS_OP              1
            3232 EXTENDED_ARG             6
            3234 POP_JUMP_IF_FALSE     1628 (to 3256)

2462        3236 LOAD_FAST               40 (must_not)
            3238 LOAD_METHOD             38 (append)
            3240 LOAD_FAST               37 (constraint)
            3242 CALL_METHOD              1
            3244 POP_TOP

2463        3246 LOAD_FAST                4 (evidence)
            3248 LOAD_METHOD             24 (extend)
            3250 LOAD_FAST               35 (matches)
            3252 CALL_METHOD              1
            3254 POP_TOP
         >> 3256 EXTENDED_ARG             6
            3258 JUMP_ABSOLUTE         1606 (to 3212)

2464     >> 3260 LOAD_FAST                8 (v6)
            3262 LOAD_CONST              28 ('ai_regulation_current')
            3264 BINARY_SUBSCR
            3266 EXTENDED_ARG             6
            3268 POP_JUMP_IF_FALSE     1650 (to 3300)
            3270 LOAD_FAST                9 (fp)
            3272 LOAD_CONST              30 ('suppress_current_search')
            3274 BINARY_SUBSCR
            3276 EXTENDED_ARG             6
            3278 POP_JUMP_IF_TRUE      1650 (to 3300)
            3280 LOAD_CONST             105 ('no_web_search')
            3282 LOAD_FAST               40 (must_not)
            3284 CONTAINS_OP              1
            3286 EXTENDED_ARG             6
            3288 POP_JUMP_IF_FALSE     1650 (to 3300)

2465        3290 LOAD_FAST               40 (must_not)
            3292 LOAD_METHOD             38 (append)
            3294 LOAD_CONST             105 ('no_web_search')
            3296 CALL_METHOD              1
            3298 POP_TOP

2466     >> 3300 LOAD_CONST             105 ('no_web_search')
            3302 LOAD_FAST               40 (must_not)
            3304 CONTAINS_OP              0
            3306 EXTENDED_ARG             6
            3308 POP_JUMP_IF_FALSE     1662 (to 3324)

2467        3310 LOAD_CONST             107 (<code object <listcomp> at 0x000002A98128A130, file "D:\Thought State Register\semantic_routing\baseline.py", line 2467>)
            3312 LOAD_CONST               8 ('extract_semantic_packet.<locals>.<listcomp>')
            3314 MAKE_FUNCTION            0
            3316 LOAD_DEREF               0 (operations)
            3318 GET_ITER
            3320 CALL_FUNCTION            1
            3322 STORE_DEREF              0 (operations)

2468     >> 3324 LOAD_CONST             104 ('no_table')
            3326 LOAD_FAST               40 (must_not)
            3328 CONTAINS_OP              0
            3330 EXTENDED_ARG             6
            3332 POP_JUMP_IF_FALSE     1674 (to 3348)

2469        3334 LOAD_CONST             108 (<code object <listcomp> at 0x000002A98128A1E0, file "D:\Thought State Register\semantic_routing\baseline.py", line 2469>)
            3336 LOAD_CONST               8 ('extract_semantic_packet.<locals>.<listcomp>')
            3338 MAKE_FUNCTION            0
            3340 LOAD_FAST               32 (formats)
            3342 GET_ITER
            3344 CALL_FUNCTION            1
            3346 STORE_FAST              32 (formats)

2471     >> 3348 LOAD_CONST             109 ('low')
            3350 STORE_FAST              43 (risk_level)

2472        3352 BUILD_LIST               0
            3354 STORE_FAST              44 (risk_flags)

2473        3356 LOAD_CONST             110 (('critical', 'high'))
            3358 GET_ITER
         >> 3360 FOR_ITER                41 (to 3444)
            3362 STORE_FAST              45 (level)

2474        3364 LOAD_GLOBAL             45 (RISK_MARKERS)
            3366 LOAD_FAST               45 (level)
            3368 BINARY_SUBSCR
            3370 GET_ITER
         >> 3372 FOR_ITER                28 (to 3430)
            3374 STORE_FAST              34 (marker)

2475        3376 LOAD_GLOBAL             22 (_find_markers)
            3378 LOAD_FAST                0 (text)
            3380 LOAD_FAST               34 (marker)
            3382 BUILD_TUPLE              1
            3384 CALL_FUNCTION            2
            3386 STORE_FAST              35 (matches)

2476        3388 LOAD_FAST               35 (matches)
            3390 EXTENDED_ARG             6
            3392 POP_JUMP_IF_FALSE     1713 (to 3426)

2477        3394 LOAD_FAST               45 (level)
            3396 STORE_FAST              43 (risk_level)

2478        3398 LOAD_FAST               44 (risk_flags)
            3400 LOAD_METHOD             38 (append)
            3402 LOAD_FAST               34 (marker)
            3404 LOAD_ATTR               46 (signal)
            3406 LOAD_METHOD             47 (removesuffix)
            3408 LOAD_CONST             111 ('_risk')
            3410 CALL_METHOD              1
            3412 CALL_METHOD              1
            3414 POP_TOP

2479        3416 LOAD_FAST                4 (evidence)
            3418 LOAD_METHOD             24 (extend)
            3420 LOAD_FAST               35 (matches)
            3422 CALL_METHOD              1
            3424 POP_TOP
         >> 3426 EXTENDED_ARG             6
            3428 JUMP_ABSOLUTE         1686 (to 3372)

2480     >> 3430 LOAD_FAST               44 (risk_flags)
            3432 EXTENDED_ARG             6
            3434 POP_JUMP_IF_FALSE     1720 (to 3440)

2481        3436 POP_TOP
            3438 JUMP_FORWARD             2 (to 3444)

2480     >> 3440 EXTENDED_ARG             6
            3442 JUMP_ABSOLUTE         1680 (to 3360)

2482     >> 3444 LOAD_FAST                8 (v6)
            3446 LOAD_CONST              26 ('licensed_model_sample_rule')
            3448 BINARY_SUBSCR
            3450 EXTENDED_ARG             6
            3452 POP_JUMP_IF_FALSE     1736 (to 3472)

2483        3454 LOAD_CONST             112 ('high')
            3456 STORE_FAST              43 (risk_level)

2484        3458 LOAD_FAST               44 (risk_flags)
            3460 LOAD_METHOD             24 (extend)
            3462 LOAD_CONST             113 ('legal')
            3464 LOAD_CONST             114 ('license')
            3466 BUILD_LIST               2
            3468 CALL_METHOD              1
            3470 POP_TOP

2485     >> 3472 LOAD_FAST                8 (v6)
            3474 LOAD_CONST              27 ('ai_legal_license')
            3476 BINARY_SUBSCR
            3478 EXTENDED_ARG             6
            3480 POP_JUMP_IF_FALSE     1750 (to 3500)

2486        3482 LOAD_CONST             112 ('high')
            3484 STORE_FAST              43 (risk_level)

2487        3486 LOAD_FAST               44 (risk_flags)
            3488 LOAD_METHOD             24 (extend)
            3490 LOAD_CONST             113 ('legal')
            3492 LOAD_CONST             114 ('license')
            3494 BUILD_LIST               2
            3496 CALL_METHOD              1
            3498 POP_TOP

2488     >> 3500 LOAD_FAST                8 (v6)
            3502 LOAD_CONST              28 ('ai_regulation_current')
            3504 BINARY_SUBSCR
            3506 EXTENDED_ARG             6
            3508 POP_JUMP_IF_FALSE     1762 (to 3524)

2489        3510 LOAD_CONST             112 ('high')
            3512 STORE_FAST              43 (risk_level)

2490        3514 LOAD_FAST               44 (risk_flags)
            3516 LOAD_METHOD             38 (append)
            3518 LOAD_CONST             113 ('legal')
            3520 CALL_METHOD              1
            3522 POP_TOP

2491     >> 3524 LOAD_FAST                8 (v6)
            3526 LOAD_CONST              20 ('medical_anxiety_boundary')
            3528 BINARY_SUBSCR
            3530 EXTENDED_ARG             6
            3532 POP_JUMP_IF_FALSE     1776 (to 3552)

2492        3534 LOAD_CONST             112 ('high')
            3536 STORE_FAST              43 (risk_level)

2493        3538 LOAD_FAST               44 (risk_flags)
            3540 LOAD_METHOD             24 (extend)
            3542 LOAD_CONST             115 ('medical')
            3544 LOAD_CONST             116 ('mental_health')
            3546 BUILD_LIST               2
            3548 CALL_METHOD              1
            3550 POP_TOP

2494     >> 3552 LOAD_FAST               10 (v7)
            3554 LOAD_CONST              69 ('high_legal')
            3556 BINARY_SUBSCR
            3558 EXTENDED_ARG             6
            3560 POP_JUMP_IF_FALSE     1788 (to 3576)

2495        3562 LOAD_CONST             112 ('high')
            3564 STORE_FAST              43 (risk_level)

2496        3566 LOAD_FAST               44 (risk_flags)
            3568 LOAD_METHOD             38 (append)
            3570 LOAD_CONST             113 ('legal')
            3572 CALL_METHOD              1
            3574 POP_TOP

2497     >> 3576 LOAD_FAST               10 (v7)
            3578 LOAD_CONST              70 ('high_medical')
            3580 BINARY_SUBSCR
            3582 EXTENDED_ARG             7
            3584 POP_JUMP_IF_FALSE     1800 (to 3600)

2498        3586 LOAD_CONST             112 ('high')
            3588 STORE_FAST              43 (risk_level)

2499        3590 LOAD_FAST               44 (risk_flags)
            3592 LOAD_METHOD             38 (append)
            3594 LOAD_CONST             115 ('medical')
            3596 CALL_METHOD              1
            3598 POP_TOP

2500     >> 3600 LOAD_FAST               10 (v7)
            3602 LOAD_CONST              77 ('high_security')
            3604 BINARY_SUBSCR
            3606 EXTENDED_ARG             7
            3608 POP_JUMP_IF_FALSE     1812 (to 3624)

2501        3610 LOAD_CONST             112 ('high')
            3612 STORE_FAST              43 (risk_level)

2502        3614 LOAD_FAST               44 (risk_flags)
            3616 LOAD_METHOD             38 (append)
            3618 LOAD_CONST             117 ('security')
            3620 CALL_METHOD              1
            3622 POP_TOP

2503     >> 3624 LOAD_FAST               11 (v8)
            3626 LOAD_CONST              70 ('high_medical')
            3628 BINARY_SUBSCR
            3630 EXTENDED_ARG             7
            3632 POP_JUMP_IF_FALSE     1824 (to 3648)

2504        3634 LOAD_CONST             112 ('high')
            3636 STORE_FAST              43 (risk_level)

2505        3638 LOAD_FAST               44 (risk_flags)
            3640 LOAD_METHOD             38 (append)
            3642 LOAD_CONST             115 ('medical')
            3644 CALL_METHOD              1
            3646 POP_TOP

2506     >> 3648 LOAD_FAST               11 (v8)
            3650 LOAD_CONST             118 ('legal_high')
            3652 BINARY_SUBSCR
            3654 EXTENDED_ARG             7
            3656 POP_JUMP_IF_FALSE     1836 (to 3672)

2507        3658 LOAD_CONST             112 ('high')
            3660 STORE_FAST              43 (risk_level)

2508        3662 LOAD_FAST               44 (risk_flags)
            3664 LOAD_METHOD             38 (append)
            3666 LOAD_CONST             113 ('legal')
            3668 CALL_METHOD              1
            3670 POP_TOP

2509     >> 3672 LOAD_FAST               43 (risk_level)
            3674 LOAD_CONST             109 ('low')
            3676 COMPARE_OP               2 (==)
            3678 EXTENDED_ARG             7
            3680 POP_JUMP_IF_FALSE     1858 (to 3716)
            3682 LOAD_FAST               10 (v7)
            3684 LOAD_CONST              78 ('license_medium')
            3686 BINARY_SUBSCR
            3688 EXTENDED_ARG             7
            3690 POP_JUMP_IF_TRUE      1851 (to 3702)
            3692 LOAD_FAST               11 (v8)
            3694 LOAD_CONST              78 ('license_medium')
            3696 BINARY_SUBSCR
            3698 EXTENDED_ARG             7
            3700 POP_JUMP_IF_FALSE     1858 (to 3716)

2510     >> 3702 LOAD_CONST             119 ('medium')
            3704 STORE_FAST              43 (risk_level)

2511        3706 LOAD_FAST               44 (risk_flags)
            3708 LOAD_METHOD             38 (append)
            3710 LOAD_CONST             114 ('license')
            3712 CALL_METHOD              1
            3714 POP_TOP

2512     >> 3716 LOAD_FAST               43 (risk_level)
            3718 LOAD_CONST             109 ('low')
            3720 COMPARE_OP               2 (==)
            3722 EXTENDED_ARG             7
            3724 POP_JUMP_IF_FALSE     1875 (to 3750)
            3726 LOAD_FAST               11 (v8)
            3728 LOAD_CONST             120 ('security_medium')
            3730 BINARY_SUBSCR
            3732 EXTENDED_ARG             7
            3734 POP_JUMP_IF_FALSE     1875 (to 3750)

2513        3736 LOAD_CONST             119 ('medium')
            3738 STORE_FAST              43 (risk_level)

2514        3740 LOAD_FAST               44 (risk_flags)
            3742 LOAD_METHOD             38 (append)
            3744 LOAD_CONST             117 ('security')
            3746 CALL_METHOD              1
            3748 POP_TOP

2515     >> 3750 LOAD_FAST               43 (risk_level)
            3752 LOAD_CONST             109 ('low')
            3754 COMPARE_OP               2 (==)
            3756 EXTENDED_ARG             7
            3758 POP_JUMP_IF_FALSE     1891 (to 3782)
            3760 LOAD_GLOBAL             25 (re)
            3762 LOAD_METHOD             26 (search)
            3764 LOAD_CONST             121 ('\\b(before adding this number|\\d+ incidents is correct)\\b')
            3766 LOAD_FAST                0 (text)
            3768 LOAD_GLOBAL             25 (re)
            3770 LOAD_ATTR               27 (I)
            3772 CALL_METHOD              3
            3774 EXTENDED_ARG             7
            3776 POP_JUMP_IF_FALSE     1891 (to 3782)

2516        3778 LOAD_CONST             119 ('medium')
            3780 STORE_FAST              43 (risk_level)

2517     >> 3782 LOAD_FAST               43 (risk_level)
            3784 LOAD_CONST             109 ('low')
            3786 COMPARE_OP               2 (==)
            3788 EXTENDED_ARG             7
            3790 POP_JUMP_IF_FALSE     1908 (to 3816)
            3792 LOAD_FAST               10 (v7)
            3794 LOAD_CONST              44 ('legal_medium')
            3796 BINARY_SUBSCR
            3798 EXTENDED_ARG             7
            3800 POP_JUMP_IF_FALSE     1908 (to 3816)

2518        3802 LOAD_CONST             119 ('medium')
            3804 STORE_FAST              43 (risk_level)

2519        3806 LOAD_FAST               44 (risk_flags)
            3808 LOAD_METHOD             38 (append)
            3810 LOAD_CONST             113 ('legal')
            3812 CALL_METHOD              1
            3814 POP_TOP

2520     >> 3816 LOAD_FAST               43 (risk_level)
            3818 LOAD_CONST             109 ('low')
            3820 COMPARE_OP               2 (==)
            3822 EXTENDED_ARG             7
            3824 POP_JUMP_IF_FALSE     1925 (to 3850)
            3826 LOAD_FAST               10 (v7)
            3828 LOAD_CONST             122 ('future_medium')
            3830 BINARY_SUBSCR
            3832 EXTENDED_ARG             7
            3834 POP_JUMP_IF_FALSE     1925 (to 3850)

2521        3836 LOAD_CONST             119 ('medium')
            3838 STORE_FAST              43 (risk_level)

2522        3840 LOAD_FAST               44 (risk_flags)
            3842 LOAD_METHOD             38 (append)
            3844 LOAD_CONST             123 ('future_prediction')
            3846 CALL_METHOD              1
            3848 POP_TOP

2523     >> 3850 LOAD_FAST               43 (risk_level)
            3852 LOAD_CONST             109 ('low')
            3854 COMPARE_OP               2 (==)
            3856 EXTENDED_ARG             7
            3858 POP_JUMP_IF_FALSE     1942 (to 3884)
            3860 LOAD_FAST               10 (v7)
            3862 LOAD_CONST             124 ('political_medium')
            3864 BINARY_SUBSCR
            3866 EXTENDED_ARG             7
            3868 POP_JUMP_IF_FALSE     1942 (to 3884)

2524        3870 LOAD_CONST             119 ('medium')
            3872 STORE_FAST              43 (risk_level)

2525        3874 LOAD_FAST               44 (risk_flags)
            3876 LOAD_METHOD             38 (append)
            3878 LOAD_CONST             125 ('political')
            3880 CALL_METHOD              1
            3882 POP_TOP

2526     >> 3884 LOAD_FAST               43 (risk_level)
            3886 LOAD_CONST             109 ('low')
            3888 COMPARE_OP               2 (==)
            3890 EXTENDED_ARG             7
            3892 POP_JUMP_IF_FALSE     1959 (to 3918)
            3894 LOAD_FAST               10 (v7)
            3896 LOAD_CONST             126 ('risk_comparison_medium')
            3898 BINARY_SUBSCR
            3900 EXTENDED_ARG             7
            3902 POP_JUMP_IF_FALSE     1959 (to 3918)

2527        3904 LOAD_CONST             119 ('medium')
            3906 STORE_FAST              43 (risk_level)

2528        3908 LOAD_FAST               44 (risk_flags)
            3910 LOAD_METHOD             38 (append)
            3912 LOAD_CONST             127 ('risk_comparison')
            3914 CALL_METHOD              1
            3916 POP_TOP

2529     >> 3918 LOAD_FAST               43 (risk_level)
            3920 LOAD_CONST             109 ('low')
            3922 COMPARE_OP               2 (==)
            3924 EXTENDED_ARG             7
            3926 POP_JUMP_IF_FALSE     1978 (to 3956)
            3928 LOAD_FAST                8 (v6)
            3930 LOAD_CONST              34 ('local_llm_hostile_boundary')
            3932 BINARY_SUBSCR
            3934 EXTENDED_ARG             7
            3936 POP_JUMP_IF_FALSE     1978 (to 3956)

2530        3938 LOAD_CONST             119 ('medium')
            3940 STORE_FAST              43 (risk_level)

2531        3942 LOAD_FAST               44 (risk_flags)
            3944 LOAD_METHOD             24 (extend)
            3946 LOAD_CONST             128 ('hostile_user')
            3948 LOAD_CONST             129 ('safety')
            3950 BUILD_LIST               2
            3952 CALL_METHOD              1
            3954 POP_TOP

2532     >> 3956 LOAD_FAST               43 (risk_level)
            3958 LOAD_CONST             109 ('low')
            3960 COMPARE_OP               2 (==)
            3962 EXTENDED_ARG             7
            3964 POP_JUMP_IF_FALSE     2012 (to 4024)
            3966 LOAD_FAST                8 (v6)
            3968 LOAD_CONST              35 ('ai_persona_dependency')
            3970 BINARY_SUBSCR
            3972 EXTENDED_ARG             7
            3974 POP_JUMP_IF_FALSE     2012 (to 4024)

2533        3976 LOAD_CONST             119 ('medium')
            3978 STORE_FAST              43 (risk_level)

2534        3980 LOAD_GLOBAL             25 (re)
            3982 LOAD_METHOD             26 (search)
            3984 LOAD_CONST             130 ('人格|理解している')
            3986 LOAD_FAST                0 (text)
            3988 CALL_METHOD              2
            3990 EXTENDED_ARG             7
            3992 POP_JUMP_IF_FALSE     2005 (to 4010)

2535        3994 LOAD_FAST               44 (risk_flags)
            3996 LOAD_METHOD             24 (extend)
            3998 LOAD_CONST             131 ('persona_claim')
            4000 LOAD_CONST             116 ('mental_health')
            4002 BUILD_LIST               2
            4004 CALL_METHOD              1
            4006 POP_TOP
            4008 JUMP_FORWARD             7 (to 4024)

2537     >> 4010 LOAD_FAST               44 (risk_flags)
            4012 LOAD_METHOD             24 (extend)
            4014 LOAD_CONST             116 ('mental_health')
            4016 LOAD_CONST             132 ('dependency_risk')
            4018 BUILD_LIST               2
            4020 CALL_METHOD              1
            4022 POP_TOP

2538     >> 4024 LOAD_FAST               43 (risk_level)
            4026 LOAD_CONST             109 ('low')
            4028 COMPARE_OP               2 (==)
            4030 EXTENDED_ARG             7
            4032 POP_JUMP_IF_FALSE     2031 (to 4062)
            4034 LOAD_FAST                8 (v6)
            4036 LOAD_CONST              36 ('ai_abuse_ethics')
            4038 BINARY_SUBSCR
            4040 EXTENDED_ARG             7
            4042 POP_JUMP_IF_FALSE     2031 (to 4062)

2539        4044 LOAD_CONST             119 ('medium')
            4046 STORE_FAST              43 (risk_level)

2540        4048 LOAD_FAST               44 (risk_flags)
            4050 LOAD_METHOD             24 (extend)
            4052 LOAD_CONST             133 ('ai_ethics')
            4054 LOAD_CONST             128 ('hostile_user')
            4056 BUILD_LIST               2
            4058 CALL_METHOD              1
            4060 POP_TOP

2541     >> 4062 LOAD_FAST               43 (risk_level)
            4064 LOAD_CONST             109 ('low')
            4066 COMPARE_OP               2 (==)
            4068 EXTENDED_ARG             8
            4070 POP_JUMP_IF_FALSE     2050 (to 4100)
            4072 LOAD_FAST                8 (v6)
            4074 LOAD_CONST              37 ('political_future_split')
            4076 BINARY_SUBSCR
            4078 EXTENDED_ARG             8
            4080 POP_JUMP_IF_FALSE     2050 (to 4100)

2542        4082 LOAD_CONST             119 ('medium')
            4084 STORE_FAST              43 (risk_level)

2543        4086 LOAD_FAST               44 (risk_flags)
            4088 LOAD_METHOD             24 (extend)
            4090 LOAD_CONST             125 ('political')
            4092 LOAD_CONST             123 ('future_prediction')
            4094 BUILD_LIST               2
            4096 CALL_METHOD              1
            4098 POP_TOP

2544     >> 4100 LOAD_FAST               43 (risk_level)
            4102 LOAD_CONST             109 ('low')
            4104 COMPARE_OP               2 (==)
            4106 EXTENDED_ARG             8
            4108 POP_JUMP_IF_FALSE     2069 (to 4138)
            4110 LOAD_FAST                8 (v6)
            4112 LOAD_CONST              38 ('political_neutrality_advice')
            4114 BINARY_SUBSCR
            4116 EXTENDED_ARG             8
            4118 POP_JUMP_IF_FALSE     2069 (to 4138)

2545        4120 LOAD_CONST             119 ('medium')
            4122 STORE_FAST              43 (risk_level)

2546        4124 LOAD_FAST               44 (risk_flags)
            4126 LOAD_METHOD             24 (extend)
            4128 LOAD_CONST             125 ('political')
            4130 LOAD_CONST             134 ('values')
            4132 BUILD_LIST               2
            4134 CALL_METHOD              1
            4136 POP_TOP

2547     >> 4138 LOAD_FAST               43 (risk_level)
            4140 LOAD_CONST             109 ('low')
            4142 COMPARE_OP               2 (==)
            4144 EXTENDED_ARG             8
            4146 POP_JUMP_IF_FALSE     2086 (to 4172)
            4148 LOAD_FAST                8 (v6)
            4150 LOAD_CONST              39 ('future_job_displacement')
            4152 BINARY_SUBSCR
            4154 EXTENDED_ARG             8
            4156 POP_JUMP_IF_FALSE     2086 (to 4172)

2548        4158 LOAD_CONST             119 ('medium')
            4160 STORE_FAST              43 (risk_level)

2549        4162 LOAD_FAST               44 (risk_flags)
            4164 LOAD_METHOD             38 (append)
            4166 LOAD_CONST             123 ('future_prediction')
            4168 CALL_METHOD              1
            4170 POP_TOP

2550     >> 4172 LOAD_FAST               43 (risk_level)
            4174 LOAD_CONST             109 ('low')
            4176 COMPARE_OP               2 (==)
            4178 EXTENDED_ARG             8
            4180 POP_JUMP_IF_FALSE     2096 (to 4192)
            4182 LOAD_FAST               15 (current_matches)
            4184 EXTENDED_ARG             8
            4186 POP_JUMP_IF_FALSE     2096 (to 4192)

2551        4188 LOAD_CONST             119 ('medium')
            4190 STORE_FAST              43 (risk_level)

2552     >> 4192 LOAD_GLOBAL             25 (re)
            4194 LOAD_METHOD             26 (search)

2553        4196 LOAD_CONST             135 ('claim below|vendor claims|reported figures|report says|supposedly|do not assume it is true|i heard this (?:number|figure|value) is correct|\\u8a00\\u308f\\u308c\\u307e\\u3057\\u305f')

2554        4198 LOAD_FAST                0 (text)

2555        4200 LOAD_GLOBAL             25 (re)
            4202 LOAD_ATTR               27 (I)

2552        4204 CALL_METHOD              3

2556        4206 LOAD_CONST               0 (None)

2552        4208 IS_OP                    1
            4210 STORE_FAST              46 (unverified_risk_escalates)

2557        4212 LOAD_FAST               43 (risk_level)
            4214 LOAD_CONST             109 ('low')
            4216 COMPARE_OP               2 (==)
            4218 EXTENDED_ARG             8
            4220 POP_JUMP_IF_FALSE     2129 (to 4258)
            4222 LOAD_FAST               19 (unverified_risk_matches)
            4224 EXTENDED_ARG             8
            4226 POP_JUMP_IF_FALSE     2129 (to 4258)

2558        4228 LOAD_CONST              76 ('cite_sources')
            4230 LOAD_FAST               36 (must)
            4232 CONTAINS_OP              0

2557        4234 EXTENDED_ARG             8
            4236 POP_JUMP_IF_TRUE      2127 (to 4254)

2558        4238 LOAD_CONST              93 ('avoid_overclaim')
            4240 LOAD_FAST               36 (must)
            4242 CONTAINS_OP              0

2557        4244 EXTENDED_ARG             8
            4246 POP_JUMP_IF_TRUE      2127 (to 4254)

2558        4248 LOAD_FAST               46 (unverified_risk_escalates)

2557        4250 EXTENDED_ARG             8
            4252 POP_JUMP_IF_FALSE     2129 (to 4258)

2560     >> 4254 LOAD_CONST             119 ('medium')
            4256 STORE_FAST              43 (risk_level)

2561     >> 4258 LOAD_FAST                9 (fp)
            4260 LOAD_CONST              33 ('low_risk_boundary')
            4262 BINARY_SUBSCR
            4264 EXTENDED_ARG             8
            4266 POP_JUMP_IF_TRUE      2144 (to 4288)
            4268 LOAD_FAST               10 (v7)
            4270 LOAD_CONST              33 ('low_risk_boundary')
            4272 BINARY_SUBSCR
            4274 EXTENDED_ARG             8
            4276 POP_JUMP_IF_TRUE      2144 (to 4288)
            4278 LOAD_FAST               11 (v8)
            4280 LOAD_CONST              33 ('low_risk_boundary')
            4282 BINARY_SUBSCR
            4284 EXTENDED_ARG             8
            4286 POP_JUMP_IF_FALSE     2148 (to 4296)

2562     >> 4288 LOAD_CONST             109 ('low')
            4290 STORE_FAST              43 (risk_level)

2563        4292 BUILD_LIST               0
            4294 STORE_FAST              44 (risk_flags)

2564     >> 4296 LOAD_FAST               15 (current_matches)
            4298 EXTENDED_ARG             8
            4300 POP_JUMP_IF_FALSE     2161 (to 4322)

2565        4302 LOAD_FAST               44 (risk_flags)
            4304 LOAD_METHOD             38 (append)
            4306 LOAD_CONST             136 ('current_information')
            4308 CALL_METHOD              1
            4310 POP_TOP

2566        4312 LOAD_FAST                4 (evidence)
            4314 LOAD_METHOD             24 (extend)
            4316 LOAD_FAST               15 (current_matches)
            4318 CALL_METHOD              1
            4320 POP_TOP

2567     >> 4322 LOAD_FAST               18 (unverified_info_matches)
            4324 EXTENDED_ARG             8
            4326 POP_JUMP_IF_FALSE     2182 (to 4364)

2568        4328 LOAD_FAST                4 (evidence)
            4330 LOAD_METHOD             24 (extend)
            4332 LOAD_FAST               18 (unverified_info_matches)
            4334 CALL_METHOD              1
            4336 POP_TOP

2569        4338 LOAD_FAST               43 (risk_level)
            4340 LOAD_CONST             109 ('low')
            4342 COMPARE_OP               3 (!=)
            4344 EXTENDED_ARG             8
            4346 POP_JUMP_IF_FALSE     2182 (to 4364)
            4348 LOAD_FAST               19 (unverified_risk_matches)
            4350 EXTENDED_ARG             8
            4352 POP_JUMP_IF_FALSE     2182 (to 4364)

2570        4354 LOAD_FAST               44 (risk_flags)
            4356 LOAD_METHOD             38 (append)
            4358 LOAD_CONST              40 ('unverified_claim')
            4360 CALL_METHOD              1
            4362 POP_TOP

2572     >> 4364 LOAD_FAST                9 (fp)
            4366 LOAD_CONST             137 ('suppress_response_length_constraint')
            4368 BINARY_SUBSCR
            4370 EXTENDED_ARG             8
            4372 POP_JUMP_IF_FALSE     2191 (to 4382)

2573        4374 BUILD_LIST               0
            4376 STORE_FAST              25 (short_matches)

2574        4378 BUILD_LIST               0
            4380 STORE_FAST              27 (long_matches)

2576     >> 4382 LOAD_FAST               25 (short_matches)
            4384 EXTENDED_ARG             8
            4386 POP_JUMP_IF_FALSE     2202 (to 4404)

2577        4388 LOAD_CONST             138 ('short')
            4390 STORE_FAST              47 (response_length)

2578        4392 LOAD_FAST                4 (evidence)
            4394 LOAD_METHOD             24 (extend)
            4396 LOAD_FAST               25 (short_matches)
            4398 CALL_METHOD              1
            4400 POP_TOP
            4402 JUMP_FORWARD            24 (to 4452)

2579     >> 4404 LOAD_FAST               26 (medium_matches)
            4406 EXTENDED_ARG             8
            4408 POP_JUMP_IF_FALSE     2213 (to 4426)

2580        4410 LOAD_CONST             119 ('medium')
            4412 STORE_FAST              47 (response_length)

2581        4414 LOAD_FAST                4 (evidence)
            4416 LOAD_METHOD             24 (extend)
            4418 LOAD_FAST               26 (medium_matches)
            4420 CALL_METHOD              1
            4422 POP_TOP
            4424 JUMP_FORWARD            13 (to 4452)

2582     >> 4426 LOAD_FAST               27 (long_matches)
            4428 EXTENDED_ARG             8
            4430 POP_JUMP_IF_FALSE     2224 (to 4448)

2583        4432 LOAD_CONST             139 ('long')
            4434 STORE_FAST              47 (response_length)

2584        4436 LOAD_FAST                4 (evidence)
            4438 LOAD_METHOD             24 (extend)
            4440 LOAD_FAST               27 (long_matches)
            4442 CALL_METHOD              1
            4444 POP_TOP
            4446 JUMP_FORWARD             2 (to 4452)

2586     >> 4448 LOAD_CONST             140 ('unspecified')
            4450 STORE_FAST              47 (response_length)

2588     >> 4452 LOAD_GLOBAL             25 (re)
            4454 LOAD_METHOD             26 (search)
            4456 LOAD_CONST             141 ('\\blength and explain\\b')
            4458 LOAD_FAST                0 (text)
            4460 LOAD_GLOBAL             25 (re)
            4462 LOAD_ATTR               27 (I)
            4464 CALL_METHOD              3
            4466 EXTENDED_ARG             8
            4468 POP_JUMP_IF_FALSE     2251 (to 4502)

2589        4470 BUILD_LIST               0
            4472 STORE_FAST              20 (multiple_matches)

2590        4474 LOAD_GLOBAL             48 (any)
            4476 LOAD_CLOSURE             0 (operations)
            4478 BUILD_TUPLE              1
            4480 LOAD_CONST             142 (<code object <genexpr> at 0x000002A98128A290, file "D:\Thought State Register\semantic_routing\baseline.py", line 2590>)
            4482 LOAD_CONST             143 ('extract_semantic_packet.<locals>.<genexpr>')
            4484 MAKE_FUNCTION            8 (closure)
            4486 LOAD_CONST             144 (frozenset({'compare', 'build'}))
            4488 GET_ITER
            4490 CALL_FUNCTION            1
            4492 CALL_FUNCTION            1
            4494 EXTENDED_ARG             8
            4496 POP_JUMP_IF_TRUE      2251 (to 4502)

2591        4498 BUILD_LIST               0
            4500 STORE_FAST              20 (multiple_matches)

2592     >> 4502 LOAD_GLOBAL             31 (list)
            4504 LOAD_GLOBAL             49 (dict)
            4506 LOAD_METHOD             50 (fromkeys)
            4508 LOAD_DEREF               0 (operations)
            4510 CALL_METHOD              1
            4512 CALL_FUNCTION            1
            4514 STORE_DEREF              0 (operations)

2593        4516 LOAD_CONST             145 (<code object <listcomp> at 0x000002A98128A340, file "D:\Thought State Register\semantic_routing\baseline.py", line 2593>)
            4518 LOAD_CONST               8 ('extract_semantic_packet.<locals>.<listcomp>')
            4520 MAKE_FUNCTION            0
            4522 LOAD_DEREF               0 (operations)
            4524 GET_ITER
            4526 CALL_FUNCTION            1
            4528 STORE_FAST              48 (meaningful_operations)

2594        4530 LOAD_GLOBAL             15 (bool)
            4532 LOAD_FAST               20 (multiple_matches)
            4534 CALL_FUNCTION            1
            4536 EXTENDED_ARG             8
            4538 JUMP_IF_TRUE_OR_POP   2287 (to 4574)

2595        4540 LOAD_FAST                5 (primary)
            4542 LOAD_CONST              19 ('clarify')
            4544 COMPARE_OP               2 (==)
            4546 EXTENDED_ARG             8
            4548 JUMP_IF_FALSE_OR_POP  2287 (to 4574)

2596        4550 LOAD_GLOBAL             48 (any)
            4552 LOAD_CONST             146 (<code object <genexpr> at 0x000002A98128A3F0, file "D:\Thought State Register\semantic_routing\baseline.py", line 2596>)
            4554 LOAD_CONST             143 ('extract_semantic_packet.<locals>.<genexpr>')
            4556 MAKE_FUNCTION            0

2598        4558 LOAD_FAST               48 (meaningful_operations)
            4560 LOAD_CONST             147 (1)
            4562 LOAD_CONST               0 (None)
            4564 BUILD_SLICE              2
            4566 BINARY_SUBSCR

2596        4568 GET_ITER
            4570 CALL_FUNCTION            1
            4572 CALL_FUNCTION            1

2594     >> 4574 STORE_FAST              49 (multiple_intents)

2601        4576 LOAD_FAST               12 (v9)
            4578 LOAD_CONST             148 ('override')
            4580 BINARY_SUBSCR
            4582 EXTENDED_ARG             8
            4584 JUMP_IF_TRUE_OR_POP   2296 (to 4592)
            4586 LOAD_FAST               13 (v9_ext)
            4588 LOAD_CONST             148 ('override')
            4590 BINARY_SUBSCR
         >> 4592 STORE_FAST              50 (v9_override)

2602        4594 LOAD_FAST               50 (v9_override)
            4596 EXTENDED_ARG             9
            4598 POP_JUMP_IF_FALSE     2406 (to 4812)

2603        4600 LOAD_GLOBAL              1 (str)
            4602 LOAD_FAST               50 (v9_override)
            4604 LOAD_CONST             149 ('primary_intent')
            4606 BINARY_SUBSCR
            4608 CALL_FUNCTION            1
            4610 STORE_FAST               5 (primary)

2604        4612 LOAD_GLOBAL             31 (list)
            4614 LOAD_FAST               50 (v9_override)
            4616 LOAD_CONST             150 ('operations')
            4618 BINARY_SUBSCR
            4620 CALL_FUNCTION            1
            4622 STORE_DEREF              0 (operations)

2605        4624 LOAD_GLOBAL             49 (dict)
            4626 LOAD_FAST               50 (v9_override)
            4628 LOAD_CONST             151 ('information_state')
            4630 BINARY_SUBSCR
            4632 CALL_FUNCTION            1
            4634 STORE_FAST              51 (info)

2606        4636 LOAD_GLOBAL             15 (bool)
            4638 LOAD_FAST               51 (info)
            4640 LOAD_CONST             152 ('missing_required_information')
            4642 BINARY_SUBSCR
            4644 CALL_FUNCTION            1
            4646 STORE_FAST              52 (missing_required_information)

2607        4648 LOAD_GLOBAL             15 (bool)
            4650 LOAD_FAST               51 (info)
            4652 LOAD_CONST             153 ('contains_unverified_claims')
            4654 BINARY_SUBSCR
            4656 CALL_FUNCTION            1
            4658 STORE_FAST              53 (contains_unverified_claims)

2608        4660 LOAD_GLOBAL             15 (bool)
            4662 LOAD_FAST               51 (info)
            4664 LOAD_CONST             154 ('requires_current_information')
            4666 BINARY_SUBSCR
            4668 CALL_FUNCTION            1
            4670 STORE_FAST              54 (requires_current_information)

2609        4672 LOAD_GLOBAL             15 (bool)
            4674 LOAD_FAST               51 (info)
            4676 LOAD_CONST             155 ('multiple_intents')
            4678 BINARY_SUBSCR
            4680 CALL_FUNCTION            1
            4682 STORE_FAST              49 (multiple_intents)

2610        4684 LOAD_GLOBAL             49 (dict)
            4686 LOAD_FAST               50 (v9_override)
            4688 LOAD_CONST             156 ('constraints')
            4690 BINARY_SUBSCR
            4692 CALL_FUNCTION            1
            4694 STORE_FAST              55 (constraints)

2611        4696 LOAD_GLOBAL              1 (str)
            4698 LOAD_FAST               55 (constraints)
            4700 LOAD_CONST             157 ('response_length')
            4702 BINARY_SUBSCR
            4704 CALL_FUNCTION            1
            4706 STORE_FAST              47 (response_length)

2612        4708 LOAD_GLOBAL             31 (list)
            4710 LOAD_FAST               55 (constraints)
            4712 LOAD_CONST             158 ('formats')
            4714 BINARY_SUBSCR
            4716 CALL_FUNCTION            1
            4718 STORE_FAST              32 (formats)

2613        4720 LOAD_GLOBAL             31 (list)
            4722 LOAD_FAST               55 (constraints)
            4724 LOAD_CONST             159 ('must')
            4726 BINARY_SUBSCR
            4728 CALL_FUNCTION            1
            4730 STORE_FAST              36 (must)

2614        4732 LOAD_GLOBAL             31 (list)
            4734 LOAD_FAST               55 (constraints)
            4736 LOAD_CONST             160 ('must_not')
            4738 BINARY_SUBSCR
            4740 CALL_FUNCTION            1
            4742 STORE_FAST              40 (must_not)

2615        4744 LOAD_GLOBAL             49 (dict)
            4746 LOAD_FAST               50 (v9_override)
            4748 LOAD_CONST             161 ('risk')
            4750 BINARY_SUBSCR
            4752 CALL_FUNCTION            1
            4754 STORE_FAST              56 (risk)

2616        4756 LOAD_GLOBAL              1 (str)
            4758 LOAD_FAST               56 (risk)
            4760 LOAD_CONST             162 ('level')
            4762 BINARY_SUBSCR
            4764 CALL_FUNCTION            1
            4766 STORE_FAST              43 (risk_level)

2617        4768 LOAD_GLOBAL             31 (list)
            4770 LOAD_FAST               56 (risk)
            4772 LOAD_CONST             163 ('flags')
            4774 BINARY_SUBSCR
            4776 CALL_FUNCTION            1
            4778 STORE_FAST              44 (risk_flags)

2618        4780 LOAD_GLOBAL             51 (max)
            4782 LOAD_FAST                3 (candidates)
            4784 LOAD_CONST               2 (0)
            4786 BINARY_SUBSCR
            4788 LOAD_ATTR               14 (confidence)
            4790 LOAD_CONST             164 (0.99)
            4792 CALL_FUNCTION            2
            4794 STORE_FAST              57 (confidence)

2619        4796 LOAD_GLOBAL             13 (IntentCandidate)
            4798 LOAD_FAST                5 (primary)
            4800 LOAD_FAST               57 (confidence)
            4802 LOAD_CONST              15 (('intent', 'confidence'))
            4804 CALL_FUNCTION_KW         2
            4806 BUILD_LIST               1
            4808 STORE_FAST               3 (candidates)
            4810 JUMP_FORWARD            12 (to 4836)

2621     >> 4812 LOAD_GLOBAL             15 (bool)
            4814 LOAD_FAST               14 (missing_matches)
            4816 CALL_FUNCTION            1
            4818 STORE_FAST              52 (missing_required_information)

2622        4820 LOAD_GLOBAL             15 (bool)
            4822 LOAD_FAST               18 (unverified_info_matches)
            4824 CALL_FUNCTION            1
            4826 STORE_FAST              53 (contains_unverified_claims)

2623        4828 LOAD_GLOBAL             15 (bool)
            4830 LOAD_FAST               15 (current_matches)
            4832 CALL_FUNCTION            1
            4834 STORE_FAST              54 (requires_current_information)

2624     >> 4836 LOAD_GLOBAL              9 (sorted)
            4838 LOAD_GLOBAL             52 (set)
            4840 LOAD_FAST                4 (evidence)
            4842 CALL_FUNCTION            1
            4844 LOAD_CONST             165 (<code object <lambda> at 0x000002A98128A4A0, file "D:\Thought State Register\semantic_routing\baseline.py", line 2624>)
            4846 LOAD_CONST              10 ('extract_semantic_packet.<locals>.<lambda>')
            4848 MAKE_FUNCTION            0
            4850 LOAD_CONST              11 (('key',))
            4852 CALL_FUNCTION_KW         2
            4854 STORE_FAST               4 (evidence)

2625        4856 LOAD_FAST                3 (candidates)
            4858 LOAD_CONST               2 (0)
            4860 BINARY_SUBSCR
            4862 LOAD_ATTR               14 (confidence)
            4864 STORE_FAST              57 (confidence)

2626        4866 LOAD_FAST               57 (confidence)
            4868 LOAD_CONST             166 (0.6)
            4870 COMPARE_OP               5 (>=)
            4872 EXTENDED_ARG             9
            4874 POP_JUMP_IF_FALSE     2440 (to 4880)
            4876 BUILD_LIST               0
            4878 JUMP_FORWARD             2 (to 4884)
         >> 4880 LOAD_CONST             149 ('primary_intent')
            4882 BUILD_LIST               1
         >> 4884 STORE_FAST              58 (unknowns)

2627        4886 BUILD_LIST               0
            4888 STORE_FAST              59 (conflicts)

2628        4890 LOAD_GLOBAL             53 (len)
            4892 LOAD_FAST                3 (candidates)
            4894 CALL_FUNCTION            1
            4896 LOAD_CONST             147 (1)
            4898 COMPARE_OP               4 (>)
            4900 EXTENDED_ARG             9
            4902 POP_JUMP_IF_FALSE     2468 (to 4936)
            4904 LOAD_FAST                3 (candidates)
            4906 LOAD_CONST               2 (0)
            4908 BINARY_SUBSCR
            4910 LOAD_ATTR               14 (confidence)
            4912 LOAD_FAST                3 (candidates)
            4914 LOAD_CONST             147 (1)
            4916 BINARY_SUBSCR
            4918 LOAD_ATTR               14 (confidence)
            4920 COMPARE_OP               2 (==)
            4922 EXTENDED_ARG             9
            4924 POP_JUMP_IF_FALSE     2468 (to 4936)

2629        4926 LOAD_FAST               59 (conflicts)
            4928 LOAD_METHOD             38 (append)
            4930 LOAD_CONST             149 ('primary_intent')
            4932 CALL_METHOD              1
            4934 POP_TOP

2631     >> 4936 LOAD_GLOBAL             54 (parse_semantic_packet)

2633        4938 LOAD_CONST             167 ('semantic-packet.v1')

2634        4940 LOAD_GLOBAL             55 (request_digest)
            4942 LOAD_FAST                0 (text)
            4944 CALL_FUNCTION            1

2636        4946 LOAD_CONST             168 ('deterministic_signal_extractor')

2637        4948 LOAD_CONST             169 ('0.2')

2635        4950 LOAD_CONST             170 (('kind', 'version'))
            4952 BUILD_CONST_KEY_MAP      2

2639        4954 LOAD_GLOBAL             56 (_language)
            4956 LOAD_FAST                0 (text)
            4958 CALL_FUNCTION            1

2640        4960 LOAD_CONST             171 (<code object <listcomp> at 0x000002A98128A550, file "D:\Thought State Register\semantic_routing\baseline.py", line 2640>)
            4962 LOAD_CONST               8 ('extract_semantic_packet.<locals>.<listcomp>')
            4964 MAKE_FUNCTION            0

2641        4966 LOAD_FAST                3 (candidates)

2640        4968 GET_ITER
            4970 CALL_FUNCTION            1

2643        4972 LOAD_DEREF               0 (operations)

2645        4974 LOAD_FAST               52 (missing_required_information)

2646        4976 LOAD_FAST               53 (contains_unverified_claims)

2647        4978 LOAD_FAST               54 (requires_current_information)

2648        4980 LOAD_FAST               49 (multiple_intents)

2644        4982 LOAD_CONST             172 (('missing_required_information', 'contains_unverified_claims', 'requires_current_information', 'multiple_intents'))
            4984 BUILD_CONST_KEY_MAP      4

2651        4986 LOAD_FAST               47 (response_length)

2652        4988 LOAD_FAST               32 (formats)

2653        4990 LOAD_FAST               36 (must)

2654        4992 LOAD_FAST               40 (must_not)

2650        4994 LOAD_CONST             173 (('response_length', 'formats', 'must', 'must_not'))
            4996 BUILD_CONST_KEY_MAP      4

2657        4998 LOAD_FAST               43 (risk_level)

2658        5000 LOAD_GLOBAL             31 (list)
            5002 LOAD_GLOBAL             49 (dict)
            5004 LOAD_METHOD             50 (fromkeys)
            5006 LOAD_FAST               44 (risk_flags)
            5008 CALL_METHOD              1
            5010 CALL_FUNCTION            1

2656        5012 LOAD_CONST             174 (('level', 'flags'))
            5014 BUILD_CONST_KEY_MAP      2

2660        5016 LOAD_CONST             175 (<code object <listcomp> at 0x000002A98128A600, file "D:\Thought State Register\semantic_routing\baseline.py", line 2660>)
            5018 LOAD_CONST               8 ('extract_semantic_packet.<locals>.<listcomp>')
            5020 MAKE_FUNCTION            0

2662        5022 LOAD_FAST                4 (evidence)

2660        5024 GET_ITER
            5026 CALL_FUNCTION            1

2664        5028 LOAD_FAST               58 (unknowns)

2665        5030 LOAD_FAST               59 (conflicts)

2666        5032 LOAD_FAST               57 (confidence)

2632        5034 LOAD_CONST             176 (('schema_version', 'request_digest', 'adapter', 'language', 'intent_candidates', 'operations', 'information_state', 'constraints', 'risk', 'evidence', 'unknowns', 'conflicts', 'confidence'))
            5036 BUILD_CONST_KEY_MAP     13

2631        5038 CALL_FUNCTION            1
            5040 RETURN_VALUE

Disassembly of <code object <listcomp> at 0x000002A981289C60, file "D:\Thought State Register\semantic_routing\baseline.py", line 2169>:
2169           0 BUILD_LIST               0
               2 LOAD_FAST                0 (.0)
         >>    4 FOR_ITER                11 (to 28)

2171           6 UNPACK_SEQUENCE          2
               8 STORE_FAST               1 (k)
              10 STORE_FAST               2 (v)

2170          12 LOAD_FAST                1 (k)
              14 LOAD_GLOBAL              0 (round)
              16 LOAD_FAST                2 (v)
              18 LOAD_CONST               0 (4)
              20 CALL_FUNCTION            2
              22 BUILD_LIST               2

2169          24 LIST_APPEND              2
              26 JUMP_ABSOLUTE            2 (to 4)
         >>   28 RETURN_VALUE

Disassembly of <code object <lambda> at 0x000002A981289D10, file "D:\Thought State Register\semantic_routing\baseline.py", line 2172>:
2172           0 LOAD_FAST                0 (kv)
               2 LOAD_CONST               1 (1)
               4 BINARY_SUBSCR
               6 UNARY_NEGATIVE
               8 RETURN_VALUE

Disassembly of <code object <setcomp> at 0x000002A981289DC0, file "D:\Thought State Register\semantic_routing\baseline.py", line 2283>:
2283           0 BUILD_SET                0
               2 LOAD_FAST                0 (.0)
         >>    4 FOR_ITER                 5 (to 16)
               6 STORE_FAST               1 (candidate)
               8 LOAD_FAST                1 (candidate)
              10 LOAD_ATTR                0 (intent)
              12 SET_ADD                  2
              14 JUMP_ABSOLUTE            2 (to 4)
         >>   16 RETURN_VALUE

Disassembly of <code object <listcomp> at 0x000002A981289E70, file "D:\Thought State Register\semantic_routing\baseline.py", line 2377>:
2377           0 BUILD_LIST               0
               2 LOAD_FAST                0 (.0)
         >>    4 FOR_ITER                 8 (to 22)
               6 STORE_FAST               1 (format_name)
               8 LOAD_FAST                1 (format_name)
              10 LOAD_CONST               0 ('table')
              12 COMPARE_OP               3 (!=)
              14 POP_JUMP_IF_FALSE        2 (to 4)
              16 LOAD_FAST                1 (format_name)
              18 LIST_APPEND              2
              20 JUMP_ABSOLUTE            2 (to 4)
         >>   22 RETURN_VALUE

Disassembly of <code object <listcomp> at 0x000002A981289F20, file "D:\Thought State Register\semantic_routing\baseline.py", line 2409>:
2409           0 BUILD_LIST               0
               2 LOAD_FAST                0 (.0)
         >>    4 FOR_ITER                 8 (to 22)
               6 STORE_FAST               1 (constraint)
               8 LOAD_FAST                1 (constraint)
              10 LOAD_CONST               0 ('ask_first')
              12 COMPARE_OP               3 (!=)
              14 POP_JUMP_IF_FALSE        2 (to 4)
              16 LOAD_FAST                1 (constraint)
              18 LIST_APPEND              2
              20 JUMP_ABSOLUTE            2 (to 4)
         >>   22 RETURN_VALUE

Disassembly of <code object <listcomp> at 0x000002A981289FD0, file "D:\Thought State Register\semantic_routing\baseline.py", line 2411>:
2411           0 BUILD_LIST               0
               2 LOAD_FAST                0 (.0)
         >>    4 FOR_ITER                 8 (to 22)
               6 STORE_FAST               1 (constraint)
               8 LOAD_FAST                1 (constraint)
              10 LOAD_CONST               0 ('ask_first')
              12 COMPARE_OP               3 (!=)
              14 POP_JUMP_IF_FALSE        2 (to 4)
              16 LOAD_FAST                1 (constraint)
              18 LIST_APPEND              2
              20 JUMP_ABSOLUTE            2 (to 4)
         >>   22 RETURN_VALUE

Disassembly of <code object <listcomp> at 0x000002A98128A080, file "D:\Thought State Register\semantic_routing\baseline.py", line 2439>:
2439           0 BUILD_LIST               0
               2 LOAD_FAST                0 (.0)
         >>    4 FOR_ITER                 8 (to 22)
               6 STORE_FAST               1 (constraint)
               8 LOAD_FAST                1 (constraint)
              10 LOAD_DEREF               0 (suppressed_constraints)
              12 CONTAINS_OP              1
              14 POP_JUMP_IF_FALSE        2 (to 4)
              16 LOAD_FAST                1 (constraint)
              18 LIST_APPEND              2
              20 JUMP_ABSOLUTE            2 (to 4)
         >>   22 RETURN_VALUE

Disassembly of <code object <listcomp> at 0x000002A98128A130, file "D:\Thought State Register\semantic_routing\baseline.py", line 2467>:
2467           0 BUILD_LIST               0
               2 LOAD_FAST                0 (.0)
         >>    4 FOR_ITER                 8 (to 22)
               6 STORE_FAST               1 (operation)
               8 LOAD_FAST                1 (operation)
              10 LOAD_CONST               0 ('search')
              12 COMPARE_OP               3 (!=)
              14 POP_JUMP_IF_FALSE        2 (to 4)
              16 LOAD_FAST                1 (operation)
              18 LIST_APPEND              2
              20 JUMP_ABSOLUTE            2 (to 4)
         >>   22 RETURN_VALUE

Disassembly of <code object <listcomp> at 0x000002A98128A1E0, file "D:\Thought State Register\semantic_routing\baseline.py", line 2469>:
2469           0 BUILD_LIST               0
               2 LOAD_FAST                0 (.0)
         >>    4 FOR_ITER                 8 (to 22)
               6 STORE_FAST               1 (format_name)
               8 LOAD_FAST                1 (format_name)
              10 LOAD_CONST               0 ('table')
              12 COMPARE_OP               3 (!=)
              14 POP_JUMP_IF_FALSE        2 (to 4)
              16 LOAD_FAST                1 (format_name)
              18 LIST_APPEND              2
              20 JUMP_ABSOLUTE            2 (to 4)
         >>   22 RETURN_VALUE

Disassembly of <code object <genexpr> at 0x000002A98128A290, file "D:\Thought State Register\semantic_routing\baseline.py", line 2590>:
               0 GEN_START                0

2590           2 LOAD_FAST                0 (.0)
         >>    4 FOR_ITER                 7 (to 20)
               6 STORE_FAST               1 (operation)
               8 LOAD_FAST                1 (operation)
              10 LOAD_DEREF               0 (operations)
              12 CONTAINS_OP              0
              14 YIELD_VALUE
              16 POP_TOP
              18 JUMP_ABSOLUTE            2 (to 4)
         >>   20 LOAD_CONST               0 (None)
              22 RETURN_VALUE

Disassembly of <code object <listcomp> at 0x000002A98128A340, file "D:\Thought State Register\semantic_routing\baseline.py", line 2593>:
2593           0 BUILD_LIST               0
               2 LOAD_FAST                0 (.0)
         >>    4 FOR_ITER                 8 (to 22)
               6 STORE_FAST               1 (operation)
               8 LOAD_FAST                1 (operation)
              10 LOAD_CONST               0 ('search')
              12 COMPARE_OP               3 (!=)
              14 POP_JUMP_IF_FALSE        2 (to 4)
              16 LOAD_FAST                1 (operation)
              18 LIST_APPEND              2
              20 JUMP_ABSOLUTE            2 (to 4)
         >>   22 RETURN_VALUE

Disassembly of <code object <genexpr> at 0x000002A98128A3F0, file "D:\Thought State Register\semantic_routing\baseline.py", line 2596>:
               0 GEN_START                0

2596           2 LOAD_FAST                0 (.0)
         >>    4 FOR_ITER                 7 (to 20)

2598           6 STORE_FAST               1 (operation)

2597           8 LOAD_FAST                1 (operation)
              10 LOAD_CONST               0 (frozenset({'explain', 'compare', 'summarize', 'build'}))
              12 CONTAINS_OP              0

2596          14 YIELD_VALUE
              16 POP_TOP
              18 JUMP_ABSOLUTE            2 (to 4)
         >>   20 LOAD_CONST               1 (None)
              22 RETURN_VALUE

Disassembly of <code object <lambda> at 0x000002A98128A4A0, file "D:\Thought State Register\semantic_routing\baseline.py", line 2624>:
2624           0 LOAD_FAST                0 (item)
               2 LOAD_CONST               1 (1)
               4 BINARY_SUBSCR
               6 LOAD_FAST                0 (item)
               8 LOAD_CONST               2 (2)
              10 BINARY_SUBSCR
              12 LOAD_FAST                0 (item)
              14 LOAD_CONST               3 (0)
              16 BINARY_SUBSCR
              18 BUILD_TUPLE              3
              20 RETURN_VALUE

Disassembly of <code object <listcomp> at 0x000002A98128A550, file "D:\Thought State Register\semantic_routing\baseline.py", line 2640>:
2640           0 BUILD_LIST               0
               2 LOAD_FAST                0 (.0)
         >>    4 FOR_ITER                 6 (to 18)

2641           6 STORE_FAST               1 (candidate)
               8 LOAD_FAST                1 (candidate)
              10 LOAD_METHOD              0 (as_dict)
              12 CALL_METHOD              0

2640          14 LIST_APPEND              2
              16 JUMP_ABSOLUTE            2 (to 4)
         >>   18 RETURN_VALUE

Disassembly of <code object <listcomp> at 0x000002A98128A600, file "D:\Thought State Register\semantic_routing\baseline.py", line 2660>:
2660           0 BUILD_LIST               0
               2 LOAD_FAST                0 (.0)
         >>    4 FOR_ITER                11 (to 28)

2662           6 UNPACK_SEQUENCE          3
               8 STORE_FAST               1 (signal)
              10 STORE_FAST               2 (start)
              12 STORE_FAST               3 (end)

2661          14 LOAD_FAST                1 (signal)
              16 LOAD_FAST                2 (start)
              18 LOAD_FAST                3 (end)
              20 LOAD_CONST               0 (('signal', 'start', 'end'))
              22 BUILD_CONST_KEY_MAP      3

2660          24 LIST_APPEND              2
              26 JUMP_ABSOLUTE            2 (to 4)
         >>   28 RETURN_VALUE


